Workbook

Sheet Como usar
B1: COMO USAR – Escola Modelo (dados fictícios)
B2: Células em bege = você preenche. Células brancas = calculam sozinhas (não apague). Campos com ▼ = escolha da lista.
B4: 1. ANTES DE COMEÇAR (uma vez só)
B5: 1 | C5: Aba Config: preencha o dia de vencimento do boleto, multa, juros, tarifa por boleto e o saldo inicial do caixa.
B6: 2 | C6: Aba Config: preencha o valor da mensalidade de cada turma e o valor do Judô e do Balé.
B7: 3 | C7: Aba Alunos: confira a turma de cada aluno, marque Judô/Balé, desconto (se houver) e preencha o CPF do responsável.
B8: 4 | C8: Aba Despesas Fixas: cadastre as contas que se repetem todo mês (aluguel, salários, internet, contador...).
B9: 5 | C9: Não apague nada nas colunas brancas – são elas que fazem a planilha calcular sozinha.
B11: 2. NO DIA A DIA
B12: 1 | C12: Boleto pago: na aba Boletos, coloque a data do pagamento (e o nº do boleto da plataforma de cobrança, se quiser). Valor pago só se for diferente.
B13: 2 | C13: Conta fixa paga: na aba Contas Fixas, coloque a data do pagamento.
B14: 3 | C14: Outra despesa (conserto, material, evento...): lance na aba Despesas com vencimento, categoria, tipo e valor. Quando pagar, coloque a data.
B15: 4 | C15: Dinheiro que não veio de boleto (matrícula, uniforme, festa...): lance na aba Outras Receitas.
B16: 5 | C16: Boleto cancelado na plataforma de cobrança: marque Sim em Cancelado? na aba Boletos.
B18: 3. ACOMPANHAMENTO
B19: 1 | C19: Aba Resumo: receitas, despesas, saldo de cada mês e indicadores. O aviso no topo diz se falta algo ou se está tudo em dia.
B20: 2 | C20: Aba Pendências: lista sozinha os boletos vencidos (com multa e juros) e os cadastros sem CPF.
B21: 3 | C21: Status com cores: verde = pago, vermelho = vencido/atrasado, amarelo = a vencer.
B23: 4. ALUNOS
B24: 1 | C24: Aluno novo: escreva o nome na primeira linha vazia da aba Alunos e escolha a turma – os 12 boletos são criados sozinhos.
B25: 2 | C25: A aba Alunos A-Z mostra todos em ordem alfabética, atualizando sozinha. Não classifique (A→Z) a aba Alunos: isso desalinha os pagamentos da aba Boletos.
B26: 3 | C26: Mudou de turma: troque a turma na coluna ao lado do nome – mensalidade e boletos se atualizam.
B27: 4 | C27: Aluno saiu: mude a Situação para Inativo – ele para de gerar boletos.
B28: 5 | C28: Entrou ou vai sair no meio do ano: escolha o Mês de entrada / Mês de saída – os boletos só são gerados nos meses certos.
B30: 5. VIRADA DE ANO
B31: 1 | C31: Faça uma cópia do arquivo e renomeie com o novo ano (ex.: 2028). Guarde o arquivo antigo como histórico.
B32: 2 | C32: Config: troque o ano, ajuste as mensalidades e coloque como saldo inicial o saldo de dezembro do ano anterior.
B33: 3 | C33: Alunos: suba as turmas, marque Inativo quem saiu e cadastre os novos.
B34: 4 | C34: Apague só as colunas em bege das abas Boletos e Contas Fixas, e os lançamentos de Despesas e Outras Receitas.
B36: DICAS
B37: 1 | C37: Atalho para a data de hoje no Excel: Ctrl + ; | No Google Planilhas, clique 2x na célula de data para abrir o calendário.
B38: 2 | C38: Use os filtros no cabeçalho das abas Boletos e Despesas para ver só um aluno, só um mês ou só os vencidos.
B39: 3 | C39: As células de fórmula estão protegidas contra apagamento acidental (sem senha). Para liberar: Revisão → Desproteger Planilha.

Sheet Resumo
A1: ="Resumo financeiro – "&Config!B3&" – "&Config!B4
A2: =IF(Config!B5="","⚠ Preencha o dia de vencimento na aba Config",IF(COUNTBLANK(Config!B14:B17)>0,"⚠ Preencha o valor das mensalidades na aba Config",IF(COUNTIF(Boletos!J3:J3602,"Vencido")>0,"⚠ Existem "&COUNTIF(Boletos!J3:J3602,"Vencido")&" boletos vencidos – veja a aba Pendências",IF(COUNTIF('Contas Fixas'!I3:I362,"Atrasada")>0,"⚠ Existem "&COUNTIF('Contas Fixas'!I3:I362,"Atrasada")&" contas fixas atrasadas – veja a aba Contas Fixas","✓ Tudo em dia"))))
A3: Mês | B3: Boletos previstos | C3: Boletos recebidos | D3: Outras receitas | E3: Total receitas | F3: Despesas pagas | G3: Tarifas de boleto | H3: Resultado | I3: Saldo acumulado
A4: Jan | B4: =SUMIFS(Boletos!$E$3:$E$3602,Boletos!$C$3:$C$3602,A4,Boletos!$J$3:$J$3602,"<>Cancelado") | C4: =SUMIFS(Boletos!$N$3:$N$3602,Boletos!$M$3:$M$3602,1) | D4: =SUMIFS('Outras Receitas'!$D$2:$D$500,'Outras Receitas'!$E$2:$E$500,1) | E4: =C4+D4 | F4: =SUMIFS(Despesas!$F$2:$F$1000,Despesas!$I$2:$I$1000,1)+SUMIFS('Contas Fixas'!$K$3:$K$362,'Contas Fixas'!$J$3:$J$362,1) | G4: =COUNTIFS(Boletos!$M$3:$M$3602,1)*Config!$B$8 | H4: =E4-F4-G4 | I4: =Config!$B$9+H4
A5: Fev | B5: =SUMIFS(Boletos!$E$3:$E$3602,Boletos!$C$3:$C$3602,A5,Boletos!$J$3:$J$3602,"<>Cancelado") | C5: =SUMIFS(Boletos!$N$3:$N$3602,Boletos!$M$3:$M$3602,2) | D5: =SUMIFS('Outras Receitas'!$D$2:$D$500,'Outras Receitas'!$E$2:$E$500,2) | E5: =C5+D5 | F5: =SUMIFS(Despesas!$F$2:$F$1000,Despesas!$I$2:$I$1000,2)+SUMIFS('Contas Fixas'!$K$3:$K$362,'Contas Fixas'!$J$3:$J$362,2) | G5: =COUNTIFS(Boletos!$M$3:$M$3602,2)*Config!$B$8 | H5: =E5-F5-G5 | I5: =I4+H5
A6: Mar | B6: =SUMIFS(Boletos!$E$3:$E$3602,Boletos!$C$3:$C$3602,A6,Boletos!$J$3:$J$3602,"<>Cancelado") | C6: =SUMIFS(Boletos!$N$3:$N$3602,Boletos!$M$3:$M$3602,3) | D6: =SUMIFS('Outras Receitas'!$D$2:$D$500,'Outras Receitas'!$E$2:$E$500,3) | E6: =C6+D6 | F6: =SUMIFS(Despesas!$F$2:$F$1000,Despesas!$I$2:$I$1000,3)+SUMIFS('Contas Fixas'!$K$3:$K$362,'Contas Fixas'!$J$3:$J$362,3) | G6: =COUNTIFS(Boletos!$M$3:$M$3602,3)*Config!$B$8 | H6: =E6-F6-G6 | I6: =I5+H6
A7: Abr | B7: =SUMIFS(Boletos!$E$3:$E$3602,Boletos!$C$3:$C$3602,A7,Boletos!$J$3:$J$3602,"<>Cancelado") | C7: =SUMIFS(Boletos!$N$3:$N$3602,Boletos!$M$3:$M$3602,4) | D7: =SUMIFS('Outras Receitas'!$D$2:$D$500,'Outras Receitas'!$E$2:$E$500,4) | E7: =C7+D7 | F7: =SUMIFS(Despesas!$F$2:$F$1000,Despesas!$I$2:$I$1000,4)+SUMIFS('Contas Fixas'!$K$3:$K$362,'Contas Fixas'!$J$3:$J$362,4) | G7: =COUNTIFS(Boletos!$M$3:$M$3602,4)*Config!$B$8 | H7: =E7-F7-G7 | I7: =I6+H7
A8: Mai | B8: =SUMIFS(Boletos!$E$3:$E$3602,Boletos!$C$3:$C$3602,A8,Boletos!$J$3:$J$3602,"<>Cancelado") | C8: =SUMIFS(Boletos!$N$3:$N$3602,Boletos!$M$3:$M$3602,5) | D8: =SUMIFS('Outras Receitas'!$D$2:$D$500,'Outras Receitas'!$E$2:$E$500,5) | E8: =C8+D8 | F8: =SUMIFS(Despesas!$F$2:$F$1000,Despesas!$I$2:$I$1000,5)+SUMIFS('Contas Fixas'!$K$3:$K$362,'Contas Fixas'!$J$3:$J$362,5) | G8: =COUNTIFS(Boletos!$M$3:$M$3602,5)*Config!$B$8 | H8: =E8-F8-G8 | I8: =I7+H8
A9: Jun | B9: =SUMIFS(Boletos!$E$3:$E$3602,Boletos!$C$3:$C$3602,A9,Boletos!$J$3:$J$3602,"<>Cancelado") | C9: =SUMIFS(Boletos!$N$3:$N$3602,Boletos!$M$3:$M$3602,6) | D9: =SUMIFS('Outras Receitas'!$D$2:$D$500,'Outras Receitas'!$E$2:$E$500,6) | E9: =C9+D9 | F9: =SUMIFS(Despesas!$F$2:$F$1000,Despesas!$I$2:$I$1000,6)+SUMIFS('Contas Fixas'!$K$3:$K$362,'Contas Fixas'!$J$3:$J$362,6) | G9: =COUNTIFS(Boletos!$M$3:$M$3602,6)*Config!$B$8 | H9: =E9-F9-G9 | I9: =I8+H9
A10: Jul | B10: =SUMIFS(Boletos!$E$3:$E$3602,Boletos!$C$3:$C$3602,A10,Boletos!$J$3:$J$3602,"<>Cancelado") | C10: =SUMIFS(Boletos!$N$3:$N$3602,Boletos!$M$3:$M$3602,7) | D10: =SUMIFS('Outras Receitas'!$D$2:$D$500,'Outras Receitas'!$E$2:$E$500,7) | E10: =C10+D10 | F10: =SUMIFS(Despesas!$F$2:$F$1000,Despesas!$I$2:$I$1000,7)+SUMIFS('Contas Fixas'!$K$3:$K$362,'Contas Fixas'!$J$3:$J$362,7) | G10: =COUNTIFS(Boletos!$M$3:$M$3602,7)*Config!$B$8 | H10: =E10-F10-G10 | I10: =I9+H10
A11: Ago | B11: =SUMIFS(Boletos!$E$3:$E$3602,Boletos!$C$3:$C$3602,A11,Boletos!$J$3:$J$3602,"<>Cancelado") | C11: =SUMIFS(Boletos!$N$3:$N$3602,Boletos!$M$3:$M$3602,8) | D11: =SUMIFS('Outras Receitas'!$D$2:$D$500,'Outras Receitas'!$E$2:$E$500,8) | E11: =C11+D11 | F11: =SUMIFS(Despesas!$F$2:$F$1000,Despesas!$I$2:$I$1000,8)+SUMIFS('Contas Fixas'!$K$3:$K$362,'Contas Fixas'!$J$3:$J$362,8) | G11: =COUNTIFS(Boletos!$M$3:$M$3602,8)*Config!$B$8 | H11: =E11-F11-G11 | I11: =I10+H11
A12: Set | B12: =SUMIFS(Boletos!$E$3:$E$3602,Boletos!$C$3:$C$3602,A12,Boletos!$J$3:$J$3602,"<>Cancelado") | C12: =SUMIFS(Boletos!$N$3:$N$3602,Boletos!$M$3:$M$3602,9) | D12: =SUMIFS('Outras Receitas'!$D$2:$D$500,'Outras Receitas'!$E$2:$E$500,9) | E12: =C12+D12 | F12: =SUMIFS(Despesas!$F$2:$F$1000,Despesas!$I$2:$I$1000,9)+SUMIFS('Contas Fixas'!$K$3:$K$362,'Contas Fixas'!$J$3:$J$362,9) | G12: =COUNTIFS(Boletos!$M$3:$M$3602,9)*Config!$B$8 | H12: =E12-F12-G12 | I12: =I11+H12
A13: Out | B13: =SUMIFS(Boletos!$E$3:$E$3602,Boletos!$C$3:$C$3602,A13,Boletos!$J$3:$J$3602,"<>Cancelado") | C13: =SUMIFS(Boletos!$N$3:$N$3602,Boletos!$M$3:$M$3602,10) | D13: =SUMIFS('Outras Receitas'!$D$2:$D$500,'Outras Receitas'!$E$2:$E$500,10) | E13: =C13+D13 | F13: =SUMIFS(Despesas!$F$2:$F$1000,Despesas!$I$2:$I$1000,10)+SUMIFS('Contas Fixas'!$K$3:$K$362,'Contas Fixas'!$J$3:$J$362,10) | G13: =COUNTIFS(Boletos!$M$3:$M$3602,10)*Config!$B$8 | H13: =E13-F13-G13 | I13: =I12+H13
A14: Nov | B14: =SUMIFS(Boletos!$E$3:$E$3602,Boletos!$C$3:$C$3602,A14,Boletos!$J$3:$J$3602,"<>Cancelado") | C14: =SUMIFS(Boletos!$N$3:$N$3602,Boletos!$M$3:$M$3602,11) | D14: =SUMIFS('Outras Receitas'!$D$2:$D$500,'Outras Receitas'!$E$2:$E$500,11) | E14: =C14+D14 | F14: =SUMIFS(Despesas!$F$2:$F$1000,Despesas!$I$2:$I$1000,11)+SUMIFS('Contas Fixas'!$K$3:$K$362,'Contas Fixas'!$J$3:$J$362,11) | G14: =COUNTIFS(Boletos!$M$3:$M$3602,11)*Config!$B$8 | H14: =E14-F14-G14 | I14: =I13+H14
A15: Dez | B15: =SUMIFS(Boletos!$E$3:$E$3602,Boletos!$C$3:$C$3602,A15,Boletos!$J$3:$J$3602,"<>Cancelado") | C15: =SUMIFS(Boletos!$N$3:$N$3602,Boletos!$M$3:$M$3602,12) | D15: =SUMIFS('Outras Receitas'!$D$2:$D$500,'Outras Receitas'!$E$2:$E$500,12) | E15: =C15+D15 | F15: =SUMIFS(Despesas!$F$2:$F$1000,Despesas!$I$2:$I$1000,12)+SUMIFS('Contas Fixas'!$K$3:$K$362,'Contas Fixas'!$J$3:$J$362,12) | G15: =COUNTIFS(Boletos!$M$3:$M$3602,12)*Config!$B$8 | H15: =E15-F15-G15 | I15: =I14+H15
A16: TOTAL | B16: =SUM(B4:B15) | C16: =SUM(C4:C15) | D16: =SUM(D4:D15) | E16: =SUM(E4:E15) | F16: =SUM(F4:F15) | G16: =SUM(G4:G15) | H16: =SUM(H4:H15)
A18: ="INDICADORES "&Config!B4
A19: Alunos ativos | B19: =COUNTIF(Alunos!L:L,"Ativo")+COUNTIF(Alunos!L:L,"Bolsista")
A20: Alunos no Maternal 2 | B20: =COUNTIFS(Alunos!B:B,"Maternal 2",Alunos!L:L,"<>Inativo")
A21: Alunos no Maternal 3 | B21: =COUNTIFS(Alunos!B:B,"Maternal 3",Alunos!L:L,"<>Inativo")
A22: Alunos no 1º Período | B22: =COUNTIFS(Alunos!B:B,"1º Período",Alunos!L:L,"<>Inativo")
A23: Alunos no 2º Período | B23: =COUNTIFS(Alunos!B:B,"2º Período",Alunos!L:L,"<>Inativo")
A24: Alunos no Judô | B24: =COUNTIF(Alunos!G:G,"Sim")
A25: Alunos no Balé | B25: =COUNTIF(Alunos!H:H,"Sim")
A26: Receita prevista por mês | B26: =SUM(Alunos!K2:K301)
A27: Boletos pagos | B27: =COUNTIF(Boletos!J3:J3602,"Pago")
A28: Boletos vencidos | B28: =COUNTIF(Boletos!J3:J3602,"Vencido")
A29: Valor vencido (atualizado) | B29: =SUMIFS(Boletos!L3:L3602,Boletos!J3:J3602,"Vencido")
A30: Inadimplência (% do vencido) | B30: =IFERROR(SUMIFS(Boletos!E3:E3602,Boletos!J3:J3602,"Vencido")/(SUMIFS(Boletos!E3:E3602,Boletos!J3:J3602,"Vencido")+SUMIFS(Boletos!E3:E3602,Boletos!J3:J3602,"Pago")),0)
A31: Despesas atrasadas | B31: =SUMIFS(Despesas!F:F,Despesas!H:H,"Atrasada")+SUMIFS('Contas Fixas'!F3:F362,'Contas Fixas'!I3:I362,"Atrasada")
A32: Despesas fixas pagas no ano | B32: =SUMIFS(Despesas!F:F,Despesas!D:D,"Fixa",Despesas!H:H,"Pago")+SUM('Contas Fixas'!K3:K362)
A33: Despesas variáveis pagas no ano | B33: =SUMIFS(Despesas!F:F,Despesas!D:D,"Variável",Despesas!H:H,"Pago")
A34: Margem do ano | B34: =IFERROR(H16/E16,0)

Sheet Pendências
A1: PENDÊNCIAS – atualiza sozinha
A3: Boletos vencidos | H3: Total vencido | J3: Cadastros sem CPF do responsável
A4: Aluno | B4: Responsável | C4: Mês ref. | D4: Vencimento | E4: Dias de atraso | F4: Valor atualizado | H4: =SUMIFS(Boletos!L3:L3602,Boletos!J3:J3602,"Vencido") | J4: Aluno | K4: Responsável
A5: {=IFERROR(INDEX(Boletos!$A:$A,SMALL(Boletos!$O$3:$O$3602,1)),"")} | B5: {=IFERROR(INDEX(Boletos!$B:$B,SMALL(Boletos!$O$3:$O$3602,1)),"")} | C5: {=IFERROR(INDEX(Boletos!$C:$C,SMALL(Boletos!$O$3:$O$3602,1)),"")} | D5: {=IFERROR(INDEX(Boletos!$D:$D,SMALL(Boletos!$O$3:$O$3602,1)),"")} | E5: {=IFERROR(INDEX(Boletos!$K:$K,SMALL(Boletos!$O$3:$O$3602,1)),"")} | F5: {=IFERROR(INDEX(Boletos!$L:$L,SMALL(Boletos!$O$3:$O$3602,1)),"")} | J5: {=IFERROR(INDEX(Alunos!$A:$A,SMALL(Alunos!$O$2:$O$301,1)),"")} | K5: {=IFERROR(INDEX(Alunos!$C:$C,SMALL(Alunos!$O$2:$O$301,1)),"")}
A6: {=IFERROR(INDEX(Boletos!$A:$A,SMALL(Boletos!$O$3:$O$3602,2)),"")} | B6: {=IFERROR(INDEX(Boletos!$B:$B,SMALL(Boletos!$O$3:$O$3602,2)),"")} | C6: {=IFERROR(INDEX(Boletos!$C:$C,SMALL(Boletos!$O$3:$O$3602,2)),"")} | D6: {=IFERROR(INDEX(Boletos!$D:$D,SMALL(Boletos!$O$3:$O$3602,2)),"")} | E6: {=IFERROR(INDEX(Boletos!$K:$K,SMALL(Boletos!$O$3:$O$3602,2)),"")} | F6: {=IFERROR(INDEX(Boletos!$L:$L,SMALL(Boletos!$O$3:$O$3602,2)),"")} | H6: Boletos vencidos | J6: {=IFERROR(INDEX(Alunos!$A:$A,SMALL(Alunos!$O$2:$O$301,2)),"")} | K6: {=IFERROR(INDEX(Alunos!$C:$C,SMALL(Alunos!$O$2:$O$301,2)),"")}
A7: {=IFERROR(INDEX(Boletos!$A:$A,SMALL(Boletos!$O$3:$O$3602,3)),"")} | B7: {=IFERROR(INDEX(Boletos!$B:$B,SMALL(Boletos!$O$3:$O$3602,3)),"")} | C7: {=IFERROR(INDEX(Boletos!$C:$C,SMALL(Boletos!$O$3:$O$3602,3)),"")} | D7: {=IFERROR(INDEX(Boletos!$D:$D,SMALL(Boletos!$O$3:$O$3602,3)),"")} | E7: {=IFERROR(INDEX(Boletos!$K:$K,SMALL(Boletos!$O$3:$O$3602,3)),"")} | F7: {=IFERROR(INDEX(Boletos!$L:$L,SMALL(Boletos!$O$3:$O$3602,3)),"")} | H7: =COUNTIF(Boletos!J3:J3602,"Vencido") | J7: {=IFERROR(INDEX(Alunos!$A:$A,SMALL(Alunos!$O$2:$O$301,3)),"")} | K7: {=IFERROR(INDEX(Alunos!$C:$C,SMALL(Alunos!$O$2:$O$301,3)),"")}
A8: {=IFERROR(INDEX(Boletos!$A:$A,SMALL(Boletos!$O$3:$O$3602,4)),"")} | B8: {=IFERROR(INDEX(Boletos!$B:$B,SMALL(Boletos!$O$3:$O$3602,4)),"")} | C8: {=IFERROR(INDEX(Boletos!$C:$C,SMALL(Boletos!$O$3:$O$3602,4)),"")} | D8: {=IFERROR(INDEX(Boletos!$D:$D,SMALL(Boletos!$O$3:$O$3602,4)),"")} | E8: {=IFERROR(INDEX(Boletos!$K:$K,SMALL(Boletos!$O$3:$O$3602,4)),"")} | F8: {=IFERROR(INDEX(Boletos!$L:$L,SMALL(Boletos!$O$3:$O$3602,4)),"")} | J8: {=IFERROR(INDEX(Alunos!$A:$A,SMALL(Alunos!$O$2:$O$301,4)),"")} | K8: {=IFERROR(INDEX(Alunos!$C:$C,SMALL(Alunos!$O$2:$O$301,4)),"")}
A9: {=IFERROR(INDEX(Boletos!$A:$A,SMALL(Boletos!$O$3:$O$3602,5)),"")} | B9: {=IFERROR(INDEX(Boletos!$B:$B,SMALL(Boletos!$O$3:$O$3602,5)),"")} | C9: {=IFERROR(INDEX(Boletos!$C:$C,SMALL(Boletos!$O$3:$O$3602,5)),"")} | D9: {=IFERROR(INDEX(Boletos!$D:$D,SMALL(Boletos!$O$3:$O$3602,5)),"")} | E9: {=IFERROR(INDEX(Boletos!$K:$K,SMALL(Boletos!$O$3:$O$3602,5)),"")} | F9: {=IFERROR(INDEX(Boletos!$L:$L,SMALL(Boletos!$O$3:$O$3602,5)),"")} | H9: Contas fixas atrasadas | J9: {=IFERROR(INDEX(Alunos!$A:$A,SMALL(Alunos!$O$2:$O$301,5)),"")} | K9: {=IFERROR(INDEX(Alunos!$C:$C,SMALL(Alunos!$O$2:$O$301,5)),"")}
A10: {=IFERROR(INDEX(Boletos!$A:$A,SMALL(Boletos!$O$3:$O$3602,6)),"")} | B10: {=IFERROR(INDEX(Boletos!$B:$B,SMALL(Boletos!$O$3:$O$3602,6)),"")} | C10: {=IFERROR(INDEX(Boletos!$C:$C,SMALL(Boletos!$O$3:$O$3602,6)),"")} | D10: {=IFERROR(INDEX(Boletos!$D:$D,SMALL(Boletos!$O$3:$O$3602,6)),"")} | E10: {=IFERROR(INDEX(Boletos!$K:$K,SMALL(Boletos!$O$3:$O$3602,6)),"")} | F10: {=IFERROR(INDEX(Boletos!$L:$L,SMALL(Boletos!$O$3:$O$3602,6)),"")} | H10: =COUNTIF('Contas Fixas'!I3:I362,"Atrasada") | J10: {=IFERROR(INDEX(Alunos!$A:$A,SMALL(Alunos!$O$2:$O$301,6)),"")} | K10: {=IFERROR(INDEX(Alunos!$C:$C,SMALL(Alunos!$O$2:$O$301,6)),"")}
A11: {=IFERROR(INDEX(Boletos!$A:$A,SMALL(Boletos!$O$3:$O$3602,7)),"")} | B11: {=IFERROR(INDEX(Boletos!$B:$B,SMALL(Boletos!$O$3:$O$3602,7)),"")} | C11: {=IFERROR(INDEX(Boletos!$C:$C,SMALL(Boletos!$O$3:$O$3602,7)),"")} | D11: {=IFERROR(INDEX(Boletos!$D:$D,SMALL(Boletos!$O$3:$O$3602,7)),"")} | E11: {=IFERROR(INDEX(Boletos!$K:$K,SMALL(Boletos!$O$3:$O$3602,7)),"")} | F11: {=IFERROR(INDEX(Boletos!$L:$L,SMALL(Boletos!$O$3:$O$3602,7)),"")} | J11: {=IFERROR(INDEX(Alunos!$A:$A,SMALL(Alunos!$O$2:$O$301,7)),"")} | K11: {=IFERROR(INDEX(Alunos!$C:$C,SMALL(Alunos!$O$2:$O$301,7)),"")}
A12: {=IFERROR(INDEX(Boletos!$A:$A,SMALL(Boletos!$O$3:$O$3602,8)),"")} | B12: {=IFERROR(INDEX(Boletos!$B:$B,SMALL(Boletos!$O$3:$O$3602,8)),"")} | C12: {=IFERROR(INDEX(Boletos!$C:$C,SMALL(Boletos!$O$3:$O$3602,8)),"")} | D12: {=IFERROR(INDEX(Boletos!$D:$D,SMALL(Boletos!$O$3:$O$3602,8)),"")} | E12: {=IFERROR(INDEX(Boletos!$K:$K,SMALL(Boletos!$O$3:$O$3602,8)),"")} | F12: {=IFERROR(INDEX(Boletos!$L:$L,SMALL(Boletos!$O$3:$O$3602,8)),"")} | J12: {=IFERROR(INDEX(Alunos!$A:$A,SMALL(Alunos!$O$2:$O$301,8)),"")} | K12: {=IFERROR(INDEX(Alunos!$C:$C,SMALL(Alunos!$O$2:$O$301,8)),"")}
A13: {=IFERROR(INDEX(Boletos!$A:$A,SMALL(Boletos!$O$3:$O$3602,9)),"")} | B13: {=IFERROR(INDEX(Boletos!$B:$B,SMALL(Boletos!$O$3:$O$3602,9)),"")} | C13: {=IFERROR(INDEX(Boletos!$C:$C,SMALL(Boletos!$O$3:$O$3602,9)),"")} | D13: {=IFERROR(INDEX(Boletos!$D:$D,SMALL(Boletos!$O$3:$O$3602,9)),"")} | E13: {=IFERROR(INDEX(Boletos!$K:$K,SMALL(Boletos!$O$3:$O$3602,9)),"")} | F13: {=IFERROR(INDEX(Boletos!$L:$L,SMALL(Boletos!$O$3:$O$3602,9)),"")} | J13: {=IFERROR(INDEX(Alunos!$A:$A,SMALL(Alunos!$O$2:$O$301,9)),"")} | K13: {=IFERROR(INDEX(Alunos!$C:$C,SMALL(Alunos!$O$2:$O$301,9)),"")}
A14: {=IFERROR(INDEX(Boletos!$A:$A,SMALL(Boletos!$O$3:$O$3602,10)),"")} | B14: {=IFERROR(INDEX(Boletos!$B:$B,SMALL(Boletos!$O$3:$O$3602,10)),"")} | C14: {=IFERROR(INDEX(Boletos!$C:$C,SMALL(Boletos!$O$3:$O$3602,10)),"")} | D14: {=IFERROR(INDEX(Boletos!$D:$D,SMALL(Boletos!$O$3:$O$3602,10)),"")} | E14: {=IFERROR(INDEX(Boletos!$K:$K,SMALL(Boletos!$O$3:$O$3602,10)),"")} | F14: {=IFERROR(INDEX(Boletos!$L:$L,SMALL(Boletos!$O$3:$O$3602,10)),"")} | J14: {=IFERROR(INDEX(Alunos!$A:$A,SMALL(Alunos!$O$2:$O$301,10)),"")} | K14: {=IFERROR(INDEX(Alunos!$C:$C,SMALL(Alunos!$O$2:$O$301,10)),"")}
A15: {=IFERROR(INDEX(Boletos!$A:$A,SMALL(Boletos!$O$3:$O$3602,11)),"")} | B15: {=IFERROR(INDEX(Boletos!$B:$B,SMALL(Boletos!$O$3:$O$3602,11)),"")} | C15: {=IFERROR(INDEX(Boletos!$C:$C,SMALL(Boletos!$O$3:$O$3602,11)),"")} | D15: {=IFERROR(INDEX(Boletos!$D:$D,SMALL(Boletos!$O$3:$O$3602,11)),"")} | E15: {=IFERROR(INDEX(Boletos!$K:$K,SMALL(Boletos!$O$3:$O$3602,11)),"")} | F15: {=IFERROR(INDEX(Boletos!$L:$L,SMALL(Boletos!$O$3:$O$3602,11)),"")} | J15: {=IFERROR(INDEX(Alunos!$A:$A,SMALL(Alunos!$O$2:$O$301,11)),"")} | K15: {=IFERROR(INDEX(Alunos!$C:$C,SMALL(Alunos!$O$2:$O$301,11)),"")}
A16: {=IFERROR(INDEX(Boletos!$A:$A,SMALL(Boletos!$O$3:$O$3602,12)),"")} | B16: {=IFERROR(INDEX(Boletos!$B:$B,SMALL(Boletos!$O$3:$O$3602,12)),"")} | C16: {=IFERROR(INDEX(Boletos!$C:$C,SMALL(Boletos!$O$3:$O$3602,12)),"")} | D16: {=IFERROR(INDEX(Boletos!$D:$D,SMALL(Boletos!$O$3:$O$3602,12)),"")} | E16: {=IFERROR(INDEX(Boletos!$K:$K,SMALL(Boletos!$O$3:$O$3602,12)),"")} | F16: {=IFERROR(INDEX(Boletos!$L:$L,SMALL(Boletos!$O$3:$O$3602,12)),"")} | J16: {=IFERROR(INDEX(Alunos!$A:$A,SMALL(Alunos!$O$2:$O$301,12)),"")} | K16: {=IFERROR(INDEX(Alunos!$C:$C,SMALL(Alunos!$O$2:$O$301,12)),"")}
A17: {=IFERROR(INDEX(Boletos!$A:$A,SMALL(Boletos!$O$3:$O$3602,13)),"")} | B17: {=IFERROR(INDEX(Boletos!$B:$B,SMALL(Boletos!$O$3:$O$3602,13)),"")} | C17: {=IFERROR(INDEX(Boletos!$C:$C,SMALL(Boletos!$O$3:$O$3602,13)),"")} | D17: {=IFERROR(INDEX(Boletos!$D:$D,SMALL(Boletos!$O$3:$O$3602,13)),"")} | E17: {=IFERROR(INDEX(Boletos!$K:$K,SMALL(Boletos!$O$3:$O$3602,13)),"")} | F17: {=IFERROR(INDEX(Boletos!$L:$L,SMALL(Boletos!$O$3:$O$3602,13)),"")} | J17: {=IFERROR(INDEX(Alunos!$A:$A,SMALL(Alunos!$O$2:$O$301,13)),"")} | K17: {=IFERROR(INDEX(Alunos!$C:$C,SMALL(Alunos!$O$2:$O$301,13)),"")}
A18: {=IFERROR(INDEX(Boletos!$A:$A,SMALL(Boletos!$O$3:$O$3602,14)),"")} | B18: {=IFERROR(INDEX(Boletos!$B:$B,SMALL(Boletos!$O$3:$O$3602,14)),"")} | C18: {=IFERROR(INDEX(Boletos!$C:$C,SMALL(Boletos!$O$3:$O$3602,14)),"")} | D18: {=IFERROR(INDEX(Boletos!$D:$D,SMALL(Boletos!$O$3:$O$3602,14)),"")} | E18: {=IFERROR(INDEX(Boletos!$K:$K,SMALL(Boletos!$O$3:$O$3602,14)),"")} | F18: {=IFERROR(INDEX(Boletos!$L:$L,SMALL(Boletos!$O$3:$O$3602,14)),"")} | J18: {=IFERROR(INDEX(Alunos!$A:$A,SMALL(Alunos!$O$2:$O$301,14)),"")} | K18: {=IFERROR(INDEX(Alunos!$C:$C,SMALL(Alunos!$O$2:$O$301,14)),"")}
A19: {=IFERROR(INDEX(Boletos!$A:$A,SMALL(Boletos!$O$3:$O$3602,15)),"")} | B19: {=IFERROR(INDEX(Boletos!$B:$B,SMALL(Boletos!$O$3:$O$3602,15)),"")} | C19: {=IFERROR(INDEX(Boletos!$C:$C,SMALL(Boletos!$O$3:$O$3602,15)),"")} | D19: {=IFERROR(INDEX(Boletos!$D:$D,SMALL(Boletos!$O$3:$O$3602,15)),"")} | E19: {=IFERROR(INDEX(Boletos!$K:$K,SMALL(Boletos!$O$3:$O$3602,15)),"")} | F19: {=IFERROR(INDEX(Boletos!$L:$L,SMALL(Boletos!$O$3:$O$3602,15)),"")} | J19: {=IFERROR(INDEX(Alunos!$A:$A,SMALL(Alunos!$O$2:$O$301,15)),"")} | K19: {=IFERROR(INDEX(Alunos!$C:$C,SMALL(Alunos!$O$2:$O$301,15)),"")}
A20: {=IFERROR(INDEX(Boletos!$A:$A,SMALL(Boletos!$O$3:$O$3602,16)),"")} | B20: {=IFERROR(INDEX(Boletos!$B:$B,SMALL(Boletos!$O$3:$O$3602,16)),"")} | C20: {=IFERROR(INDEX(Boletos!$C:$C,SMALL(Boletos!$O$3:$O$3602,16)),"")} | D20: {=IFERROR(INDEX(Boletos!$D:$D,SMALL(Boletos!$O$3:$O$3602,16)),"")} | E20: {=IFERROR(INDEX(Boletos!$K:$K,SMALL(Boletos!$O$3:$O$3602,16)),"")} | F20: {=IFERROR(INDEX(Boletos!$L:$L,SMALL(Boletos!$O$3:$O$3602,16)),"")} | J20: {=IFERROR(INDEX(Alunos!$A:$A,SMALL(Alunos!$O$2:$O$301,16)),"")} | K20: {=IFERROR(INDEX(Alunos!$C:$C,SMALL(Alunos!$O$2:$O$301,16)),"")}
A21: {=IFERROR(INDEX(Boletos!$A:$A,SMALL(Boletos!$O$3:$O$3602,17)),"")} | B21: {=IFERROR(INDEX(Boletos!$B:$B,SMALL(Boletos!$O$3:$O$3602,17)),"")} | C21: {=IFERROR(INDEX(Boletos!$C:$C,SMALL(Boletos!$O$3:$O$3602,17)),"")} | D21: {=IFERROR(INDEX(Boletos!$D:$D,SMALL(Boletos!$O$3:$O$3602,17)),"")} | E21: {=IFERROR(INDEX(Boletos!$K:$K,SMALL(Boletos!$O$3:$O$3602,17)),"")} | F21: {=IFERROR(INDEX(Boletos!$L:$L,SMALL(Boletos!$O$3:$O$3602,17)),"")} | J21: {=IFERROR(INDEX(Alunos!$A:$A,SMALL(Alunos!$O$2:$O$301,17)),"")} | K21: {=IFERROR(INDEX(Alunos!$C:$C,SMALL(Alunos!$O$2:$O$301,17)),"")}
A22: {=IFERROR(INDEX(Boletos!$A:$A,SMALL(Boletos!$O$3:$O$3602,18)),"")} | B22: {=IFERROR(INDEX(Boletos!$B:$B,SMALL(Boletos!$O$3:$O$3602,18)),"")} | C22: {=IFERROR(INDEX(Boletos!$C:$C,SMALL(Boletos!$O$3:$O$3602,18)),"")} | D22: {=IFERROR(INDEX(Boletos!$D:$D,SMALL(Boletos!$O$3:$O$3602,18)),"")} | E22: {=IFERROR(INDEX(Boletos!$K:$K,SMALL(Boletos!$O$3:$O$3602,18)),"")} | F22: {=IFERROR(INDEX(Boletos!$L:$L,SMALL(Boletos!$O$3:$O$3602,18)),"")} | J22: {=IFERROR(INDEX(Alunos!$A:$A,SMALL(Alunos!$O$2:$O$301,18)),"")} | K22: {=IFERROR(INDEX(Alunos!$C:$C,SMALL(Alunos!$O$2:$O$301,18)),"")}
A23: {=IFERROR(INDEX(Boletos!$A:$A,SMALL(Boletos!$O$3:$O$3602,19)),"")} | B23: {=IFERROR(INDEX(Boletos!$B:$B,SMALL(Boletos!$O$3:$O$3602,19)),"")} | C23: {=IFERROR(INDEX(Boletos!$C:$C,SMALL(Boletos!$O$3:$O$3602,19)),"")} | D23: {=IFERROR(INDEX(Boletos!$D:$D,SMALL(Boletos!$O$3:$O$3602,19)),"")} | E23: {=IFERROR(INDEX(Boletos!$K:$K,SMALL(Boletos!$O$3:$O$3602,19)),"")} | F23: {=IFERROR(INDEX(Boletos!$L:$L,SMALL(Boletos!$O$3:$O$3602,19)),"")} | J23: {=IFERROR(INDEX(Alunos!$A:$A,SMALL(Alunos!$O$2:$O$301,19)),"")} | K23: {=IFERROR(INDEX(Alunos!$C:$C,SMALL(Alunos!$O$2:$O$301,19)),"")}
A24: {=IFERROR(INDEX(Boletos!$A:$A,SMALL(Boletos!$O$3:$O$3602,20)),"")} | B24: {=IFERROR(INDEX(Boletos!$B:$B,SMALL(Boletos!$O$3:$O$3602,20)),"")} | C24: {=IFERROR(INDEX(Boletos!$C:$C,SMALL(Boletos!$O$3:$O$3602,20)),"")} | D24: {=IFERROR(INDEX(Boletos!$D:$D,SMALL(Boletos!$O$3:$O$3602,20)),"")} | E24: {=IFERROR(INDEX(Boletos!$K:$K,SMALL(Boletos!$O$3:$O$3602,20)),"")} | F24: {=IFERROR(INDEX(Boletos!$L:$L,SMALL(Boletos!$O$3:$O$3602,20)),"")} | J24: {=IFERROR(INDEX(Alunos!$A:$A,SMALL(Alunos!$O$2:$O$301,20)),"")} | K24: {=IFERROR(INDEX(Alunos!$C:$C,SMALL(Alunos!$O$2:$O$301,20)),"")}
A25: {=IFERROR(INDEX(Boletos!$A:$A,SMALL(Boletos!$O$3:$O$3602,21)),"")} | B25: {=IFERROR(INDEX(Boletos!$B:$B,SMALL(Boletos!$O$3:$O$3602,21)),"")} | C25: {=IFERROR(INDEX(Boletos!$C:$C,SMALL(Boletos!$O$3:$O$3602,21)),"")} | D25: {=IFERROR(INDEX(Boletos!$D:$D,SMALL(Boletos!$O$3:$O$3602,21)),"")} | E25: {=IFERROR(INDEX(Boletos!$K:$K,SMALL(Boletos!$O$3:$O$3602,21)),"")} | F25: {=IFERROR(INDEX(Boletos!$L:$L,SMALL(Boletos!$O$3:$O$3602,21)),"")} | J25: {=IFERROR(INDEX(Alunos!$A:$A,SMALL(Alunos!$O$2:$O$301,21)),"")} | K25: {=IFERROR(INDEX(Alunos!$C:$C,SMALL(Alunos!$O$2:$O$301,21)),"")}
A26: {=IFERROR(INDEX(Boletos!$A:$A,SMALL(Boletos!$O$3:$O$3602,22)),"")} | B26: {=IFERROR(INDEX(Boletos!$B:$B,SMALL(Boletos!$O$3:$O$3602,22)),"")} | C26: {=IFERROR(INDEX(Boletos!$C:$C,SMALL(Boletos!$O$3:$O$3602,22)),"")} | D26: {=IFERROR(INDEX(Boletos!$D:$D,SMALL(Boletos!$O$3:$O$3602,22)),"")} | E26: {=IFERROR(INDEX(Boletos!$K:$K,SMALL(Boletos!$O$3:$O$3602,22)),"")} | F26: {=IFERROR(INDEX(Boletos!$L:$L,SMALL(Boletos!$O$3:$O$3602,22)),"")} | J26: {=IFERROR(INDEX(Alunos!$A:$A,SMALL(Alunos!$O$2:$O$301,22)),"")} | K26: {=IFERROR(INDEX(Alunos!$C:$C,SMALL(Alunos!$O$2:$O$301,22)),"")}
A27: {=IFERROR(INDEX(Boletos!$A:$A,SMALL(Boletos!$O$3:$O$3602,23)),"")} | B27: {=IFERROR(INDEX(Boletos!$B:$B,SMALL(Boletos!$O$3:$O$3602,23)),"")} | C27: {=IFERROR(INDEX(Boletos!$C:$C,SMALL(Boletos!$O$3:$O$3602,23)),"")} | D27: {=IFERROR(INDEX(Boletos!$D:$D,SMALL(Boletos!$O$3:$O$3602,23)),"")} | E27: {=IFERROR(INDEX(Boletos!$K:$K,SMALL(Boletos!$O$3:$O$3602,23)),"")} | F27: {=IFERROR(INDEX(Boletos!$L:$L,SMALL(Boletos!$O$3:$O$3602,23)),"")} | J27: {=IFERROR(INDEX(Alunos!$A:$A,SMALL(Alunos!$O$2:$O$301,23)),"")} | K27: {=IFERROR(INDEX(Alunos!$C:$C,SMALL(Alunos!$O$2:$O$301,23)),"")}
A28: {=IFERROR(INDEX(Boletos!$A:$A,SMALL(Boletos!$O$3:$O$3602,24)),"")} | B28: {=IFERROR(INDEX(Boletos!$B:$B,SMALL(Boletos!$O$3:$O$3602,24)),"")} | C28: {=IFERROR(INDEX(Boletos!$C:$C,SMALL(Boletos!$O$3:$O$3602,24)),"")} | D28: {=IFERROR(INDEX(Boletos!$D:$D,SMALL(Boletos!$O$3:$O$3602,24)),"")} | E28: {=IFERROR(INDEX(Boletos!$K:$K,SMALL(Boletos!$O$3:$O$3602,24)),"")} | F28: {=IFERROR(INDEX(Boletos!$L:$L,SMALL(Boletos!$O$3:$O$3602,24)),"")} | J28: {=IFERROR(INDEX(Alunos!$A:$A,SMALL(Alunos!$O$2:$O$301,24)),"")} | K28: {=IFERROR(INDEX(Alunos!$C:$C,SMALL(Alunos!$O$2:$O$301,24)),"")}
A29: {=IFERROR(INDEX(Boletos!$A:$A,SMALL(Boletos!$O$3:$O$3602,25)),"")} | B29: {=IFERROR(INDEX(Boletos!$B:$B,SMALL(Boletos!$O$3:$O$3602,25)),"")} | C29: {=IFERROR(INDEX(Boletos!$C:$C,SMALL(Boletos!$O$3:$O$3602,25)),"")} | D29: {=IFERROR(INDEX(Boletos!$D:$D,SMALL(Boletos!$O$3:$O$3602,25)),"")} | E29: {=IFERROR(INDEX(Boletos!$K:$K,SMALL(Boletos!$O$3:$O$3602,25)),"")} | F29: {=IFERROR(INDEX(Boletos!$L:$L,SMALL(Boletos!$O$3:$O$3602,25)),"")} | J29: {=IFERROR(INDEX(Alunos!$A:$A,SMALL(Alunos!$O$2:$O$301,25)),"")} | K29: {=IFERROR(INDEX(Alunos!$C:$C,SMALL(Alunos!$O$2:$O$301,25)),"")}
A30: {=IFERROR(INDEX(Boletos!$A:$A,SMALL(Boletos!$O$3:$O$3602,26)),"")} | B30: {=IFERROR(INDEX(Boletos!$B:$B,SMALL(Boletos!$O$3:$O$3602,26)),"")} | C30: {=IFERROR(INDEX(Boletos!$C:$C,SMALL(Boletos!$O$3:$O$3602,26)),"")} | D30: {=IFERROR(INDEX(Boletos!$D:$D,SMALL(Boletos!$O$3:$O$3602,26)),"")} | E30: {=IFERROR(INDEX(Boletos!$K:$K,SMALL(Boletos!$O$3:$O$3602,26)),"")} | F30: {=IFERROR(INDEX(Boletos!$L:$L,SMALL(Boletos!$O$3:$O$3602,26)),"")} | J30: {=IFERROR(INDEX(Alunos!$A:$A,SMALL(Alunos!$O$2:$O$301,26)),"")} | K30: {=IFERROR(INDEX(Alunos!$C:$C,SMALL(Alunos!$O$2:$O$301,26)),"")}
A31: {=IFERROR(INDEX(Boletos!$A:$A,SMALL(Boletos!$O$3:$O$3602,27)),"")} | B31: {=IFERROR(INDEX(Boletos!$B:$B,SMALL(Boletos!$O$3:$O$3602,27)),"")} | C31: {=IFERROR(INDEX(Boletos!$C:$C,SMALL(Boletos!$O$3:$O$3602,27)),"")} | D31: {=IFERROR(INDEX(Boletos!$D:$D,SMALL(Boletos!$O$3:$O$3602,27)),"")} | E31: {=IFERROR(INDEX(Boletos!$K:$K,SMALL(Boletos!$O$3:$O$3602,27)),"")} | F31: {=IFERROR(INDEX(Boletos!$L:$L,SMALL(Boletos!$O$3:$O$3602,27)),"")} | J31: {=IFERROR(INDEX(Alunos!$A:$A,SMALL(Alunos!$O$2:$O$301,27)),"")} | K31: {=IFERROR(INDEX(Alunos!$C:$C,SMALL(Alunos!$O$2:$O$301,27)),"")}
A32: {=IFERROR(INDEX(Boletos!$A:$A,SMALL(Boletos!$O$3:$O$3602,28)),"")} | B32: {=IFERROR(INDEX(Boletos!$B:$B,SMALL(Boletos!$O$3:$O$3602,28)),"")} | C32: {=IFERROR(INDEX(Boletos!$C:$C,SMALL(Boletos!$O$3:$O$3602,28)),"")} | D32: {=IFERROR(INDEX(Boletos!$D:$D,SMALL(Boletos!$O$3:$O$3602,28)),"")} | E32: {=IFERROR(INDEX(Boletos!$K:$K,SMALL(Boletos!$O$3:$O$3602,28)),"")} | F32: {=IFERROR(INDEX(Boletos!$L:$L,SMALL(Boletos!$O$3:$O$3602,28)),"")} | J32: {=IFERROR(INDEX(Alunos!$A:$A,SMALL(Alunos!$O$2:$O$301,28)),"")} | K32: {=IFERROR(INDEX(Alunos!$C:$C,SMALL(Alunos!$O$2:$O$301,28)),"")}
A33: {=IFERROR(INDEX(Boletos!$A:$A,SMALL(Boletos!$O$3:$O$3602,29)),"")} | B33: {=IFERROR(INDEX(Boletos!$B:$B,SMALL(Boletos!$O$3:$O$3602,29)),"")} | C33: {=IFERROR(INDEX(Boletos!$C:$C,SMALL(Boletos!$O$3:$O$3602,29)),"")} | D33: {=IFERROR(INDEX(Boletos!$D:$D,SMALL(Boletos!$O$3:$O$3602,29)),"")} | E33: {=IFERROR(INDEX(Boletos!$K:$K,SMALL(Boletos!$O$3:$O$3602,29)),"")} | F33: {=IFERROR(INDEX(Boletos!$L:$L,SMALL(Boletos!$O$3:$O$3602,29)),"")} | J33: {=IFERROR(INDEX(Alunos!$A:$A,SMALL(Alunos!$O$2:$O$301,29)),"")} | K33: {=IFERROR(INDEX(Alunos!$C:$C,SMALL(Alunos!$O$2:$O$301,29)),"")}
A34: {=IFERROR(INDEX(Boletos!$A:$A,SMALL(Boletos!$O$3:$O$3602,30)),"")} | B34: {=IFERROR(INDEX(Boletos!$B:$B,SMALL(Boletos!$O$3:$O$3602,30)),"")} | C34: {=IFERROR(INDEX(Boletos!$C:$C,SMALL(Boletos!$O$3:$O$3602,30)),"")} | D34: {=IFERROR(INDEX(Boletos!$D:$D,SMALL(Boletos!$O$3:$O$3602,30)),"")} | E34: {=IFERROR(INDEX(Boletos!$K:$K,SMALL(Boletos!$O$3:$O$3602,30)),"")} | F34: {=IFERROR(INDEX(Boletos!$L:$L,SMALL(Boletos!$O$3:$O$3602,30)),"")} | J34: {=IFERROR(INDEX(Alunos!$A:$A,SMALL(Alunos!$O$2:$O$301,30)),"")} | K34: {=IFERROR(INDEX(Alunos!$C:$C,SMALL(Alunos!$O$2:$O$301,30)),"")}
A35: {=IFERROR(INDEX(Boletos!$A:$A,SMALL(Boletos!$O$3:$O$3602,31)),"")} | B35: {=IFERROR(INDEX(Boletos!$B:$B,SMALL(Boletos!$O$3:$O$3602,31)),"")} | C35: {=IFERROR(INDEX(Boletos!$C:$C,SMALL(Boletos!$O$3:$O$3602,31)),"")} | D35: {=IFERROR(INDEX(Boletos!$D:$D,SMALL(Boletos!$O$3:$O$3602,31)),"")} | E35: {=IFERROR(INDEX(Boletos!$K:$K,SMALL(Boletos!$O$3:$O$3602,31)),"")} | F35: {=IFERROR(INDEX(Boletos!$L:$L,SMALL(Boletos!$O$3:$O$3602,31)),"")} | J35: {=IFERROR(INDEX(Alunos!$A:$A,SMALL(Alunos!$O$2:$O$301,31)),"")} | K35: {=IFERROR(INDEX(Alunos!$C:$C,SMALL(Alunos!$O$2:$O$301,31)),"")}
A36: {=IFERROR(INDEX(Boletos!$A:$A,SMALL(Boletos!$O$3:$O$3602,32)),"")} | B36: {=IFERROR(INDEX(Boletos!$B:$B,SMALL(Boletos!$O$3:$O$3602,32)),"")} | C36: {=IFERROR(INDEX(Boletos!$C:$C,SMALL(Boletos!$O$3:$O$3602,32)),"")} | D36: {=IFERROR(INDEX(Boletos!$D:$D,SMALL(Boletos!$O$3:$O$3602,32)),"")} | E36: {=IFERROR(INDEX(Boletos!$K:$K,SMALL(Boletos!$O$3:$O$3602,32)),"")} | F36: {=IFERROR(INDEX(Boletos!$L:$L,SMALL(Boletos!$O$3:$O$3602,32)),"")} | J36: {=IFERROR(INDEX(Alunos!$A:$A,SMALL(Alunos!$O$2:$O$301,32)),"")} | K36: {=IFERROR(INDEX(Alunos!$C:$C,SMALL(Alunos!$O$2:$O$301,32)),"")}
A37: {=IFERROR(INDEX(Boletos!$A:$A,SMALL(Boletos!$O$3:$O$3602,33)),"")} | B37: {=IFERROR(INDEX(Boletos!$B:$B,SMALL(Boletos!$O$3:$O$3602,33)),"")} | C37: {=IFERROR(INDEX(Boletos!$C:$C,SMALL(Boletos!$O$3:$O$3602,33)),"")} | D37: {=IFERROR(INDEX(Boletos!$D:$D,SMALL(Boletos!$O$3:$O$3602,33)),"")} | E37: {=IFERROR(INDEX(Boletos!$K:$K,SMALL(Boletos!$O$3:$O$3602,33)),"")} | F37: {=IFERROR(INDEX(Boletos!$L:$L,SMALL(Boletos!$O$3:$O$3602,33)),"")} | J37: {=IFERROR(INDEX(Alunos!$A:$A,SMALL(Alunos!$O$2:$O$301,33)),"")} | K37: {=IFERROR(INDEX(Alunos!$C:$C,SMALL(Alunos!$O$2:$O$301,33)),"")}
A38: {=IFERROR(INDEX(Boletos!$A:$A,SMALL(Boletos!$O$3:$O$3602,34)),"")} | B38: {=IFERROR(INDEX(Boletos!$B:$B,SMALL(Boletos!$O$3:$O$3602,34)),"")} | C38: {=IFERROR(INDEX(Boletos!$C:$C,SMALL(Boletos!$O$3:$O$3602,34)),"")} | D38: {=IFERROR(INDEX(Boletos!$D:$D,SMALL(Boletos!$O$3:$O$3602,34)),"")} | E38: {=IFERROR(INDEX(Boletos!$K:$K,SMALL(Boletos!$O$3:$O$3602,34)),"")} | F38: {=IFERROR(INDEX(Boletos!$L:$L,SMALL(Boletos!$O$3:$O$3602,34)),"")} | J38: {=IFERROR(INDEX(Alunos!$A:$A,SMALL(Alunos!$O$2:$O$301,34)),"")} | K38: {=IFERROR(INDEX(Alunos!$C:$C,SMALL(Alunos!$O$2:$O$301,34)),"")}
A39: {=IFERROR(INDEX(Boletos!$A:$A,SMALL(Boletos!$O$3:$O$3602,35)),"")} | B39: {=IFERROR(INDEX(Boletos!$B:$B,SMALL(Boletos!$O$3:$O$3602,35)),"")} | C39: {=IFERROR(INDEX(Boletos!$C:$C,SMALL(Boletos!$O$3:$O$3602,35)),"")} | D39: {=IFERROR(INDEX(Boletos!$D:$D,SMALL(Boletos!$O$3:$O$3602,35)),"")} | E39: {=IFERROR(INDEX(Boletos!$K:$K,SMALL(Boletos!$O$3:$O$3602,35)),"")} | F39: {=IFERROR(INDEX(Boletos!$L:$L,SMALL(Boletos!$O$3:$O$3602,35)),"")} | J39: {=IFERROR(INDEX(Alunos!$A:$A,SMALL(Alunos!$O$2:$O$301,35)),"")} | K39: {=IFERROR(INDEX(Alunos!$C:$C,SMALL(Alunos!$O$2:$O$301,35)),"")}
A40: {=IFERROR(INDEX(Boletos!$A:$A,SMALL(Boletos!$O$3:$O$3602,36)),"")} | B40: {=IFERROR(INDEX(Boletos!$B:$B,SMALL(Boletos!$O$3:$O$3602,36)),"")} | C40: {=IFERROR(INDEX(Boletos!$C:$C,SMALL(Boletos!$O$3:$O$3602,36)),"")} | D40: {=IFERROR(INDEX(Boletos!$D:$D,SMALL(Boletos!$O$3:$O$3602,36)),"")} | E40: {=IFERROR(INDEX(Boletos!$K:$K,SMALL(Boletos!$O$3:$O$3602,36)),"")} | F40: {=IFERROR(INDEX(Boletos!$L:$L,SMALL(Boletos!$O$3:$O$3602,36)),"")} | J40: {=IFERROR(INDEX(Alunos!$A:$A,SMALL(Alunos!$O$2:$O$301,36)),"")} | K40: {=IFERROR(INDEX(Alunos!$C:$C,SMALL(Alunos!$O$2:$O$301,36)),"")}
A41: {=IFERROR(INDEX(Boletos!$A:$A,SMALL(Boletos!$O$3:$O$3602,37)),"")} | B41: {=IFERROR(INDEX(Boletos!$B:$B,SMALL(Boletos!$O$3:$O$3602,37)),"")} | C41: {=IFERROR(INDEX(Boletos!$C:$C,SMALL(Boletos!$O$3:$O$3602,37)),"")} | D41: {=IFERROR(INDEX(Boletos!$D:$D,SMALL(Boletos!$O$3:$O$3602,37)),"")} | E41: {=IFERROR(INDEX(Boletos!$K:$K,SMALL(Boletos!$O$3:$O$3602,37)),"")} | F41: {=IFERROR(INDEX(Boletos!$L:$L,SMALL(Boletos!$O$3:$O$3602,37)),"")} | J41: {=IFERROR(INDEX(Alunos!$A:$A,SMALL(Alunos!$O$2:$O$301,37)),"")} | K41: {=IFERROR(INDEX(Alunos!$C:$C,SMALL(Alunos!$O$2:$O$301,37)),"")}
A42: {=IFERROR(INDEX(Boletos!$A:$A,SMALL(Boletos!$O$3:$O$3602,38)),"")} | B42: {=IFERROR(INDEX(Boletos!$B:$B,SMALL(Boletos!$O$3:$O$3602,38)),"")} | C42: {=IFERROR(INDEX(Boletos!$C:$C,SMALL(Boletos!$O$3:$O$3602,38)),"")} | D42: {=IFERROR(INDEX(Boletos!$D:$D,SMALL(Boletos!$O$3:$O$3602,38)),"")} | E42: {=IFERROR(INDEX(Boletos!$K:$K,SMALL(Boletos!$O$3:$O$3602,38)),"")} | F42: {=IFERROR(INDEX(Boletos!$L:$L,SMALL(Boletos!$O$3:$O$3602,38)),"")} | J42: {=IFERROR(INDEX(Alunos!$A:$A,SMALL(Alunos!$O$2:$O$301,38)),"")} | K42: {=IFERROR(INDEX(Alunos!$C:$C,SMALL(Alunos!$O$2:$O$301,38)),"")}
A43: {=IFERROR(INDEX(Boletos!$A:$A,SMALL(Boletos!$O$3:$O$3602,39)),"")} | B43: {=IFERROR(INDEX(Boletos!$B:$B,SMALL(Boletos!$O$3:$O$3602,39)),"")} | C43: {=IFERROR(INDEX(Boletos!$C:$C,SMALL(Boletos!$O$3:$O$3602,39)),"")} | D43: {=IFERROR(INDEX(Boletos!$D:$D,SMALL(Boletos!$O$3:$O$3602,39)),"")} | E43: {=IFERROR(INDEX(Boletos!$K:$K,SMALL(Boletos!$O$3:$O$3602,39)),"")} | F43: {=IFERROR(INDEX(Boletos!$L:$L,SMALL(Boletos!$O$3:$O$3602,39)),"")} | J43: {=IFERROR(INDEX(Alunos!$A:$A,SMALL(Alunos!$O$2:$O$301,39)),"")} | K43: {=IFERROR(INDEX(Alunos!$C:$C,SMALL(Alunos!$O$2:$O$301,39)),"")}
A44: {=IFERROR(INDEX(Boletos!$A:$A,SMALL(Boletos!$O$3:$O$3602,40)),"")} | B44: {=IFERROR(INDEX(Boletos!$B:$B,SMALL(Boletos!$O$3:$O$3602,40)),"")} | C44: {=IFERROR(INDEX(Boletos!$C:$C,SMALL(Boletos!$O$3:$O$3602,40)),"")} | D44: {=IFERROR(INDEX(Boletos!$D:$D,SMALL(Boletos!$O$3:$O$3602,40)),"")} | E44: {=IFERROR(INDEX(Boletos!$K:$K,SMALL(Boletos!$O$3:$O$3602,40)),"")} | F44: {=IFERROR(INDEX(Boletos!$L:$L,SMALL(Boletos!$O$3:$O$3602,40)),"")} | J44: {=IFERROR(INDEX(Alunos!$A:$A,SMALL(Alunos!$O$2:$O$301,40)),"")} | K44: {=IFERROR(INDEX(Alunos!$C:$C,SMALL(Alunos!$O$2:$O$301,40)),"")}
A45: {=IFERROR(INDEX(Boletos!$A:$A,SMALL(Boletos!$O$3:$O$3602,41)),"")} | B45: {=IFERROR(INDEX(Boletos!$B:$B,SMALL(Boletos!$O$3:$O$3602,41)),"")} | C45: {=IFERROR(INDEX(Boletos!$C:$C,SMALL(Boletos!$O$3:$O$3602,41)),"")} | D45: {=IFERROR(INDEX(Boletos!$D:$D,SMALL(Boletos!$O$3:$O$3602,41)),"")} | E45: {=IFERROR(INDEX(Boletos!$K:$K,SMALL(Boletos!$O$3:$O$3602,41)),"")} | F45: {=IFERROR(INDEX(Boletos!$L:$L,SMALL(Boletos!$O$3:$O$3602,41)),"")} | J45: {=IFERROR(INDEX(Alunos!$A:$A,SMALL(Alunos!$O$2:$O$301,41)),"")} | K45: {=IFERROR(INDEX(Alunos!$C:$C,SMALL(Alunos!$O$2:$O$301,41)),"")}
A46: {=IFERROR(INDEX(Boletos!$A:$A,SMALL(Boletos!$O$3:$O$3602,42)),"")} | B46: {=IFERROR(INDEX(Boletos!$B:$B,SMALL(Boletos!$O$3:$O$3602,42)),"")} | C46: {=IFERROR(INDEX(Boletos!$C:$C,SMALL(Boletos!$O$3:$O$3602,42)),"")} | D46: {=IFERROR(INDEX(Boletos!$D:$D,SMALL(Boletos!$O$3:$O$3602,42)),"")} | E46: {=IFERROR(INDEX(Boletos!$K:$K,SMALL(Boletos!$O$3:$O$3602,42)),"")} | F46: {=IFERROR(INDEX(Boletos!$L:$L,SMALL(Boletos!$O$3:$O$3602,42)),"")} | J46: {=IFERROR(INDEX(Alunos!$A:$A,SMALL(Alunos!$O$2:$O$301,42)),"")} | K46: {=IFERROR(INDEX(Alunos!$C:$C,SMALL(Alunos!$O$2:$O$301,42)),"")}
A47: {=IFERROR(INDEX(Boletos!$A:$A,SMALL(Boletos!$O$3:$O$3602,43)),"")} | B47: {=IFERROR(INDEX(Boletos!$B:$B,SMALL(Boletos!$O$3:$O$3602,43)),"")} | C47: {=IFERROR(INDEX(Boletos!$C:$C,SMALL(Boletos!$O$3:$O$3602,43)),"")} | D47: {=IFERROR(INDEX(Boletos!$D:$D,SMALL(Boletos!$O$3:$O$3602,43)),"")} | E47: {=IFERROR(INDEX(Boletos!$K:$K,SMALL(Boletos!$O$3:$O$3602,43)),"")} | F47: {=IFERROR(INDEX(Boletos!$L:$L,SMALL(Boletos!$O$3:$O$3602,43)),"")} | J47: {=IFERROR(INDEX(Alunos!$A:$A,SMALL(Alunos!$O$2:$O$301,43)),"")} | K47: {=IFERROR(INDEX(Alunos!$C:$C,SMALL(Alunos!$O$2:$O$301,43)),"")}
A48: {=IFERROR(INDEX(Boletos!$A:$A,SMALL(Boletos!$O$3:$O$3602,44)),"")} | B48: {=IFERROR(INDEX(Boletos!$B:$B,SMALL(Boletos!$O$3:$O$3602,44)),"")} | C48: {=IFERROR(INDEX(Boletos!$C:$C,SMALL(Boletos!$O$3:$O$3602,44)),"")} | D48: {=IFERROR(INDEX(Boletos!$D:$D,SMALL(Boletos!$O$3:$O$3602,44)),"")} | E48: {=IFERROR(INDEX(Boletos!$K:$K,SMALL(Boletos!$O$3:$O$3602,44)),"")} | F48: {=IFERROR(INDEX(Boletos!$L:$L,SMALL(Boletos!$O$3:$O$3602,44)),"")} | J48: {=IFERROR(INDEX(Alunos!$A:$A,SMALL(Alunos!$O$2:$O$301,44)),"")} | K48: {=IFERROR(INDEX(Alunos!$C:$C,SMALL(Alunos!$O$2:$O$301,44)),"")}
A49: {=IFERROR(INDEX(Boletos!$A:$A,SMALL(Boletos!$O$3:$O$3602,45)),"")} | B49: {=IFERROR(INDEX(Boletos!$B:$B,SMALL(Boletos!$O$3:$O$3602,45)),"")} | C49: {=IFERROR(INDEX(Boletos!$C:$C,SMALL(Boletos!$O$3:$O$3602,45)),"")} | D49: {=IFERROR(INDEX(Boletos!$D:$D,SMALL(Boletos!$O$3:$O$3602,45)),"")} | E49: {=IFERROR(INDEX(Boletos!$K:$K,SMALL(Boletos!$O$3:$O$3602,45)),"")} | F49: {=IFERROR(INDEX(Boletos!$L:$L,SMALL(Boletos!$O$3:$O$3602,45)),"")} | J49: {=IFERROR(INDEX(Alunos!$A:$A,SMALL(Alunos!$O$2:$O$301,45)),"")} | K49: {=IFERROR(INDEX(Alunos!$C:$C,SMALL(Alunos!$O$2:$O$301,45)),"")}
A50: {=IFERROR(INDEX(Boletos!$A:$A,SMALL(Boletos!$O$3:$O$3602,46)),"")} | B50: {=IFERROR(INDEX(Boletos!$B:$B,SMALL(Boletos!$O$3:$O$3602,46)),"")} | C50: {=IFERROR(INDEX(Boletos!$C:$C,SMALL(Boletos!$O$3:$O$3602,46)),"")} | D50: {=IFERROR(INDEX(Boletos!$D:$D,SMALL(Boletos!$O$3:$O$3602,46)),"")} | E50: {=IFERROR(INDEX(Boletos!$K:$K,SMALL(Boletos!$O$3:$O$3602,46)),"")} | F50: {=IFERROR(INDEX(Boletos!$L:$L,SMALL(Boletos!$O$3:$O$3602,46)),"")} | J50: {=IFERROR(INDEX(Alunos!$A:$A,SMALL(Alunos!$O$2:$O$301,46)),"")} | K50: {=IFERROR(INDEX(Alunos!$C:$C,SMALL(Alunos!$O$2:$O$301,46)),"")}
A51: {=IFERROR(INDEX(Boletos!$A:$A,SMALL(Boletos!$O$3:$O$3602,47)),"")} | B51: {=IFERROR(INDEX(Boletos!$B:$B,SMALL(Boletos!$O$3:$O$3602,47)),"")} | C51: {=IFERROR(INDEX(Boletos!$C:$C,SMALL(Boletos!$O$3:$O$3602,47)),"")} | D51: {=IFERROR(INDEX(Boletos!$D:$D,SMALL(Boletos!$O$3:$O$3602,47)),"")} | E51: {=IFERROR(INDEX(Boletos!$K:$K,SMALL(Boletos!$O$3:$O$3602,47)),"")} | F51: {=IFERROR(INDEX(Boletos!$L:$L,SMALL(Boletos!$O$3:$O$3602,47)),"")} | J51: {=IFERROR(INDEX(Alunos!$A:$A,SMALL(Alunos!$O$2:$O$301,47)),"")} | K51: {=IFERROR(INDEX(Alunos!$C:$C,SMALL(Alunos!$O$2:$O$301,47)),"")}
A52: {=IFERROR(INDEX(Boletos!$A:$A,SMALL(Boletos!$O$3:$O$3602,48)),"")} | B52: {=IFERROR(INDEX(Boletos!$B:$B,SMALL(Boletos!$O$3:$O$3602,48)),"")} | C52: {=IFERROR(INDEX(Boletos!$C:$C,SMALL(Boletos!$O$3:$O$3602,48)),"")} | D52: {=IFERROR(INDEX(Boletos!$D:$D,SMALL(Boletos!$O$3:$O$3602,48)),"")} | E52: {=IFERROR(INDEX(Boletos!$K:$K,SMALL(Boletos!$O$3:$O$3602,48)),"")} | F52: {=IFERROR(INDEX(Boletos!$L:$L,SMALL(Boletos!$O$3:$O$3602,48)),"")} | J52: {=IFERROR(INDEX(Alunos!$A:$A,SMALL(Alunos!$O$2:$O$301,48)),"")} | K52: {=IFERROR(INDEX(Alunos!$C:$C,SMALL(Alunos!$O$2:$O$301,48)),"")}
A53: {=IFERROR(INDEX(Boletos!$A:$A,SMALL(Boletos!$O$3:$O$3602,49)),"")} | B53: {=IFERROR(INDEX(Boletos!$B:$B,SMALL(Boletos!$O$3:$O$3602,49)),"")} | C53: {=IFERROR(INDEX(Boletos!$C:$C,SMALL(Boletos!$O$3:$O$3602,49)),"")} | D53: {=IFERROR(INDEX(Boletos!$D:$D,SMALL(Boletos!$O$3:$O$3602,49)),"")} | E53: {=IFERROR(INDEX(Boletos!$K:$K,SMALL(Boletos!$O$3:$O$3602,49)),"")} | F53: {=IFERROR(INDEX(Boletos!$L:$L,SMALL(Boletos!$O$3:$O$3602,49)),"")} | J53: {=IFERROR(INDEX(Alunos!$A:$A,SMALL(Alunos!$O$2:$O$301,49)),"")} | K53: {=IFERROR(INDEX(Alunos!$C:$C,SMALL(Alunos!$O$2:$O$301,49)),"")}
A54: {=IFERROR(INDEX(Boletos!$A:$A,SMALL(Boletos!$O$3:$O$3602,50)),"")} | B54: {=IFERROR(INDEX(Boletos!$B:$B,SMALL(Boletos!$O$3:$O$3602,50)),"")} | C54: {=IFERROR(INDEX(Boletos!$C:$C,SMALL(Boletos!$O$3:$O$3602,50)),"")} | D54: {=IFERROR(INDEX(Boletos!$D:$D,SMALL(Boletos!$O$3:$O$3602,50)),"")} | E54: {=IFERROR(INDEX(Boletos!$K:$K,SMALL(Boletos!$O$3:$O$3602,50)),"")} | F54: {=IFERROR(INDEX(Boletos!$L:$L,SMALL(Boletos!$O$3:$O$3602,50)),"")} | J54: {=IFERROR(INDEX(Alunos!$A:$A,SMALL(Alunos!$O$2:$O$301,50)),"")} | K54: {=IFERROR(INDEX(Alunos!$C:$C,SMALL(Alunos!$O$2:$O$301,50)),"")}
A55: {=IFERROR(INDEX(Boletos!$A:$A,SMALL(Boletos!$O$3:$O$3602,51)),"")} | B55: {=IFERROR(INDEX(Boletos!$B:$B,SMALL(Boletos!$O$3:$O$3602,51)),"")} | C55: {=IFERROR(INDEX(Boletos!$C:$C,SMALL(Boletos!$O$3:$O$3602,51)),"")} | D55: {=IFERROR(INDEX(Boletos!$D:$D,SMALL(Boletos!$O$3:$O$3602,51)),"")} | E55: {=IFERROR(INDEX(Boletos!$K:$K,SMALL(Boletos!$O$3:$O$3602,51)),"")} | F55: {=IFERROR(INDEX(Boletos!$L:$L,SMALL(Boletos!$O$3:$O$3602,51)),"")} | J55: {=IFERROR(INDEX(Alunos!$A:$A,SMALL(Alunos!$O$2:$O$301,51)),"")} | K55: {=IFERROR(INDEX(Alunos!$C:$C,SMALL(Alunos!$O$2:$O$301,51)),"")}
A56: {=IFERROR(INDEX(Boletos!$A:$A,SMALL(Boletos!$O$3:$O$3602,52)),"")} | B56: {=IFERROR(INDEX(Boletos!$B:$B,SMALL(Boletos!$O$3:$O$3602,52)),"")} | C56: {=IFERROR(INDEX(Boletos!$C:$C,SMALL(Boletos!$O$3:$O$3602,52)),"")} | D56: {=IFERROR(INDEX(Boletos!$D:$D,SMALL(Boletos!$O$3:$O$3602,52)),"")} | E56: {=IFERROR(INDEX(Boletos!$K:$K,SMALL(Boletos!$O$3:$O$3602,52)),"")} | F56: {=IFERROR(INDEX(Boletos!$L:$L,SMALL(Boletos!$O$3:$O$3602,52)),"")} | J56: {=IFERROR(INDEX(Alunos!$A:$A,SMALL(Alunos!$O$2:$O$301,52)),"")} | K56: {=IFERROR(INDEX(Alunos!$C:$C,SMALL(Alunos!$O$2:$O$301,52)),"")}
A57: {=IFERROR(INDEX(Boletos!$A:$A,SMALL(Boletos!$O$3:$O$3602,53)),"")} | B57: {=IFERROR(INDEX(Boletos!$B:$B,SMALL(Boletos!$O$3:$O$3602,53)),"")} | C57: {=IFERROR(INDEX(Boletos!$C:$C,SMALL(Boletos!$O$3:$O$3602,53)),"")} | D57: {=IFERROR(INDEX(Boletos!$D:$D,SMALL(Boletos!$O$3:$O$3602,53)),"")} | E57: {=IFERROR(INDEX(Boletos!$K:$K,SMALL(Boletos!$O$3:$O$3602,53)),"")} | F57: {=IFERROR(INDEX(Boletos!$L:$L,SMALL(Boletos!$O$3:$O$3602,53)),"")} | J57: {=IFERROR(INDEX(Alunos!$A:$A,SMALL(Alunos!$O$2:$O$301,53)),"")} | K57: {=IFERROR(INDEX(Alunos!$C:$C,SMALL(Alunos!$O$2:$O$301,53)),"")}
A58: {=IFERROR(INDEX(Boletos!$A:$A,SMALL(Boletos!$O$3:$O$3602,54)),"")} | B58: {=IFERROR(INDEX(Boletos!$B:$B,SMALL(Boletos!$O$3:$O$3602,54)),"")} | C58: {=IFERROR(INDEX(Boletos!$C:$C,SMALL(Boletos!$O$3:$O$3602,54)),"")} | D58: {=IFERROR(INDEX(Boletos!$D:$D,SMALL(Boletos!$O$3:$O$3602,54)),"")} | E58: {=IFERROR(INDEX(Boletos!$K:$K,SMALL(Boletos!$O$3:$O$3602,54)),"")} | F58: {=IFERROR(INDEX(Boletos!$L:$L,SMALL(Boletos!$O$3:$O$3602,54)),"")} | J58: {=IFERROR(INDEX(Alunos!$A:$A,SMALL(Alunos!$O$2:$O$301,54)),"")} | K58: {=IFERROR(INDEX(Alunos!$C:$C,SMALL(Alunos!$O$2:$O$301,54)),"")}
A59: {=IFERROR(INDEX(Boletos!$A:$A,SMALL(Boletos!$O$3:$O$3602,55)),"")} | B59: {=IFERROR(INDEX(Boletos!$B:$B,SMALL(Boletos!$O$3:$O$3602,55)),"")} | C59: {=IFERROR(INDEX(Boletos!$C:$C,SMALL(Boletos!$O$3:$O$3602,55)),"")} | D59: {=IFERROR(INDEX(Boletos!$D:$D,SMALL(Boletos!$O$3:$O$3602,55)),"")} | E59: {=IFERROR(INDEX(Boletos!$K:$K,SMALL(Boletos!$O$3:$O$3602,55)),"")} | F59: {=IFERROR(INDEX(Boletos!$L:$L,SMALL(Boletos!$O$3:$O$3602,55)),"")} | J59: {=IFERROR(INDEX(Alunos!$A:$A,SMALL(Alunos!$O$2:$O$301,55)),"")} | K59: {=IFERROR(INDEX(Alunos!$C:$C,SMALL(Alunos!$O$2:$O$301,55)),"")}
A60: {=IFERROR(INDEX(Boletos!$A:$A,SMALL(Boletos!$O$3:$O$3602,56)),"")} | B60: {=IFERROR(INDEX(Boletos!$B:$B,SMALL(Boletos!$O$3:$O$3602,56)),"")} | C60: {=IFERROR(INDEX(Boletos!$C:$C,SMALL(Boletos!$O$3:$O$3602,56)),"")} | D60: {=IFERROR(INDEX(Boletos!$D:$D,SMALL(Boletos!$O$3:$O$3602,56)),"")} | E60: {=IFERROR(INDEX(Boletos!$K:$K,SMALL(Boletos!$O$3:$O$3602,56)),"")} | F60: {=IFERROR(INDEX(Boletos!$L:$L,SMALL(Boletos!$O$3:$O$3602,56)),"")} | J60: {=IFERROR(INDEX(Alunos!$A:$A,SMALL(Alunos!$O$2:$O$301,56)),"")} | K60: {=IFERROR(INDEX(Alunos!$C:$C,SMALL(Alunos!$O$2:$O$301,56)),"")}
A61: {=IFERROR(INDEX(Boletos!$A:$A,SMALL(Boletos!$O$3:$O$3602,57)),"")} | B61: {=IFERROR(INDEX(Boletos!$B:$B,SMALL(Boletos!$O$3:$O$3602,57)),"")} | C61: {=IFERROR(INDEX(Boletos!$C:$C,SMALL(Boletos!$O$3:$O$3602,57)),"")} | D61: {=IFERROR(INDEX(Boletos!$D:$D,SMALL(Boletos!$O$3:$O$3602,57)),"")} | E61: {=IFERROR(INDEX(Boletos!$K:$K,SMALL(Boletos!$O$3:$O$3602,57)),"")} | F61: {=IFERROR(INDEX(Boletos!$L:$L,SMALL(Boletos!$O$3:$O$3602,57)),"")} | J61: {=IFERROR(INDEX(Alunos!$A:$A,SMALL(Alunos!$O$2:$O$301,57)),"")} | K61: {=IFERROR(INDEX(Alunos!$C:$C,SMALL(Alunos!$O$2:$O$301,57)),"")}
A62: {=IFERROR(INDEX(Boletos!$A:$A,SMALL(Boletos!$O$3:$O$3602,58)),"")} | B62: {=IFERROR(INDEX(Boletos!$B:$B,SMALL(Boletos!$O$3:$O$3602,58)),"")} | C62: {=IFERROR(INDEX(Boletos!$C:$C,SMALL(Boletos!$O$3:$O$3602,58)),"")} | D62: {=IFERROR(INDEX(Boletos!$D:$D,SMALL(Boletos!$O$3:$O$3602,58)),"")} | E62: {=IFERROR(INDEX(Boletos!$K:$K,SMALL(Boletos!$O$3:$O$3602,58)),"")} | F62: {=IFERROR(INDEX(Boletos!$L:$L,SMALL(Boletos!$O$3:$O$3602,58)),"")} | J62: {=IFERROR(INDEX(Alunos!$A:$A,SMALL(Alunos!$O$2:$O$301,58)),"")} | K62: {=IFERROR(INDEX(Alunos!$C:$C,SMALL(Alunos!$O$2:$O$301,58)),"")}
A63: {=IFERROR(INDEX(Boletos!$A:$A,SMALL(Boletos!$O$3:$O$3602,59)),"")} | B63: {=IFERROR(INDEX(Boletos!$B:$B,SMALL(Boletos!$O$3:$O$3602,59)),"")} | C63: {=IFERROR(INDEX(Boletos!$C:$C,SMALL(Boletos!$O$3:$O$3602,59)),"")} | D63: {=IFERROR(INDEX(Boletos!$D:$D,SMALL(Boletos!$O$3:$O$3602,59)),"")} | E63: {=IFERROR(INDEX(Boletos!$K:$K,SMALL(Boletos!$O$3:$O$3602,59)),"")} | F63: {=IFERROR(INDEX(Boletos!$L:$L,SMALL(Boletos!$O$3:$O$3602,59)),"")} | J63: {=IFERROR(INDEX(Alunos!$A:$A,SMALL(Alunos!$O$2:$O$301,59)),"")} | K63: {=IFERROR(INDEX(Alunos!$C:$C,SMALL(Alunos!$O$2:$O$301,59)),"")}
A64: {=IFERROR(INDEX(Boletos!$A:$A,SMALL(Boletos!$O$3:$O$3602,60)),"")} | B64: {=IFERROR(INDEX(Boletos!$B:$B,SMALL(Boletos!$O$3:$O$3602,60)),"")} | C64: {=IFERROR(INDEX(Boletos!$C:$C,SMALL(Boletos!$O$3:$O$3602,60)),"")} | D64: {=IFERROR(INDEX(Boletos!$D:$D,SMALL(Boletos!$O$3:$O$3602,60)),"")} | E64: {=IFERROR(INDEX(Boletos!$K:$K,SMALL(Boletos!$O$3:$O$3602,60)),"")} | F64: {=IFERROR(INDEX(Boletos!$L:$L,SMALL(Boletos!$O$3:$O$3602,60)),"")} | J64: {=IFERROR(INDEX(Alunos!$A:$A,SMALL(Alunos!$O$2:$O$301,60)),"")} | K64: {=IFERROR(INDEX(Alunos!$C:$C,SMALL(Alunos!$O$2:$O$301,60)),"")}
A65: {=IFERROR(INDEX(Boletos!$A:$A,SMALL(Boletos!$O$3:$O$3602,61)),"")} | B65: {=IFERROR(INDEX(Boletos!$B:$B,SMALL(Boletos!$O$3:$O$3602,61)),"")} | C65: {=IFERROR(INDEX(Boletos!$C:$C,SMALL(Boletos!$O$3:$O$3602,61)),"")} | D65: {=IFERROR(INDEX(Boletos!$D:$D,SMALL(Boletos!$O$3:$O$3602,61)),"")} | E65: {=IFERROR(INDEX(Boletos!$K:$K,SMALL(Boletos!$O$3:$O$3602,61)),"")} | F65: {=IFERROR(INDEX(Boletos!$L:$L,SMALL(Boletos!$O$3:$O$3602,61)),"")} | J65: {=IFERROR(INDEX(Alunos!$A:$A,SMALL(Alunos!$O$2:$O$301,61)),"")} | K65: {=IFERROR(INDEX(Alunos!$C:$C,SMALL(Alunos!$O$2:$O$301,61)),"")}
A66: {=IFERROR(INDEX(Boletos!$A:$A,SMALL(Boletos!$O$3:$O$3602,62)),"")} | B66: {=IFERROR(INDEX(Boletos!$B:$B,SMALL(Boletos!$O$3:$O$3602,62)),"")} | C66: {=IFERROR(INDEX(Boletos!$C:$C,SMALL(Boletos!$O$3:$O$3602,62)),"")} | D66: {=IFERROR(INDEX(Boletos!$D:$D,SMALL(Boletos!$O$3:$O$3602,62)),"")} | E66: {=IFERROR(INDEX(Boletos!$K:$K,SMALL(Boletos!$O$3:$O$3602,62)),"")} | F66: {=IFERROR(INDEX(Boletos!$L:$L,SMALL(Boletos!$O$3:$O$3602,62)),"")} | J66: {=IFERROR(INDEX(Alunos!$A:$A,SMALL(Alunos!$O$2:$O$301,62)),"")} | K66: {=IFERROR(INDEX(Alunos!$C:$C,SMALL(Alunos!$O$2:$O$301,62)),"")}
A67: {=IFERROR(INDEX(Boletos!$A:$A,SMALL(Boletos!$O$3:$O$3602,63)),"")} | B67: {=IFERROR(INDEX(Boletos!$B:$B,SMALL(Boletos!$O$3:$O$3602,63)),"")} | C67: {=IFERROR(INDEX(Boletos!$C:$C,SMALL(Boletos!$O$3:$O$3602,63)),"")} | D67: {=IFERROR(INDEX(Boletos!$D:$D,SMALL(Boletos!$O$3:$O$3602,63)),"")} | E67: {=IFERROR(INDEX(Boletos!$K:$K,SMALL(Boletos!$O$3:$O$3602,63)),"")} | F67: {=IFERROR(INDEX(Boletos!$L:$L,SMALL(Boletos!$O$3:$O$3602,63)),"")} | J67: {=IFERROR(INDEX(Alunos!$A:$A,SMALL(Alunos!$O$2:$O$301,63)),"")} | K67: {=IFERROR(INDEX(Alunos!$C:$C,SMALL(Alunos!$O$2:$O$301,63)),"")}
A68: {=IFERROR(INDEX(Boletos!$A:$A,SMALL(Boletos!$O$3:$O$3602,64)),"")} | B68: {=IFERROR(INDEX(Boletos!$B:$B,SMALL(Boletos!$O$3:$O$3602,64)),"")} | C68: {=IFERROR(INDEX(Boletos!$C:$C,SMALL(Boletos!$O$3:$O$3602,64)),"")} | D68: {=IFERROR(INDEX(Boletos!$D:$D,SMALL(Boletos!$O$3:$O$3602,64)),"")} | E68: {=IFERROR(INDEX(Boletos!$K:$K,SMALL(Boletos!$O$3:$O$3602,64)),"")} | F68: {=IFERROR(INDEX(Boletos!$L:$L,SMALL(Boletos!$O$3:$O$3602,64)),"")} | J68: {=IFERROR(INDEX(Alunos!$A:$A,SMALL(Alunos!$O$2:$O$301,64)),"")} | K68: {=IFERROR(INDEX(Alunos!$C:$C,SMALL(Alunos!$O$2:$O$301,64)),"")}
A69: {=IFERROR(INDEX(Boletos!$A:$A,SMALL(Boletos!$O$3:$O$3602,65)),"")} | B69: {=IFERROR(INDEX(Boletos!$B:$B,SMALL(Boletos!$O$3:$O$3602,65)),"")} | C69: {=IFERROR(INDEX(Boletos!$C:$C,SMALL(Boletos!$O$3:$O$3602,65)),"")} | D69: {=IFERROR(INDEX(Boletos!$D:$D,SMALL(Boletos!$O$3:$O$3602,65)),"")} | E69: {=IFERROR(INDEX(Boletos!$K:$K,SMALL(Boletos!$O$3:$O$3602,65)),"")} | F69: {=IFERROR(INDEX(Boletos!$L:$L,SMALL(Boletos!$O$3:$O$3602,65)),"")} | J69: {=IFERROR(INDEX(Alunos!$A:$A,SMALL(Alunos!$O$2:$O$301,65)),"")} | K69: {=IFERROR(INDEX(Alunos!$C:$C,SMALL(Alunos!$O$2:$O$301,65)),"")}
A70: {=IFERROR(INDEX(Boletos!$A:$A,SMALL(Boletos!$O$3:$O$3602,66)),"")} | B70: {=IFERROR(INDEX(Boletos!$B:$B,SMALL(Boletos!$O$3:$O$3602,66)),"")} | C70: {=IFERROR(INDEX(Boletos!$C:$C,SMALL(Boletos!$O$3:$O$3602,66)),"")} | D70: {=IFERROR(INDEX(Boletos!$D:$D,SMALL(Boletos!$O$3:$O$3602,66)),"")} | E70: {=IFERROR(INDEX(Boletos!$K:$K,SMALL(Boletos!$O$3:$O$3602,66)),"")} | F70: {=IFERROR(INDEX(Boletos!$L:$L,SMALL(Boletos!$O$3:$O$3602,66)),"")} | J70: {=IFERROR(INDEX(Alunos!$A:$A,SMALL(Alunos!$O$2:$O$301,66)),"")} | K70: {=IFERROR(INDEX(Alunos!$C:$C,SMALL(Alunos!$O$2:$O$301,66)),"")}
A71: {=IFERROR(INDEX(Boletos!$A:$A,SMALL(Boletos!$O$3:$O$3602,67)),"")} | B71: {=IFERROR(INDEX(Boletos!$B:$B,SMALL(Boletos!$O$3:$O$3602,67)),"")} | C71: {=IFERROR(INDEX(Boletos!$C:$C,SMALL(Boletos!$O$3:$O$3602,67)),"")} | D71: {=IFERROR(INDEX(Boletos!$D:$D,SMALL(Boletos!$O$3:$O$3602,67)),"")} | E71: {=IFERROR(INDEX(Boletos!$K:$K,SMALL(Boletos!$O$3:$O$3602,67)),"")} | F71: {=IFERROR(INDEX(Boletos!$L:$L,SMALL(Boletos!$O$3:$O$3602,67)),"")} | J71: {=IFERROR(INDEX(Alunos!$A:$A,SMALL(Alunos!$O$2:$O$301,67)),"")} | K71: {=IFERROR(INDEX(Alunos!$C:$C,SMALL(Alunos!$O$2:$O$301,67)),"")}
A72: {=IFERROR(INDEX(Boletos!$A:$A,SMALL(Boletos!$O$3:$O$3602,68)),"")} | B72: {=IFERROR(INDEX(Boletos!$B:$B,SMALL(Boletos!$O$3:$O$3602,68)),"")} | C72: {=IFERROR(INDEX(Boletos!$C:$C,SMALL(Boletos!$O$3:$O$3602,68)),"")} | D72: {=IFERROR(INDEX(Boletos!$D:$D,SMALL(Boletos!$O$3:$O$3602,68)),"")} | E72: {=IFERROR(INDEX(Boletos!$K:$K,SMALL(Boletos!$O$3:$O$3602,68)),"")} | F72: {=IFERROR(INDEX(Boletos!$L:$L,SMALL(Boletos!$O$3:$O$3602,68)),"")} | J72: {=IFERROR(INDEX(Alunos!$A:$A,SMALL(Alunos!$O$2:$O$301,68)),"")} | K72: {=IFERROR(INDEX(Alunos!$C:$C,SMALL(Alunos!$O$2:$O$301,68)),"")}
A73: {=IFERROR(INDEX(Boletos!$A:$A,SMALL(Boletos!$O$3:$O$3602,69)),"")} | B73: {=IFERROR(INDEX(Boletos!$B:$B,SMALL(Boletos!$O$3:$O$3602,69)),"")} | C73: {=IFERROR(INDEX(Boletos!$C:$C,SMALL(Boletos!$O$3:$O$3602,69)),"")} | D73: {=IFERROR(INDEX(Boletos!$D:$D,SMALL(Boletos!$O$3:$O$3602,69)),"")} | E73: {=IFERROR(INDEX(Boletos!$K:$K,SMALL(Boletos!$O$3:$O$3602,69)),"")} | F73: {=IFERROR(INDEX(Boletos!$L:$L,SMALL(Boletos!$O$3:$O$3602,69)),"")} | J73: {=IFERROR(INDEX(Alunos!$A:$A,SMALL(Alunos!$O$2:$O$301,69)),"")} | K73: {=IFERROR(INDEX(Alunos!$C:$C,SMALL(Alunos!$O$2:$O$301,69)),"")}
A74: {=IFERROR(INDEX(Boletos!$A:$A,SMALL(Boletos!$O$3:$O$3602,70)),"")} | B74: {=IFERROR(INDEX(Boletos!$B:$B,SMALL(Boletos!$O$3:$O$3602,70)),"")} | C74: {=IFERROR(INDEX(Boletos!$C:$C,SMALL(Boletos!$O$3:$O$3602,70)),"")} | D74: {=IFERROR(INDEX(Boletos!$D:$D,SMALL(Boletos!$O$3:$O$3602,70)),"")} | E74: {=IFERROR(INDEX(Boletos!$K:$K,SMALL(Boletos!$O$3:$O$3602,70)),"")} | F74: {=IFERROR(INDEX(Boletos!$L:$L,SMALL(Boletos!$O$3:$O$3602,70)),"")} | J74: {=IFERROR(INDEX(Alunos!$A:$A,SMALL(Alunos!$O$2:$O$301,70)),"")} | K74: {=IFERROR(INDEX(Alunos!$C:$C,SMALL(Alunos!$O$2:$O$301,70)),"")}
A75: {=IFERROR(INDEX(Boletos!$A:$A,SMALL(Boletos!$O$3:$O$3602,71)),"")} | B75: {=IFERROR(INDEX(Boletos!$B:$B,SMALL(Boletos!$O$3:$O$3602,71)),"")} | C75: {=IFERROR(INDEX(Boletos!$C:$C,SMALL(Boletos!$O$3:$O$3602,71)),"")} | D75: {=IFERROR(INDEX(Boletos!$D:$D,SMALL(Boletos!$O$3:$O$3602,71)),"")} | E75: {=IFERROR(INDEX(Boletos!$K:$K,SMALL(Boletos!$O$3:$O$3602,71)),"")} | F75: {=IFERROR(INDEX(Boletos!$L:$L,SMALL(Boletos!$O$3:$O$3602,71)),"")} | J75: {=IFERROR(INDEX(Alunos!$A:$A,SMALL(Alunos!$O$2:$O$301,71)),"")} | K75: {=IFERROR(INDEX(Alunos!$C:$C,SMALL(Alunos!$O$2:$O$301,71)),"")}
A76: {=IFERROR(INDEX(Boletos!$A:$A,SMALL(Boletos!$O$3:$O$3602,72)),"")} | B76: {=IFERROR(INDEX(Boletos!$B:$B,SMALL(Boletos!$O$3:$O$3602,72)),"")} | C76: {=IFERROR(INDEX(Boletos!$C:$C,SMALL(Boletos!$O$3:$O$3602,72)),"")} | D76: {=IFERROR(INDEX(Boletos!$D:$D,SMALL(Boletos!$O$3:$O$3602,72)),"")} | E76: {=IFERROR(INDEX(Boletos!$K:$K,SMALL(Boletos!$O$3:$O$3602,72)),"")} | F76: {=IFERROR(INDEX(Boletos!$L:$L,SMALL(Boletos!$O$3:$O$3602,72)),"")} | J76: {=IFERROR(INDEX(Alunos!$A:$A,SMALL(Alunos!$O$2:$O$301,72)),"")} | K76: {=IFERROR(INDEX(Alunos!$C:$C,SMALL(Alunos!$O$2:$O$301,72)),"")}
A77: {=IFERROR(INDEX(Boletos!$A:$A,SMALL(Boletos!$O$3:$O$3602,73)),"")} | B77: {=IFERROR(INDEX(Boletos!$B:$B,SMALL(Boletos!$O$3:$O$3602,73)),"")} | C77: {=IFERROR(INDEX(Boletos!$C:$C,SMALL(Boletos!$O$3:$O$3602,73)),"")} | D77: {=IFERROR(INDEX(Boletos!$D:$D,SMALL(Boletos!$O$3:$O$3602,73)),"")} | E77: {=IFERROR(INDEX(Boletos!$K:$K,SMALL(Boletos!$O$3:$O$3602,73)),"")} | F77: {=IFERROR(INDEX(Boletos!$L:$L,SMALL(Boletos!$O$3:$O$3602,73)),"")} | J77: {=IFERROR(INDEX(Alunos!$A:$A,SMALL(Alunos!$O$2:$O$301,73)),"")} | K77: {=IFERROR(INDEX(Alunos!$C:$C,SMALL(Alunos!$O$2:$O$301,73)),"")}
A78: {=IFERROR(INDEX(Boletos!$A:$A,SMALL(Boletos!$O$3:$O$3602,74)),"")} | B78: {=IFERROR(INDEX(Boletos!$B:$B,SMALL(Boletos!$O$3:$O$3602,74)),"")} | C78: {=IFERROR(INDEX(Boletos!$C:$C,SMALL(Boletos!$O$3:$O$3602,74)),"")} | D78: {=IFERROR(INDEX(Boletos!$D:$D,SMALL(Boletos!$O$3:$O$3602,74)),"")} | E78: {=IFERROR(INDEX(Boletos!$K:$K,SMALL(Boletos!$O$3:$O$3602,74)),"")} | F78: {=IFERROR(INDEX(Boletos!$L:$L,SMALL(Boletos!$O$3:$O$3602,74)),"")} | J78: {=IFERROR(INDEX(Alunos!$A:$A,SMALL(Alunos!$O$2:$O$301,74)),"")} | K78: {=IFERROR(INDEX(Alunos!$C:$C,SMALL(Alunos!$O$2:$O$301,74)),"")}
A79: {=IFERROR(INDEX(Boletos!$A:$A,SMALL(Boletos!$O$3:$O$3602,75)),"")} | B79: {=IFERROR(INDEX(Boletos!$B:$B,SMALL(Boletos!$O$3:$O$3602,75)),"")} | C79: {=IFERROR(INDEX(Boletos!$C:$C,SMALL(Boletos!$O$3:$O$3602,75)),"")} | D79: {=IFERROR(INDEX(Boletos!$D:$D,SMALL(Boletos!$O$3:$O$3602,75)),"")} | E79: {=IFERROR(INDEX(Boletos!$K:$K,SMALL(Boletos!$O$3:$O$3602,75)),"")} | F79: {=IFERROR(INDEX(Boletos!$L:$L,SMALL(Boletos!$O$3:$O$3602,75)),"")} | J79: {=IFERROR(INDEX(Alunos!$A:$A,SMALL(Alunos!$O$2:$O$301,75)),"")} | K79: {=IFERROR(INDEX(Alunos!$C:$C,SMALL(Alunos!$O$2:$O$301,75)),"")}
A80: {=IFERROR(INDEX(Boletos!$A:$A,SMALL(Boletos!$O$3:$O$3602,76)),"")} | B80: {=IFERROR(INDEX(Boletos!$B:$B,SMALL(Boletos!$O$3:$O$3602,76)),"")} | C80: {=IFERROR(INDEX(Boletos!$C:$C,SMALL(Boletos!$O$3:$O$3602,76)),"")} | D80: {=IFERROR(INDEX(Boletos!$D:$D,SMALL(Boletos!$O$3:$O$3602,76)),"")} | E80: {=IFERROR(INDEX(Boletos!$K:$K,SMALL(Boletos!$O$3:$O$3602,76)),"")} | F80: {=IFERROR(INDEX(Boletos!$L:$L,SMALL(Boletos!$O$3:$O$3602,76)),"")} | J80: {=IFERROR(INDEX(Alunos!$A:$A,SMALL(Alunos!$O$2:$O$301,76)),"")} | K80: {=IFERROR(INDEX(Alunos!$C:$C,SMALL(Alunos!$O$2:$O$301,76)),"")}
A81: {=IFERROR(INDEX(Boletos!$A:$A,SMALL(Boletos!$O$3:$O$3602,77)),"")} | B81: {=IFERROR(INDEX(Boletos!$B:$B,SMALL(Boletos!$O$3:$O$3602,77)),"")} | C81: {=IFERROR(INDEX(Boletos!$C:$C,SMALL(Boletos!$O$3:$O$3602,77)),"")} | D81: {=IFERROR(INDEX(Boletos!$D:$D,SMALL(Boletos!$O$3:$O$3602,77)),"")} | E81: {=IFERROR(INDEX(Boletos!$K:$K,SMALL(Boletos!$O$3:$O$3602,77)),"")} | F81: {=IFERROR(INDEX(Boletos!$L:$L,SMALL(Boletos!$O$3:$O$3602,77)),"")} | J81: {=IFERROR(INDEX(Alunos!$A:$A,SMALL(Alunos!$O$2:$O$301,77)),"")} | K81: {=IFERROR(INDEX(Alunos!$C:$C,SMALL(Alunos!$O$2:$O$301,77)),"")}
A82: {=IFERROR(INDEX(Boletos!$A:$A,SMALL(Boletos!$O$3:$O$3602,78)),"")} | B82: {=IFERROR(INDEX(Boletos!$B:$B,SMALL(Boletos!$O$3:$O$3602,78)),"")} | C82: {=IFERROR(INDEX(Boletos!$C:$C,SMALL(Boletos!$O$3:$O$3602,78)),"")} | D82: {=IFERROR(INDEX(Boletos!$D:$D,SMALL(Boletos!$O$3:$O$3602,78)),"")} | E82: {=IFERROR(INDEX(Boletos!$K:$K,SMALL(Boletos!$O$3:$O$3602,78)),"")} | F82: {=IFERROR(INDEX(Boletos!$L:$L,SMALL(Boletos!$O$3:$O$3602,78)),"")} | J82: {=IFERROR(INDEX(Alunos!$A:$A,SMALL(Alunos!$O$2:$O$301,78)),"")} | K82: {=IFERROR(INDEX(Alunos!$C:$C,SMALL(Alunos!$O$2:$O$301,78)),"")}
A83: {=IFERROR(INDEX(Boletos!$A:$A,SMALL(Boletos!$O$3:$O$3602,79)),"")} | B83: {=IFERROR(INDEX(Boletos!$B:$B,SMALL(Boletos!$O$3:$O$3602,79)),"")} | C83: {=IFERROR(INDEX(Boletos!$C:$C,SMALL(Boletos!$O$3:$O$3602,79)),"")} | D83: {=IFERROR(INDEX(Boletos!$D:$D,SMALL(Boletos!$O$3:$O$3602,79)),"")} | E83: {=IFERROR(INDEX(Boletos!$K:$K,SMALL(Boletos!$O$3:$O$3602,79)),"")} | F83: {=IFERROR(INDEX(Boletos!$L:$L,SMALL(Boletos!$O$3:$O$3602,79)),"")} | J83: {=IFERROR(INDEX(Alunos!$A:$A,SMALL(Alunos!$O$2:$O$301,79)),"")} | K83: {=IFERROR(INDEX(Alunos!$C:$C,SMALL(Alunos!$O$2:$O$301,79)),"")}
A84: {=IFERROR(INDEX(Boletos!$A:$A,SMALL(Boletos!$O$3:$O$3602,80)),"")} | B84: {=IFERROR(INDEX(Boletos!$B:$B,SMALL(Boletos!$O$3:$O$3602,80)),"")} | C84: {=IFERROR(INDEX(Boletos!$C:$C,SMALL(Boletos!$O$3:$O$3602,80)),"")} | D84: {=IFERROR(INDEX(Boletos!$D:$D,SMALL(Boletos!$O$3:$O$3602,80)),"")} | E84: {=IFERROR(INDEX(Boletos!$K:$K,SMALL(Boletos!$O$3:$O$3602,80)),"")} | F84: {=IFERROR(INDEX(Boletos!$L:$L,SMALL(Boletos!$O$3:$O$3602,80)),"")} | J84: {=IFERROR(INDEX(Alunos!$A:$A,SMALL(Alunos!$O$2:$O$301,80)),"")} | K84: {=IFERROR(INDEX(Alunos!$C:$C,SMALL(Alunos!$O$2:$O$301,80)),"")}
A85: {=IFERROR(INDEX(Boletos!$A:$A,SMALL(Boletos!$O$3:$O$3602,81)),"")} | B85: {=IFERROR(INDEX(Boletos!$B:$B,SMALL(Boletos!$O$3:$O$3602,81)),"")} | C85: {=IFERROR(INDEX(Boletos!$C:$C,SMALL(Boletos!$O$3:$O$3602,81)),"")} | D85: {=IFERROR(INDEX(Boletos!$D:$D,SMALL(Boletos!$O$3:$O$3602,81)),"")} | E85: {=IFERROR(INDEX(Boletos!$K:$K,SMALL(Boletos!$O$3:$O$3602,81)),"")} | F85: {=IFERROR(INDEX(Boletos!$L:$L,SMALL(Boletos!$O$3:$O$3602,81)),"")} | J85: {=IFERROR(INDEX(Alunos!$A:$A,SMALL(Alunos!$O$2:$O$301,81)),"")} | K85: {=IFERROR(INDEX(Alunos!$C:$C,SMALL(Alunos!$O$2:$O$301,81)),"")}
A86: {=IFERROR(INDEX(Boletos!$A:$A,SMALL(Boletos!$O$3:$O$3602,82)),"")} | B86: {=IFERROR(INDEX(Boletos!$B:$B,SMALL(Boletos!$O$3:$O$3602,82)),"")} | C86: {=IFERROR(INDEX(Boletos!$C:$C,SMALL(Boletos!$O$3:$O$3602,82)),"")} | D86: {=IFERROR(INDEX(Boletos!$D:$D,SMALL(Boletos!$O$3:$O$3602,82)),"")} | E86: {=IFERROR(INDEX(Boletos!$K:$K,SMALL(Boletos!$O$3:$O$3602,82)),"")} | F86: {=IFERROR(INDEX(Boletos!$L:$L,SMALL(Boletos!$O$3:$O$3602,82)),"")} | J86: {=IFERROR(INDEX(Alunos!$A:$A,SMALL(Alunos!$O$2:$O$301,82)),"")} | K86: {=IFERROR(INDEX(Alunos!$C:$C,SMALL(Alunos!$O$2:$O$301,82)),"")}
A87: {=IFERROR(INDEX(Boletos!$A:$A,SMALL(Boletos!$O$3:$O$3602,83)),"")} | B87: {=IFERROR(INDEX(Boletos!$B:$B,SMALL(Boletos!$O$3:$O$3602,83)),"")} | C87: {=IFERROR(INDEX(Boletos!$C:$C,SMALL(Boletos!$O$3:$O$3602,83)),"")} | D87: {=IFERROR(INDEX(Boletos!$D:$D,SMALL(Boletos!$O$3:$O$3602,83)),"")} | E87: {=IFERROR(INDEX(Boletos!$K:$K,SMALL(Boletos!$O$3:$O$3602,83)),"")} | F87: {=IFERROR(INDEX(Boletos!$L:$L,SMALL(Boletos!$O$3:$O$3602,83)),"")} | J87: {=IFERROR(INDEX(Alunos!$A:$A,SMALL(Alunos!$O$2:$O$301,83)),"")} | K87: {=IFERROR(INDEX(Alunos!$C:$C,SMALL(Alunos!$O$2:$O$301,83)),"")}
A88: {=IFERROR(INDEX(Boletos!$A:$A,SMALL(Boletos!$O$3:$O$3602,84)),"")} | B88: {=IFERROR(INDEX(Boletos!$B:$B,SMALL(Boletos!$O$3:$O$3602,84)),"")} | C88: {=IFERROR(INDEX(Boletos!$C:$C,SMALL(Boletos!$O$3:$O$3602,84)),"")} | D88: {=IFERROR(INDEX(Boletos!$D:$D,SMALL(Boletos!$O$3:$O$3602,84)),"")} | E88: {=IFERROR(INDEX(Boletos!$K:$K,SMALL(Boletos!$O$3:$O$3602,84)),"")} | F88: {=IFERROR(INDEX(Boletos!$L:$L,SMALL(Boletos!$O$3:$O$3602,84)),"")} | J88: {=IFERROR(INDEX(Alunos!$A:$A,SMALL(Alunos!$O$2:$O$301,84)),"")} | K88: {=IFERROR(INDEX(Alunos!$C:$C,SMALL(Alunos!$O$2:$O$301,84)),"")}
A89: {=IFERROR(INDEX(Boletos!$A:$A,SMALL(Boletos!$O$3:$O$3602,85)),"")} | B89: {=IFERROR(INDEX(Boletos!$B:$B,SMALL(Boletos!$O$3:$O$3602,85)),"")} | C89: {=IFERROR(INDEX(Boletos!$C:$C,SMALL(Boletos!$O$3:$O$3602,85)),"")} | D89: {=IFERROR(INDEX(Boletos!$D:$D,SMALL(Boletos!$O$3:$O$3602,85)),"")} | E89: {=IFERROR(INDEX(Boletos!$K:$K,SMALL(Boletos!$O$3:$O$3602,85)),"")} | F89: {=IFERROR(INDEX(Boletos!$L:$L,SMALL(Boletos!$O$3:$O$3602,85)),"")} | J89: {=IFERROR(INDEX(Alunos!$A:$A,SMALL(Alunos!$O$2:$O$301,85)),"")} | K89: {=IFERROR(INDEX(Alunos!$C:$C,SMALL(Alunos!$O$2:$O$301,85)),"")}
A90: {=IFERROR(INDEX(Boletos!$A:$A,SMALL(Boletos!$O$3:$O$3602,86)),"")} | B90: {=IFERROR(INDEX(Boletos!$B:$B,SMALL(Boletos!$O$3:$O$3602,86)),"")} | C90: {=IFERROR(INDEX(Boletos!$C:$C,SMALL(Boletos!$O$3:$O$3602,86)),"")} | D90: {=IFERROR(INDEX(Boletos!$D:$D,SMALL(Boletos!$O$3:$O$3602,86)),"")} | E90: {=IFERROR(INDEX(Boletos!$K:$K,SMALL(Boletos!$O$3:$O$3602,86)),"")} | F90: {=IFERROR(INDEX(Boletos!$L:$L,SMALL(Boletos!$O$3:$O$3602,86)),"")} | J90: {=IFERROR(INDEX(Alunos!$A:$A,SMALL(Alunos!$O$2:$O$301,86)),"")} | K90: {=IFERROR(INDEX(Alunos!$C:$C,SMALL(Alunos!$O$2:$O$301,86)),"")}
A91: {=IFERROR(INDEX(Boletos!$A:$A,SMALL(Boletos!$O$3:$O$3602,87)),"")} | B91: {=IFERROR(INDEX(Boletos!$B:$B,SMALL(Boletos!$O$3:$O$3602,87)),"")} | C91: {=IFERROR(INDEX(Boletos!$C:$C,SMALL(Boletos!$O$3:$O$3602,87)),"")} | D91: {=IFERROR(INDEX(Boletos!$D:$D,SMALL(Boletos!$O$3:$O$3602,87)),"")} | E91: {=IFERROR(INDEX(Boletos!$K:$K,SMALL(Boletos!$O$3:$O$3602,87)),"")} | F91: {=IFERROR(INDEX(Boletos!$L:$L,SMALL(Boletos!$O$3:$O$3602,87)),"")} | J91: {=IFERROR(INDEX(Alunos!$A:$A,SMALL(Alunos!$O$2:$O$301,87)),"")} | K91: {=IFERROR(INDEX(Alunos!$C:$C,SMALL(Alunos!$O$2:$O$301,87)),"")}
A92: {=IFERROR(INDEX(Boletos!$A:$A,SMALL(Boletos!$O$3:$O$3602,88)),"")} | B92: {=IFERROR(INDEX(Boletos!$B:$B,SMALL(Boletos!$O$3:$O$3602,88)),"")} | C92: {=IFERROR(INDEX(Boletos!$C:$C,SMALL(Boletos!$O$3:$O$3602,88)),"")} | D92: {=IFERROR(INDEX(Boletos!$D:$D,SMALL(Boletos!$O$3:$O$3602,88)),"")} | E92: {=IFERROR(INDEX(Boletos!$K:$K,SMALL(Boletos!$O$3:$O$3602,88)),"")} | F92: {=IFERROR(INDEX(Boletos!$L:$L,SMALL(Boletos!$O$3:$O$3602,88)),"")} | J92: {=IFERROR(INDEX(Alunos!$A:$A,SMALL(Alunos!$O$2:$O$301,88)),"")} | K92: {=IFERROR(INDEX(Alunos!$C:$C,SMALL(Alunos!$O$2:$O$301,88)),"")}
A93: {=IFERROR(INDEX(Boletos!$A:$A,SMALL(Boletos!$O$3:$O$3602,89)),"")} | B93: {=IFERROR(INDEX(Boletos!$B:$B,SMALL(Boletos!$O$3:$O$3602,89)),"")} | C93: {=IFERROR(INDEX(Boletos!$C:$C,SMALL(Boletos!$O$3:$O$3602,89)),"")} | D93: {=IFERROR(INDEX(Boletos!$D:$D,SMALL(Boletos!$O$3:$O$3602,89)),"")} | E93: {=IFERROR(INDEX(Boletos!$K:$K,SMALL(Boletos!$O$3:$O$3602,89)),"")} | F93: {=IFERROR(INDEX(Boletos!$L:$L,SMALL(Boletos!$O$3:$O$3602,89)),"")} | J93: {=IFERROR(INDEX(Alunos!$A:$A,SMALL(Alunos!$O$2:$O$301,89)),"")} | K93: {=IFERROR(INDEX(Alunos!$C:$C,SMALL(Alunos!$O$2:$O$301,89)),"")}
A94: {=IFERROR(INDEX(Boletos!$A:$A,SMALL(Boletos!$O$3:$O$3602,90)),"")} | B94: {=IFERROR(INDEX(Boletos!$B:$B,SMALL(Boletos!$O$3:$O$3602,90)),"")} | C94: {=IFERROR(INDEX(Boletos!$C:$C,SMALL(Boletos!$O$3:$O$3602,90)),"")} | D94: {=IFERROR(INDEX(Boletos!$D:$D,SMALL(Boletos!$O$3:$O$3602,90)),"")} | E94: {=IFERROR(INDEX(Boletos!$K:$K,SMALL(Boletos!$O$3:$O$3602,90)),"")} | F94: {=IFERROR(INDEX(Boletos!$L:$L,SMALL(Boletos!$O$3:$O$3602,90)),"")} | J94: {=IFERROR(INDEX(Alunos!$A:$A,SMALL(Alunos!$O$2:$O$301,90)),"")} | K94: {=IFERROR(INDEX(Alunos!$C:$C,SMALL(Alunos!$O$2:$O$301,90)),"")}
A95: {=IFERROR(INDEX(Boletos!$A:$A,SMALL(Boletos!$O$3:$O$3602,91)),"")} | B95: {=IFERROR(INDEX(Boletos!$B:$B,SMALL(Boletos!$O$3:$O$3602,91)),"")} | C95: {=IFERROR(INDEX(Boletos!$C:$C,SMALL(Boletos!$O$3:$O$3602,91)),"")} | D95: {=IFERROR(INDEX(Boletos!$D:$D,SMALL(Boletos!$O$3:$O$3602,91)),"")} | E95: {=IFERROR(INDEX(Boletos!$K:$K,SMALL(Boletos!$O$3:$O$3602,91)),"")} | F95: {=IFERROR(INDEX(Boletos!$L:$L,SMALL(Boletos!$O$3:$O$3602,91)),"")} | J95: {=IFERROR(INDEX(Alunos!$A:$A,SMALL(Alunos!$O$2:$O$301,91)),"")} | K95: {=IFERROR(INDEX(Alunos!$C:$C,SMALL(Alunos!$O$2:$O$301,91)),"")}
A96: {=IFERROR(INDEX(Boletos!$A:$A,SMALL(Boletos!$O$3:$O$3602,92)),"")} | B96: {=IFERROR(INDEX(Boletos!$B:$B,SMALL(Boletos!$O$3:$O$3602,92)),"")} | C96: {=IFERROR(INDEX(Boletos!$C:$C,SMALL(Boletos!$O$3:$O$3602,92)),"")} | D96: {=IFERROR(INDEX(Boletos!$D:$D,SMALL(Boletos!$O$3:$O$3602,92)),"")} | E96: {=IFERROR(INDEX(Boletos!$K:$K,SMALL(Boletos!$O$3:$O$3602,92)),"")} | F96: {=IFERROR(INDEX(Boletos!$L:$L,SMALL(Boletos!$O$3:$O$3602,92)),"")} | J96: {=IFERROR(INDEX(Alunos!$A:$A,SMALL(Alunos!$O$2:$O$301,92)),"")} | K96: {=IFERROR(INDEX(Alunos!$C:$C,SMALL(Alunos!$O$2:$O$301,92)),"")}
A97: {=IFERROR(INDEX(Boletos!$A:$A,SMALL(Boletos!$O$3:$O$3602,93)),"")} | B97: {=IFERROR(INDEX(Boletos!$B:$B,SMALL(Boletos!$O$3:$O$3602,93)),"")} | C97: {=IFERROR(INDEX(Boletos!$C:$C,SMALL(Boletos!$O$3:$O$3602,93)),"")} | D97: {=IFERROR(INDEX(Boletos!$D:$D,SMALL(Boletos!$O$3:$O$3602,93)),"")} | E97: {=IFERROR(INDEX(Boletos!$K:$K,SMALL(Boletos!$O$3:$O$3602,93)),"")} | F97: {=IFERROR(INDEX(Boletos!$L:$L,SMALL(Boletos!$O$3:$O$3602,93)),"")} | J97: {=IFERROR(INDEX(Alunos!$A:$A,SMALL(Alunos!$O$2:$O$301,93)),"")} | K97: {=IFERROR(INDEX(Alunos!$C:$C,SMALL(Alunos!$O$2:$O$301,93)),"")}
A98: {=IFERROR(INDEX(Boletos!$A:$A,SMALL(Boletos!$O$3:$O$3602,94)),"")} | B98: {=IFERROR(INDEX(Boletos!$B:$B,SMALL(Boletos!$O$3:$O$3602,94)),"")} | C98: {=IFERROR(INDEX(Boletos!$C:$C,SMALL(Boletos!$O$3:$O$3602,94)),"")} | D98: {=IFERROR(INDEX(Boletos!$D:$D,SMALL(Boletos!$O$3:$O$3602,94)),"")} | E98: {=IFERROR(INDEX(Boletos!$K:$K,SMALL(Boletos!$O$3:$O$3602,94)),"")} | F98: {=IFERROR(INDEX(Boletos!$L:$L,SMALL(Boletos!$O$3:$O$3602,94)),"")} | J98: {=IFERROR(INDEX(Alunos!$A:$A,SMALL(Alunos!$O$2:$O$301,94)),"")} | K98: {=IFERROR(INDEX(Alunos!$C:$C,SMALL(Alunos!$O$2:$O$301,94)),"")}
A99: {=IFERROR(INDEX(Boletos!$A:$A,SMALL(Boletos!$O$3:$O$3602,95)),"")} | B99: {=IFERROR(INDEX(Boletos!$B:$B,SMALL(Boletos!$O$3:$O$3602,95)),"")} | C99: {=IFERROR(INDEX(Boletos!$C:$C,SMALL(Boletos!$O$3:$O$3602,95)),"")} | D99: {=IFERROR(INDEX(Boletos!$D:$D,SMALL(Boletos!$O$3:$O$3602,95)),"")} | E99: {=IFERROR(INDEX(Boletos!$K:$K,SMALL(Boletos!$O$3:$O$3602,95)),"")} | F99: {=IFERROR(INDEX(Boletos!$L:$L,SMALL(Boletos!$O$3:$O$3602,95)),"")} | J99: {=IFERROR(INDEX(Alunos!$A:$A,SMALL(Alunos!$O$2:$O$301,95)),"")} | K99: {=IFERROR(INDEX(Alunos!$C:$C,SMALL(Alunos!$O$2:$O$301,95)),"")}
A100: {=IFERROR(INDEX(Boletos!$A:$A,SMALL(Boletos!$O$3:$O$3602,96)),"")} | B100: {=IFERROR(INDEX(Boletos!$B:$B,SMALL(Boletos!$O$3:$O$3602,96)),"")} | C100: {=IFERROR(INDEX(Boletos!$C:$C,SMALL(Boletos!$O$3:$O$3602,96)),"")} | D100: {=IFERROR(INDEX(Boletos!$D:$D,SMALL(Boletos!$O$3:$O$3602,96)),"")} | E100: {=IFERROR(INDEX(Boletos!$K:$K,SMALL(Boletos!$O$3:$O$3602,96)),"")} | F100: {=IFERROR(INDEX(Boletos!$L:$L,SMALL(Boletos!$O$3:$O$3602,96)),"")} | J100: {=IFERROR(INDEX(Alunos!$A:$A,SMALL(Alunos!$O$2:$O$301,96)),"")} | K100: {=IFERROR(INDEX(Alunos!$C:$C,SMALL(Alunos!$O$2:$O$301,96)),"")}
A101: {=IFERROR(INDEX(Boletos!$A:$A,SMALL(Boletos!$O$3:$O$3602,97)),"")} | B101: {=IFERROR(INDEX(Boletos!$B:$B,SMALL(Boletos!$O$3:$O$3602,97)),"")} | C101: {=IFERROR(INDEX(Boletos!$C:$C,SMALL(Boletos!$O$3:$O$3602,97)),"")} | D101: {=IFERROR(INDEX(Boletos!$D:$D,SMALL(Boletos!$O$3:$O$3602,97)),"")} | E101: {=IFERROR(INDEX(Boletos!$K:$K,SMALL(Boletos!$O$3:$O$3602,97)),"")} | F101: {=IFERROR(INDEX(Boletos!$L:$L,SMALL(Boletos!$O$3:$O$3602,97)),"")} | J101: {=IFERROR(INDEX(Alunos!$A:$A,SMALL(Alunos!$O$2:$O$301,97)),"")} | K101: {=IFERROR(INDEX(Alunos!$C:$C,SMALL(Alunos!$O$2:$O$301,97)),"")}
...

Sheet Config
A1: ="CONFIGURAÇÕES DA ESCOLA – "&B4
A2: Legenda: células em bege = você preenche. Texto preto = calcula sozinho.
A3: Nome da escola | B3: Escola Modelo (dados fictícios)
A4: Ano letivo | B4: 2026
A5: Dia de vencimento do boleto | B5: 10
A6: Multa por atraso | B6: 0.02 | D6: Multa máxima permitida em mensalidade: 2%
A7: Juros ao mês | B7: 0.01
A8: Tarifa por boleto pago | B8: 2.49 | D8: Confira a tarifa real no contrato da plataforma de cobrança / banco
A9: ="Saldo inicial do caixa (01/01/"&B4&")" | B9: 6000
A10: Plataforma de cobrança | B10: Plataforma de boletos
A12: ="Turmas e mensalidades "&B4 | D12: Atividades extras (mensal)
A13: Turma | B13: Mensalidade | D13: Atividade | E13: Valor mensal
A14: Maternal 2 | B14: 620 | D14: Judô | E14: 110
A15: Maternal 3 | B15: 640 | D15: Balé | E15: 120
A16: 1º Período | B16: 690
A17: 2º Período | B17: 710
A20: Categorias de despesa | D20: Categorias de receita
A21: Salários | D21: Matrícula
A22: Encargos | D22: Rematrícula
A23: Aluguel | D23: Material didático
A24: Energia | D24: Uniforme
A25: Água | D25: Eventos e festas
A26: Internet | D26: Passeios
A27: Material | D27: Cantina
A28: Manutenção | D28: Horário estendido
A29: Impostos | D29: Taxas e documentos
A30: Marketing | D30: Doações
A31: Tarifas bancárias | D31: Outros
A32: Outros
A36: Você pode adicionar categorias nas linhas vazias – elas aparecem nas listas sozinhas.

Sheet Alunos
A1: Nome do aluno | B1: Turma | C1: Responsável financeiro | D1: CPF do responsável | E1: Telefone | F1: Mensalidade | G1: Judô? | H1: Balé? | I1: Valor atividades | J1: Desconto (%) | K1: Valor do boleto | L1: Situação | M1: Mês de entrada | N1: Mês de saída | R1: Cadastre alunos novos na primeira linha vazia. Não reordene esta aba – a lista em ordem alfabética fica na aba Alunos A-Z.
A2: Laura Holanda (fictício) | B2: Maternal 2 | C2: Érica Holanda | E2: (00) 99133-9711 | F2: {=IF(B2="","",IFERROR(INDEX(Config!$B$14:$B$17,MATCH(B2,Config!$A$14:$A$17,0)),0))} | G2: Não | H2: Não | I2: =IF(A2="","",IF(G2="Sim",Config!$E$14,0)+IF(H2="Sim",Config!$E$15,0)) | K2: =IF(OR(A2="",L2="Inativo"),"",N(F2)*(1-N(J2))+N(I2)) | L2: Ativo | O2: =IF(AND(A2<>"",D2=""),ROW(),"") | P2: =IF(A2="","",COUNTIF($A$2:$A$301,"<"&A2)+COUNTIF($A$2:A2,A2))
A3: Gael Rezende (fictício) | B3: Maternal 3 | C3: Leandro Rezende | D3: ***.585.813-** | E3: (00) 92064-1994 | F3: {=IF(B3="","",IFERROR(INDEX(Config!$B$14:$B$17,MATCH(B3,Config!$A$14:$A$17,0)),0))} | G3: Não | H3: Não | I3: =IF(A3="","",IF(G3="Sim",Config!$E$14,0)+IF(H3="Sim",Config!$E$15,0)) | K3: =IF(OR(A3="",L3="Inativo"),"",N(F3)*(1-N(J3))+N(I3)) | L3: Ativo | O3: =IF(AND(A3<>"",D3=""),ROW(),"") | P3: =IF(A3="","",COUNTIF($A$2:$A$301,"<"&A3)+COUNTIF($A$2:A3,A3))
A4: Cecília Duarte (fictício) | B4: 1º Período | C4: Renata Duarte | D4: ***.240.938-** | E4: (00) 98053-5561 | F4: {=IF(B4="","",IFERROR(INDEX(Config!$B$14:$B$17,MATCH(B4,Config!$A$14:$A$17,0)),0))} | G4: Não | H4: Não | I4: =IF(A4="","",IF(G4="Sim",Config!$E$14,0)+IF(H4="Sim",Config!$E$15,0)) | K4: =IF(OR(A4="",L4="Inativo"),"",N(F4)*(1-N(J4))+N(I4)) | L4: Ativo | O4: =IF(AND(A4<>"",D4=""),ROW(),"") | P4: =IF(A4="","",COUNTIF($A$2:$A$301,"<"&A4)+COUNTIF($A$2:A4,A4))
A5: Elisa Esteves (fictício) | B5: 2º Período | C5: Zilda Esteves | D5: ***.593.749-** | E5: (00) 97560-2019 | F5: {=IF(B5="","",IFERROR(INDEX(Config!$B$14:$B$17,MATCH(B5,Config!$A$14:$A$17,0)),0))} | G5: Sim | H5: Não | I5: =IF(A5="","",IF(G5="Sim",Config!$E$14,0)+IF(H5="Sim",Config!$E$15,0)) | K5: =IF(OR(A5="",L5="Inativo"),"",N(F5)*(1-N(J5))+N(I5)) | L5: Ativo | O5: =IF(AND(A5<>"",D5=""),ROW(),"") | P5: =IF(A5="","",COUNTIF($A$2:$A$301,"<"&A5)+COUNTIF($A$2:A5,A5))
A6: Heitor Prado (fictício) | B6: Maternal 2 | C6: Fábio Prado | D6: ***.699.564-** | E6: (00) 96924-5911 | F6: {=IF(B6="","",IFERROR(INDEX(Config!$B$14:$B$17,MATCH(B6,Config!$A$14:$A$17,0)),0))} | G6: Sim | H6: Sim | I6: =IF(A6="","",IF(G6="Sim",Config!$E$14,0)+IF(H6="Sim",Config!$E$15,0)) | K6: =IF(OR(A6="",L6="Inativo"),"",N(F6)*(1-N(J6))+N(I6)) | L6: Ativo | O6: =IF(AND(A6<>"",D6=""),ROW(),"") | P6: =IF(A6="","",COUNTIF($A$2:$A$301,"<"&A6)+COUNTIF($A$2:A6,A6))
A7: Samuel Macedo (fictício) | B7: 1º Período | C7: Paulo Macedo | D7: ***.992.608-** | E7: (00) 92320-3725 | F7: {=IF(B7="","",IFERROR(INDEX(Config!$B$14:$B$17,MATCH(B7,Config!$A$14:$A$17,0)),0))} | G7: Não | H7: Não | I7: =IF(A7="","",IF(G7="Sim",Config!$E$14,0)+IF(H7="Sim",Config!$E$15,0)) | K7: =IF(OR(A7="",L7="Inativo"),"",N(F7)*(1-N(J7))+N(I7)) | L7: Ativo | O7: =IF(AND(A7<>"",D7=""),ROW(),"") | P7: =IF(A7="","",COUNTIF($A$2:$A$301,"<"&A7)+COUNTIF($A$2:A7,A7))
A8: Valentina Zanetti (fictício) | B8: Maternal 3 | C8: Gisele Zanetti | D8: ***.898.349-** | E8: (00) 92341-5919 | F8: {=IF(B8="","",IFERROR(INDEX(Config!$B$14:$B$17,MATCH(B8,Config!$A$14:$A$17,0)),0))} | G8: Não | H8: Não | I8: =IF(A8="","",IF(G8="Sim",Config!$E$14,0)+IF(H8="Sim",Config!$E$15,0)) | K8: =IF(OR(A8="",L8="Inativo"),"",N(F8)*(1-N(J8))+N(I8)) | L8: Ativo | O8: =IF(AND(A8<>"",D8=""),ROW(),"") | P8: =IF(A8="","",COUNTIF($A$2:$A$301,"<"&A8)+COUNTIF($A$2:A8,A8))
A9: Sophia Ornelas (fictício) | B9: Maternal 3 | C9: Karen Ornelas | D9: ***.693.916-** | E9: (00) 98474-2126 | F9: {=IF(B9="","",IFERROR(INDEX(Config!$B$14:$B$17,MATCH(B9,Config!$A$14:$A$17,0)),0))} | G9: Não | H9: Não | I9: =IF(A9="","",IF(G9="Sim",Config!$E$14,0)+IF(H9="Sim",Config!$E$15,0)) | K9: =IF(OR(A9="",L9="Inativo"),"",N(F9)*(1-N(J9))+N(I9)) | L9: Ativo | O9: =IF(AND(A9<>"",D9=""),ROW(),"") | P9: =IF(A9="","",COUNTIF($A$2:$A$301,"<"&A9)+COUNTIF($A$2:A9,A9))
A10: Pedro Barros (fictício) | B10: 1º Período | C10: Vítor Barros | D10: ***.369.388-** | E10: (00) 91067-3386 | F10: {=IF(B10="","",IFERROR(INDEX(Config!$B$14:$B$17,MATCH(B10,Config!$A$14:$A$17,0)),0))} | G10: Não | H10: Não | I10: =IF(A10="","",IF(G10="Sim",Config!$E$14,0)+IF(H10="Sim",Config!$E$15,0)) | K10: =IF(OR(A10="",L10="Inativo"),"",N(F10)*(1-N(J10))+N(I10)) | L10: Ativo | O10: =IF(AND(A10<>"",D10=""),ROW(),"") | P10: =IF(A10="","",COUNTIF($A$2:$A$301,"<"&A10)+COUNTIF($A$2:A10,A10))
A11: Lívia Jardim (fictício) | B11: 1º Período | C11: Olívia Jardim | D11: ***.160.323-** | E11: (00) 95709-3119 | F11: {=IF(B11="","",IFERROR(INDEX(Config!$B$14:$B$17,MATCH(B11,Config!$A$14:$A$17,0)),0))} | G11: Não | H11: Não | I11: =IF(A11="","",IF(G11="Sim",Config!$E$14,0)+IF(H11="Sim",Config!$E$15,0)) | K11: =IF(OR(A11="",L11="Inativo"),"",N(F11)*(1-N(J11))+N(I11)) | L11: Ativo | O11: =IF(AND(A11<>"",D11=""),ROW(),"") | P11: =IF(A11="","",COUNTIF($A$2:$A$301,"<"&A11)+COUNTIF($A$2:A11,A11))
A12: Isabela Ibiapina (fictício) | B12: Maternal 3 | C12: Marta Ibiapina | D12: ***.691.797-** | E12: (00) 98301-5662 | F12: {=IF(B12="","",IFERROR(INDEX(Config!$B$14:$B$17,MATCH(B12,Config!$A$14:$A$17,0)),0))} | G12: Não | H12: Não | I12: =IF(A12="","",IF(G12="Sim",Config!$E$14,0)+IF(H12="Sim",Config!$E$15,0)) | K12: =IF(OR(A12="",L12="Inativo"),"",N(F12)*(1-N(J12))+N(I12)) | L12: Ativo | O12: =IF(AND(A12<>"",D12=""),ROW(),"") | P12: =IF(A12="","",COUNTIF($A$2:$A$301,"<"&A12)+COUNTIF($A$2:A12,A12))
A13: Gabriel Nogueira (fictício) | B13: 2º Período | C13: Yuri Nogueira | D13: ***.857.155-** | E13: (00) 98481-7428 | F13: {=IF(B13="","",IFERROR(INDEX(Config!$B$14:$B$17,MATCH(B13,Config!$A$14:$A$17,0)),0))} | G13: Não | H13: Não | I13: =IF(A13="","",IF(G13="Sim",Config!$E$14,0)+IF(H13="Sim",Config!$E$15,0)) | K13: =IF(OR(A13="",L13="Inativo"),"",N(F13)*(1-N(J13))+N(I13)) | L13: Ativo | M13: Mar | O13: =IF(AND(A13<>"",D13=""),ROW(),"") | P13: =IF(A13="","",COUNTIF($A$2:$A$301,"<"&A13)+COUNTIF($A$2:A13,A13))
A14: Miguel Teles (fictício) | B14: Maternal 2 | C14: Bruno Teles | D14: ***.670.979-** | E14: (00) 93181-5744 | F14: {=IF(B14="","",IFERROR(INDEX(Config!$B$14:$B$17,MATCH(B14,Config!$A$14:$A$17,0)),0))} | G14: Não | H14: Não | I14: =IF(A14="","",IF(G14="Sim",Config!$E$14,0)+IF(H14="Sim",Config!$E$15,0)) | K14: =IF(OR(A14="",L14="Inativo"),"",N(F14)*(1-N(J14))+N(I14)) | L14: Ativo | O14: =IF(AND(A14<>"",D14=""),ROW(),"") | P14: =IF(A14="","",COUNTIF($A$2:$A$301,"<"&A14)+COUNTIF($A$2:A14,A14))
A15: Alice Farias (fictício) | B15: Maternal 2 | C15: Ana Farias | D15: ***.328.745-** | E15: (00) 92013-7499 | F15: {=IF(B15="","",IFERROR(INDEX(Config!$B$14:$B$17,MATCH(B15,Config!$A$14:$A$17,0)),0))} | G15: Sim | H15: Sim | I15: =IF(A15="","",IF(G15="Sim",Config!$E$14,0)+IF(H15="Sim",Config!$E$15,0)) | K15: =IF(OR(A15="",L15="Inativo"),"",N(F15)*(1-N(J15))+N(I15)) | L15: Ativo | O15: =IF(AND(A15<>"",D15=""),ROW(),"") | P15: =IF(A15="","",COUNTIF($A$2:$A$301,"<"&A15)+COUNTIF($A$2:A15,A15))
A16: Davi Uchôa (fictício) | B16: Maternal 3 | C16: João Uchôa | D16: ***.179.882-** | E16: (00) 96140-6572 | F16: {=IF(B16="","",IFERROR(INDEX(Config!$B$14:$B$17,MATCH(B16,Config!$A$14:$A$17,0)),0))} | G16: Não | H16: Não | I16: =IF(A16="","",IF(G16="Sim",Config!$E$14,0)+IF(H16="Sim",Config!$E$15,0)) | J16: 0.1 | K16: =IF(OR(A16="",L16="Inativo"),"",N(F16)*(1-N(J16))+N(I16)) | L16: Ativo | O16: =IF(AND(A16<>"",D16=""),ROW(),"") | P16: =IF(A16="","",COUNTIF($A$2:$A$301,"<"&A16)+COUNTIF($A$2:A16,A16))
A17: Arthur Queiroz (fictício) | B17: Maternal 2 | C17: Diego Queiroz | D17: ***.481.199-** | E17: (00) 99974-2028 | F17: {=IF(B17="","",IFERROR(INDEX(Config!$B$14:$B$17,MATCH(B17,Config!$A$14:$A$17,0)),0))} | G17: Não | H17: Não | I17: =IF(A17="","",IF(G17="Sim",Config!$E$14,0)+IF(H17="Sim",Config!$E$15,0)) | K17: =IF(OR(A17="",L17="Inativo"),"",N(F17)*(1-N(J17))+N(I17)) | L17: Ativo | O17: =IF(AND(A17<>"",D17=""),ROW(),"") | P17: =IF(A17="","",COUNTIF($A$2:$A$301,"<"&A17)+COUNTIF($A$2:A17,A17))
A18: Theo Xavier (fictício) | B18: Maternal 3 | C18: Henrique Xavier | D18: ***.846.559-** | E18: (00) 95717-2199 | F18: {=IF(B18="","",IFERROR(INDEX(Config!$B$14:$B$17,MATCH(B18,Config!$A$14:$A$17,0)),0))} | G18: Sim | H18: Não | I18: =IF(A18="","",IF(G18="Sim",Config!$E$14,0)+IF(H18="Sim",Config!$E$15,0)) | K18: =IF(OR(A18="",L18="Inativo"),"",N(F18)*(1-N(J18))+N(I18)) | L18: Ativo | O18: =IF(AND(A18<>"",D18=""),ROW(),"") | P18: =IF(A18="","",COUNTIF($A$2:$A$301,"<"&A18)+COUNTIF($A$2:A18,A18))
A19: Luna Vasconcelos (fictício) | B19: 2º Período | C19: Wanda Vasconcelos | D19: ***.679.426-** | E19: (00) 93056-9445 | F19: {=IF(B19="","",IFERROR(INDEX(Config!$B$14:$B$17,MATCH(B19,Config!$A$14:$A$17,0)),0))} | G19: Não | H19: Não | I19: =IF(A19="","",IF(G19="Sim",Config!$E$14,0)+IF(H19="Sim",Config!$E$15,0)) | K19: =IF(OR(A19="",L19="Inativo"),"",N(F19)*(1-N(J19))+N(I19)) | L19: Ativo | O19: =IF(AND(A19<>"",D19=""),ROW(),"") | P19: =IF(A19="","",COUNTIF($A$2:$A$301,"<"&A19)+COUNTIF($A$2:A19,A19))
A20: Maitê Cardoso (fictício) | B20: 1º Período | C20: Tatiane Cardoso | D20: ***.337.774-** | E20: (00) 94822-1197 | F20: {=IF(B20="","",IFERROR(INDEX(Config!$B$14:$B$17,MATCH(B20,Config!$A$14:$A$17,0)),0))} | G20: Não | H20: Não | I20: =IF(A20="","",IF(G20="Sim",Config!$E$14,0)+IF(H20="Sim",Config!$E$15,0)) | K20: =IF(OR(A20="",L20="Inativo"),"",N(F20)*(1-N(J20))+N(I20)) | L20: Ativo | O20: =IF(AND(A20<>"",D20=""),ROW(),"") | P20: =IF(A20="","",COUNTIF($A$2:$A$301,"<"&A20)+COUNTIF($A$2:A20,A20))
A21: Lucas Sales (fictício) | B21: 1º Período | C21: Sérgio Sales | E21: (00) 97233-4780 | F21: {=IF(B21="","",IFERROR(INDEX(Config!$B$14:$B$17,MATCH(B21,Config!$A$14:$A$17,0)),0))} | G21: Sim | H21: Sim | I21: =IF(A21="","",IF(G21="Sim",Config!$E$14,0)+IF(H21="Sim",Config!$E$15,0)) | K21: =IF(OR(A21="",L21="Inativo"),"",N(F21)*(1-N(J21))+N(I21)) | L21: Ativo | O21: =IF(AND(A21<>"",D21=""),ROW(),"") | P21: =IF(A21="","",COUNTIF($A$2:$A$301,"<"&A21)+COUNTIF($A$2:A21,A21))
A22: Helena Yamada (fictício) | B22: Maternal 2 | C22: Carla Yamada | D22: ***.684.415-** | E22: (00) 93961-2688 | F22: {=IF(B22="","",IFERROR(INDEX(Config!$B$14:$B$17,MATCH(B22,Config!$A$14:$A$17,0)),0))} | G22: Não | H22: Não | I22: =IF(A22="","",IF(G22="Sim",Config!$E$14,0)+IF(H22="Sim",Config!$E$15,0)) | K22: =IF(OR(A22="",L22="Inativo"),"",N(F22)*(1-N(J22))+N(I22)) | L22: Bolsista | O22: =IF(AND(A22<>"",D22=""),ROW(),"") | P22: =IF(A22="","",COUNTIF($A$2:$A$301,"<"&A22)+COUNTIF($A$2:A22,A22))
A23: Rafael Leal (fictício) | B23: 2º Período | C23: Márcio Leal | D23: ***.551.266-** | E23: (00) 92801-6571 | F23: {=IF(B23="","",IFERROR(INDEX(Config!$B$14:$B$17,MATCH(B23,Config!$A$14:$A$17,0)),0))} | G23: Não | H23: Sim | I23: =IF(A23="","",IF(G23="Sim",Config!$E$14,0)+IF(H23="Sim",Config!$E$15,0)) | K23: =IF(OR(A23="",L23="Inativo"),"",N(F23)*(1-N(J23))+N(I23)) | L23: Ativo | O23: =IF(AND(A23<>"",D23=""),ROW(),"") | P23: =IF(A23="","",COUNTIF($A$2:$A$301,"<"&A23)+COUNTIF($A$2:A23,A23))
A24: Manuela Gomes (fictício) | B24: Maternal 3 | C24: Ingrid Gomes | D24: ***.875.450-** | E24: (00) 93490-9011 | F24: {=IF(B24="","",IFERROR(INDEX(Config!$B$14:$B$17,MATCH(B24,Config!$A$14:$A$17,0)),0))} | G24: Não | H24: Não | I24: =IF(A24="","",IF(G24="Sim",Config!$E$14,0)+IF(H24="Sim",Config!$E$15,0)) | J24: 0.1 | K24: =IF(OR(A24="",L24="Inativo"),"",N(F24)*(1-N(J24))+N(I24)) | L24: Ativo | O24: =IF(AND(A24<>"",D24=""),ROW(),"") | P24: =IF(A24="","",COUNTIF($A$2:$A$301,"<"&A24)+COUNTIF($A$2:A24,A24))
A25: Bernardo Almeida (fictício) | B25: Maternal 3 | C25: Nelson Almeida | D25: ***.455.123-** | E25: (00) 98564-6823 | F25: {=IF(B25="","",IFERROR(INDEX(Config!$B$14:$B$17,MATCH(B25,Config!$A$14:$A$17,0)),0))} | G25: Sim | H25: Sim | I25: =IF(A25="","",IF(G25="Sim",Config!$E$14,0)+IF(H25="Sim",Config!$E$15,0)) | K25: =IF(OR(A25="",L25="Inativo"),"",N(F25)*(1-N(J25))+N(I25)) | L25: Ativo | N25: Jun | O25: =IF(AND(A25<>"",D25=""),ROW(),"") | P25: =IF(A25="","",COUNTIF($A$2:$A$301,"<"&A25)+COUNTIF($A$2:A25,A25))
F26: {=IF(B26="","",IFERROR(INDEX(Config!$B$14:$B$17,MATCH(B26,Config!$A$14:$A$17,0)),0))} | I26: =IF(A26="","",IF(G26="Sim",Config!$E$14,0)+IF(H26="Sim",Config!$E$15,0)) | K26: =IF(OR(A26="",L26="Inativo"),"",N(F26)*(1-N(J26))+N(I26)) | O26: =IF(AND(A26<>"",D26=""),ROW(),"") | P26: =IF(A26="","",COUNTIF($A$2:$A$301,"<"&A26)+COUNTIF($A$2:A26,A26))
F27: {=IF(B27="","",IFERROR(INDEX(Config!$B$14:$B$17,MATCH(B27,Config!$A$14:$A$17,0)),0))} | I27: =IF(A27="","",IF(G27="Sim",Config!$E$14,0)+IF(H27="Sim",Config!$E$15,0)) | K27: =IF(OR(A27="",L27="Inativo"),"",N(F27)*(1-N(J27))+N(I27)) | O27: =IF(AND(A27<>"",D27=""),ROW(),"") | P27: =IF(A27="","",COUNTIF($A$2:$A$301,"<"&A27)+COUNTIF($A$2:A27,A27))
F28: {=IF(B28="","",IFERROR(INDEX(Config!$B$14:$B$17,MATCH(B28,Config!$A$14:$A$17,0)),0))} | I28: =IF(A28="","",IF(G28="Sim",Config!$E$14,0)+IF(H28="Sim",Config!$E$15,0)) | K28: =IF(OR(A28="",L28="Inativo"),"",N(F28)*(1-N(J28))+N(I28)) | O28: =IF(AND(A28<>"",D28=""),ROW(),"") | P28: =IF(A28="","",COUNTIF($A$2:$A$301,"<"&A28)+COUNTIF($A$2:A28,A28))
F29: {=IF(B29="","",IFERROR(INDEX(Config!$B$14:$B$17,MATCH(B29,Config!$A$14:$A$17,0)),0))} | I29: =IF(A29="","",IF(G29="Sim",Config!$E$14,0)+IF(H29="Sim",Config!$E$15,0)) | K29: =IF(OR(A29="",L29="Inativo"),"",N(F29)*(1-N(J29))+N(I29)) | O29: =IF(AND(A29<>"",D29=""),ROW(),"") | P29: =IF(A29="","",COUNTIF($A$2:$A$301,"<"&A29)+COUNTIF($A$2:A29,A29))
F30: {=IF(B30="","",IFERROR(INDEX(Config!$B$14:$B$17,MATCH(B30,Config!$A$14:$A$17,0)),0))} | I30: =IF(A30="","",IF(G30="Sim",Config!$E$14,0)+IF(H30="Sim",Config!$E$15,0)) | K30: =IF(OR(A30="",L30="Inativo"),"",N(F30)*(1-N(J30))+N(I30)) | O30: =IF(AND(A30<>"",D30=""),ROW(),"") | P30: =IF(A30="","",COUNTIF($A$2:$A$301,"<"&A30)+COUNTIF($A$2:A30,A30))
F31: {=IF(B31="","",IFERROR(INDEX(Config!$B$14:$B$17,MATCH(B31,Config!$A$14:$A$17,0)),0))} | I31: =IF(A31="","",IF(G31="Sim",Config!$E$14,0)+IF(H31="Sim",Config!$E$15,0)) | K31: =IF(OR(A31="",L31="Inativo"),"",N(F31)*(1-N(J31))+N(I31)) | O31: =IF(AND(A31<>"",D31=""),ROW(),"") | P31: =IF(A31="","",COUNTIF($A$2:$A$301,"<"&A31)+COUNTIF($A$2:A31,A31))
F32: {=IF(B32="","",IFERROR(INDEX(Config!$B$14:$B$17,MATCH(B32,Config!$A$14:$A$17,0)),0))} | I32: =IF(A32="","",IF(G32="Sim",Config!$E$14,0)+IF(H32="Sim",Config!$E$15,0)) | K32: =IF(OR(A32="",L32="Inativo"),"",N(F32)*(1-N(J32))+N(I32)) | O32: =IF(AND(A32<>"",D32=""),ROW(),"") | P32: =IF(A32="","",COUNTIF($A$2:$A$301,"<"&A32)+COUNTIF($A$2:A32,A32))
F33: {=IF(B33="","",IFERROR(INDEX(Config!$B$14:$B$17,MATCH(B33,Config!$A$14:$A$17,0)),0))} | I33: =IF(A33="","",IF(G33="Sim",Config!$E$14,0)+IF(H33="Sim",Config!$E$15,0)) | K33: =IF(OR(A33="",L33="Inativo"),"",N(F33)*(1-N(J33))+N(I33)) | O33: =IF(AND(A33<>"",D33=""),ROW(),"") | P33: =IF(A33="","",COUNTIF($A$2:$A$301,"<"&A33)+COUNTIF($A$2:A33,A33))
F34: {=IF(B34="","",IFERROR(INDEX(Config!$B$14:$B$17,MATCH(B34,Config!$A$14:$A$17,0)),0))} | I34: =IF(A34="","",IF(G34="Sim",Config!$E$14,0)+IF(H34="Sim",Config!$E$15,0)) | K34: =IF(OR(A34="",L34="Inativo"),"",N(F34)*(1-N(J34))+N(I34)) | O34: =IF(AND(A34<>"",D34=""),ROW(),"") | P34: =IF(A34="","",COUNTIF($A$2:$A$301,"<"&A34)+COUNTIF($A$2:A34,A34))
F35: {=IF(B35="","",IFERROR(INDEX(Config!$B$14:$B$17,MATCH(B35,Config!$A$14:$A$17,0)),0))} | I35: =IF(A35="","",IF(G35="Sim",Config!$E$14,0)+IF(H35="Sim",Config!$E$15,0)) | K35: =IF(OR(A35="",L35="Inativo"),"",N(F35)*(1-N(J35))+N(I35)) | O35: =IF(AND(A35<>"",D35=""),ROW(),"") | P35: =IF(A35="","",COUNTIF($A$2:$A$301,"<"&A35)+COUNTIF($A$2:A35,A35))
F36: {=IF(B36="","",IFERROR(INDEX(Config!$B$14:$B$17,MATCH(B36,Config!$A$14:$A$17,0)),0))} | I36: =IF(A36="","",IF(G36="Sim",Config!$E$14,0)+IF(H36="Sim",Config!$E$15,0)) | K36: =IF(OR(A36="",L36="Inativo"),"",N(F36)*(1-N(J36))+N(I36)) | O36: =IF(AND(A36<>"",D36=""),ROW(),"") | P36: =IF(A36="","",COUNTIF($A$2:$A$301,"<"&A36)+COUNTIF($A$2:A36,A36))
F37: {=IF(B37="","",IFERROR(INDEX(Config!$B$14:$B$17,MATCH(B37,Config!$A$14:$A$17,0)),0))} | I37: =IF(A37="","",IF(G37="Sim",Config!$E$14,0)+IF(H37="Sim",Config!$E$15,0)) | K37: =IF(OR(A37="",L37="Inativo"),"",N(F37)*(1-N(J37))+N(I37)) | O37: =IF(AND(A37<>"",D37=""),ROW(),"") | P37: =IF(A37="","",COUNTIF($A$2:$A$301,"<"&A37)+COUNTIF($A$2:A37,A37))
... F301: {=IF(B301="","",IFERROR(INDEX(Config!$B$14:$B$17,MATCH(B301,Config!$A$14:$A$17,0)),0))} | I301: =IF(A301="","",IF(G301="Sim",Config!$E$14,0)+IF(H301="Sim",Config!$E$15,0)) | K301: =IF(OR(A301="",L301="Inativo"),"",N(F301)*(1-N(J301))+N(I301)) | O301: =IF(AND(A301<>"",D301=""),ROW(),"") | P301: =IF(A301="","",COUNTIF($A$2:$A$301,"<"&A301)+COUNTIF($A$2:A301,A301))

Sheet Alunos A-Z
A1: ALUNOS EM ORDEM ALFABÉTICA – atualiza sozinha
A2: Só para consulta. Para cadastrar ou alterar, use a aba Alunos – o nome entra aqui automaticamente na posição certa.
A3: Nº | B3: Aluno | C3: Turma | D3: Responsável financeiro | E3: Judô? | F3: Balé? | G3: Valor do boleto | H3: Situação
A4: =IF(ISNA(MATCH(1,Alunos!$P$2:$P$301,0)),"",1) | B4: {=IFERROR(INDEX(Alunos!$A$2:$A$301,MATCH(1,Alunos!$P$2:$P$301,0))&"","")} | C4: {=IFERROR(INDEX(Alunos!$B$2:$B$301,MATCH(1,Alunos!$P$2:$P$301,0))&"","")} | D4: {=IFERROR(INDEX(Alunos!$C$2:$C$301,MATCH(1,Alunos!$P$2:$P$301,0))&"","")} | E4: {=IFERROR(INDEX(Alunos!$G$2:$G$301,MATCH(1,Alunos!$P$2:$P$301,0))&"","")} | F4: {=IFERROR(INDEX(Alunos!$H$2:$H$301,MATCH(1,Alunos!$P$2:$P$301,0))&"","")} | G4: {=IFERROR(INDEX(Alunos!$K$2:$K$301,MATCH(1,Alunos!$P$2:$P$301,0)),"")} | H4: {=IFERROR(INDEX(Alunos!$L$2:$L$301,MATCH(1,Alunos!$P$2:$P$301,0))&"","")}
A5: =IF(ISNA(MATCH(2,Alunos!$P$2:$P$301,0)),"",2) | B5: {=IFERROR(INDEX(Alunos!$A$2:$A$301,MATCH(2,Alunos!$P$2:$P$301,0))&"","")} | C5: {=IFERROR(INDEX(Alunos!$B$2:$B$301,MATCH(2,Alunos!$P$2:$P$301,0))&"","")} | D5: {=IFERROR(INDEX(Alunos!$C$2:$C$301,MATCH(2,Alunos!$P$2:$P$301,0))&"","")} | E5: {=IFERROR(INDEX(Alunos!$G$2:$G$301,MATCH(2,Alunos!$P$2:$P$301,0))&"","")} | F5: {=IFERROR(INDEX(Alunos!$H$2:$H$301,MATCH(2,Alunos!$P$2:$P$301,0))&"","")} | G5: {=IFERROR(INDEX(Alunos!$K$2:$K$301,MATCH(2,Alunos!$P$2:$P$301,0)),"")} | H5: {=IFERROR(INDEX(Alunos!$L$2:$L$301,MATCH(2,Alunos!$P$2:$P$301,0))&"","")}
A6: =IF(ISNA(MATCH(3,Alunos!$P$2:$P$301,0)),"",3) | B6: {=IFERROR(INDEX(Alunos!$A$2:$A$301,MATCH(3,Alunos!$P$2:$P$301,0))&"","")} | C6: {=IFERROR(INDEX(Alunos!$B$2:$B$301,MATCH(3,Alunos!$P$2:$P$301,0))&"","")} | D6: {=IFERROR(INDEX(Alunos!$C$2:$C$301,MATCH(3,Alunos!$P$2:$P$301,0))&"","")} | E6: {=IFERROR(INDEX(Alunos!$G$2:$G$301,MATCH(3,Alunos!$P$2:$P$301,0))&"","")} | F6: {=IFERROR(INDEX(Alunos!$H$2:$H$301,MATCH(3,Alunos!$P$2:$P$301,0))&"","")} | G6: {=IFERROR(INDEX(Alunos!$K$2:$K$301,MATCH(3,Alunos!$P$2:$P$301,0)),"")} | H6: {=IFERROR(INDEX(Alunos!$L$2:$L$301,MATCH(3,Alunos!$P$2:$P$301,0))&"","")}
A7: =IF(ISNA(MATCH(4,Alunos!$P$2:$P$301,0)),"",4) | B7: {=IFERROR(INDEX(Alunos!$A$2:$A$301,MATCH(4,Alunos!$P$2:$P$301,0))&"","")} | C7: {=IFERROR(INDEX(Alunos!$B$2:$B$301,MATCH(4,Alunos!$P$2:$P$301,0))&"","")} | D7: {=IFERROR(INDEX(Alunos!$C$2:$C$301,MATCH(4,Alunos!$P$2:$P$301,0))&"","")} | E7: {=IFERROR(INDEX(Alunos!$G$2:$G$301,MATCH(4,Alunos!$P$2:$P$301,0))&"","")} | F7: {=IFERROR(INDEX(Alunos!$H$2:$H$301,MATCH(4,Alunos!$P$2:$P$301,0))&"","")} | G7: {=IFERROR(INDEX(Alunos!$K$2:$K$301,MATCH(4,Alunos!$P$2:$P$301,0)),"")} | H7: {=IFERROR(INDEX(Alunos!$L$2:$L$301,MATCH(4,Alunos!$P$2:$P$301,0))&"","")}
A8: =IF(ISNA(MATCH(5,Alunos!$P$2:$P$301,0)),"",5) | B8: {=IFERROR(INDEX(Alunos!$A$2:$A$301,MATCH(5,Alunos!$P$2:$P$301,0))&"","")} | C8: {=IFERROR(INDEX(Alunos!$B$2:$B$301,MATCH(5,Alunos!$P$2:$P$301,0))&"","")} | D8: {=IFERROR(INDEX(Alunos!$C$2:$C$301,MATCH(5,Alunos!$P$2:$P$301,0))&"","")} | E8: {=IFERROR(INDEX(Alunos!$G$2:$G$301,MATCH(5,Alunos!$P$2:$P$301,0))&"","")} | F8: {=IFERROR(INDEX(Alunos!$H$2:$H$301,MATCH(5,Alunos!$P$2:$P$301,0))&"","")} | G8: {=IFERROR(INDEX(Alunos!$K$2:$K$301,MATCH(5,Alunos!$P$2:$P$301,0)),"")} | H8: {=IFERROR(INDEX(Alunos!$L$2:$L$301,MATCH(5,Alunos!$P$2:$P$301,0))&"","")}
A9: =IF(ISNA(MATCH(6,Alunos!$P$2:$P$301,0)),"",6) | B9: {=IFERROR(INDEX(Alunos!$A$2:$A$301,MATCH(6,Alunos!$P$2:$P$301,0))&"","")} | C9: {=IFERROR(INDEX(Alunos!$B$2:$B$301,MATCH(6,Alunos!$P$2:$P$301,0))&"","")} | D9: {=IFERROR(INDEX(Alunos!$C$2:$C$301,MATCH(6,Alunos!$P$2:$P$301,0))&"","")} | E9: {=IFERROR(INDEX(Alunos!$G$2:$G$301,MATCH(6,Alunos!$P$2:$P$301,0))&"","")} | F9: {=IFERROR(INDEX(Alunos!$H$2:$H$301,MATCH(6,Alunos!$P$2:$P$301,0))&"","")} | G9: {=IFERROR(INDEX(Alunos!$K$2:$K$301,MATCH(6,Alunos!$P$2:$P$301,0)),"")} | H9: {=IFERROR(INDEX(Alunos!$L$2:$L$301,MATCH(6,Alunos!$P$2:$P$301,0))&"","")}
A10: =IF(ISNA(MATCH(7,Alunos!$P$2:$P$301,0)),"",7) | B10: {=IFERROR(INDEX(Alunos!$A$2:$A$301,MATCH(7,Alunos!$P$2:$P$301,0))&"","")} | C10: {=IFERROR(INDEX(Alunos!$B$2:$B$301,MATCH(7,Alunos!$P$2:$P$301,0))&"","")} | D10: {=IFERROR(INDEX(Alunos!$C$2:$C$301,MATCH(7,Alunos!$P$2:$P$301,0))&"","")} | E10: {=IFERROR(INDEX(Alunos!$G$2:$G$301,MATCH(7,Alunos!$P$2:$P$301,0))&"","")} | F10: {=IFERROR(INDEX(Alunos!$H$2:$H$301,MATCH(7,Alunos!$P$2:$P$301,0))&"","")} | G10: {=IFERROR(INDEX(Alunos!$K$2:$K$301,MATCH(7,Alunos!$P$2:$P$301,0)),"")} | H10: {=IFERROR(INDEX(Alunos!$L$2:$L$301,MATCH(7,Alunos!$P$2:$P$301,0))&"","")}
A11: =IF(ISNA(MATCH(8,Alunos!$P$2:$P$301,0)),"",8) | B11: {=IFERROR(INDEX(Alunos!$A$2:$A$301,MATCH(8,Alunos!$P$2:$P$301,0))&"","")} | C11: {=IFERROR(INDEX(Alunos!$B$2:$B$301,MATCH(8,Alunos!$P$2:$P$301,0))&"","")} | D11: {=IFERROR(INDEX(Alunos!$C$2:$C$301,MATCH(8,Alunos!$P$2:$P$301,0))&"","")} | E11: {=IFERROR(INDEX(Alunos!$G$2:$G$301,MATCH(8,Alunos!$P$2:$P$301,0))&"","")} | F11: {=IFERROR(INDEX(Alunos!$H$2:$H$301,MATCH(8,Alunos!$P$2:$P$301,0))&"","")} | G11: {=IFERROR(INDEX(Alunos!$K$2:$K$301,MATCH(8,Alunos!$P$2:$P$301,0)),"")} | H11: {=IFERROR(INDEX(Alunos!$L$2:$L$301,MATCH(8,Alunos!$P$2:$P$301,0))&"","")}
A12: =IF(ISNA(MATCH(9,Alunos!$P$2:$P$301,0)),"",9) | B12: {=IFERROR(INDEX(Alunos!$A$2:$A$301,MATCH(9,Alunos!$P$2:$P$301,0))&"","")} | C12: {=IFERROR(INDEX(Alunos!$B$2:$B$301,MATCH(9,Alunos!$P$2:$P$301,0))&"","")} | D12: {=IFERROR(INDEX(Alunos!$C$2:$C$301,MATCH(9,Alunos!$P$2:$P$301,0))&"","")} | E12: {=IFERROR(INDEX(Alunos!$G$2:$G$301,MATCH(9,Alunos!$P$2:$P$301,0))&"","")} | F12: {=IFERROR(INDEX(Alunos!$H$2:$H$301,MATCH(9,Alunos!$P$2:$P$301,0))&"","")} | G12: {=IFERROR(INDEX(Alunos!$K$2:$K$301,MATCH(9,Alunos!$P$2:$P$301,0)),"")} | H12: {=IFERROR(INDEX(Alunos!$L$2:$L$301,MATCH(9,Alunos!$P$2:$P$301,0))&"","")}
A13: =IF(ISNA(MATCH(10,Alunos!$P$2:$P$301,0)),"",10) | B13: {=IFERROR(INDEX(Alunos!$A$2:$A$301,MATCH(10,Alunos!$P$2:$P$301,0))&"","")} | C13: {=IFERROR(INDEX(Alunos!$B$2:$B$301,MATCH(10,Alunos!$P$2:$P$301,0))&"","")} | D13: {=IFERROR(INDEX(Alunos!$C$2:$C$301,MATCH(10,Alunos!$P$2:$P$301,0))&"","")} | E13: {=IFERROR(INDEX(Alunos!$G$2:$G$301,MATCH(10,Alunos!$P$2:$P$301,0))&"","")} | F13: {=IFERROR(INDEX(Alunos!$H$2:$H$301,MATCH(10,Alunos!$P$2:$P$301,0))&"","")} | G13: {=IFERROR(INDEX(Alunos!$K$2:$K$301,MATCH(10,Alunos!$P$2:$P$301,0)),"")} | H13: {=IFERROR(INDEX(Alunos!$L$2:$L$301,MATCH(10,Alunos!$P$2:$P$301,0))&"","")}
A14: =IF(ISNA(MATCH(11,Alunos!$P$2:$P$301,0)),"",11) | B14: {=IFERROR(INDEX(Alunos!$A$2:$A$301,MATCH(11,Alunos!$P$2:$P$301,0))&"","")} | C14: {=IFERROR(INDEX(Alunos!$B$2:$B$301,MATCH(11,Alunos!$P$2:$P$301,0))&"","")} | D14: {=IFERROR(INDEX(Alunos!$C$2:$C$301,MATCH(11,Alunos!$P$2:$P$301,0))&"","")} | E14: {=IFERROR(INDEX(Alunos!$G$2:$G$301,MATCH(11,Alunos!$P$2:$P$301,0))&"","")} | F14: {=IFERROR(INDEX(Alunos!$H$2:$H$301,MATCH(11,Alunos!$P$2:$P$301,0))&"","")} | G14: {=IFERROR(INDEX(Alunos!$K$2:$K$301,MATCH(11,Alunos!$P$2:$P$301,0)),"")} | H14: {=IFERROR(INDEX(Alunos!$L$2:$L$301,MATCH(11,Alunos!$P$2:$P$301,0))&"","")}
A15: =IF(ISNA(MATCH(12,Alunos!$P$2:$P$301,0)),"",12) | B15: {=IFERROR(INDEX(Alunos!$A$2:$A$301,MATCH(12,Alunos!$P$2:$P$301,0))&"","")} | C15: {=IFERROR(INDEX(Alunos!$B$2:$B$301,MATCH(12,Alunos!$P$2:$P$301,0))&"","")} | D15: {=IFERROR(INDEX(Alunos!$C$2:$C$301,MATCH(12,Alunos!$P$2:$P$301,0))&"","")} | E15: {=IFERROR(INDEX(Alunos!$G$2:$G$301,MATCH(12,Alunos!$P$2:$P$301,0))&"","")} | F15: {=IFERROR(INDEX(Alunos!$H$2:$H$301,MATCH(12,Alunos!$P$2:$P$301,0))&"","")} | G15: {=IFERROR(INDEX(Alunos!$K$2:$K$301,MATCH(12,Alunos!$P$2:$P$301,0)),"")} | H15: {=IFERROR(INDEX(Alunos!$L$2:$L$301,MATCH(12,Alunos!$P$2:$P$301,0))&"","")}
A16: =IF(ISNA(MATCH(13,Alunos!$P$2:$P$301,0)),"",13) | B16: {=IFERROR(INDEX(Alunos!$A$2:$A$301,MATCH(13,Alunos!$P$2:$P$301,0))&"","")} | C16: {=IFERROR(INDEX(Alunos!$B$2:$B$301,MATCH(13,Alunos!$P$2:$P$301,0))&"","")} | D16: {=IFERROR(INDEX(Alunos!$C$2:$C$301,MATCH(13,Alunos!$P$2:$P$301,0))&"","")} | E16: {=IFERROR(INDEX(Alunos!$G$2:$G$301,MATCH(13,Alunos!$P$2:$P$301,0))&"","")} | F16: {=IFERROR(INDEX(Alunos!$H$2:$H$301,MATCH(13,Alunos!$P$2:$P$301,0))&"","")} | G16: {=IFERROR(INDEX(Alunos!$K$2:$K$301,MATCH(13,Alunos!$P$2:$P$301,0)),"")} | H16: {=IFERROR(INDEX(Alunos!$L$2:$L$301,MATCH(13,Alunos!$P$2:$P$301,0))&"","")}
A17: =IF(ISNA(MATCH(14,Alunos!$P$2:$P$301,0)),"",14) | B17: {=IFERROR(INDEX(Alunos!$A$2:$A$301,MATCH(14,Alunos!$P$2:$P$301,0))&"","")} | C17: {=IFERROR(INDEX(Alunos!$B$2:$B$301,MATCH(14,Alunos!$P$2:$P$301,0))&"","")} | D17: {=IFERROR(INDEX(Alunos!$C$2:$C$301,MATCH(14,Alunos!$P$2:$P$301,0))&"","")} | E17: {=IFERROR(INDEX(Alunos!$G$2:$G$301,MATCH(14,Alunos!$P$2:$P$301,0))&"","")} | F17: {=IFERROR(INDEX(Alunos!$H$2:$H$301,MATCH(14,Alunos!$P$2:$P$301,0))&"","")} | G17: {=IFERROR(INDEX(Alunos!$K$2:$K$301,MATCH(14,Alunos!$P$2:$P$301,0)),"")} | H17: {=IFERROR(INDEX(Alunos!$L$2:$L$301,MATCH(14,Alunos!$P$2:$P$301,0))&"","")}
A18: =IF(ISNA(MATCH(15,Alunos!$P$2:$P$301,0)),"",15) | B18: {=IFERROR(INDEX(Alunos!$A$2:$A$301,MATCH(15,Alunos!$P$2:$P$301,0))&"","")} | C18: {=IFERROR(INDEX(Alunos!$B$2:$B$301,MATCH(15,Alunos!$P$2:$P$301,0))&"","")} | D18: {=IFERROR(INDEX(Alunos!$C$2:$C$301,MATCH(15,Alunos!$P$2:$P$301,0))&"","")} | E18: {=IFERROR(INDEX(Alunos!$G$2:$G$301,MATCH(15,Alunos!$P$2:$P$301,0))&"","")} | F18: {=IFERROR(INDEX(Alunos!$H$2:$H$301,MATCH(15,Alunos!$P$2:$P$301,0))&"","")} | G18: {=IFERROR(INDEX(Alunos!$K$2:$K$301,MATCH(15,Alunos!$P$2:$P$301,0)),"")} | H18: {=IFERROR(INDEX(Alunos!$L$2:$L$301,MATCH(15,Alunos!$P$2:$P$301,0))&"","")}
A19: =IF(ISNA(MATCH(16,Alunos!$P$2:$P$301,0)),"",16) | B19: {=IFERROR(INDEX(Alunos!$A$2:$A$301,MATCH(16,Alunos!$P$2:$P$301,0))&"","")} | C19: {=IFERROR(INDEX(Alunos!$B$2:$B$301,MATCH(16,Alunos!$P$2:$P$301,0))&"","")} | D19: {=IFERROR(INDEX(Alunos!$C$2:$C$301,MATCH(16,Alunos!$P$2:$P$301,0))&"","")} | E19: {=IFERROR(INDEX(Alunos!$G$2:$G$301,MATCH(16,Alunos!$P$2:$P$301,0))&"","")} | F19: {=IFERROR(INDEX(Alunos!$H$2:$H$301,MATCH(16,Alunos!$P$2:$P$301,0))&"","")} | G19: {=IFERROR(INDEX(Alunos!$K$2:$K$301,MATCH(16,Alunos!$P$2:$P$301,0)),"")} | H19: {=IFERROR(INDEX(Alunos!$L$2:$L$301,MATCH(16,Alunos!$P$2:$P$301,0))&"","")}
A20: =IF(ISNA(MATCH(17,Alunos!$P$2:$P$301,0)),"",17) | B20: {=IFERROR(INDEX(Alunos!$A$2:$A$301,MATCH(17,Alunos!$P$2:$P$301,0))&"","")} | C20: {=IFERROR(INDEX(Alunos!$B$2:$B$301,MATCH(17,Alunos!$P$2:$P$301,0))&"","")} | D20: {=IFERROR(INDEX(Alunos!$C$2:$C$301,MATCH(17,Alunos!$P$2:$P$301,0))&"","")} | E20: {=IFERROR(INDEX(Alunos!$G$2:$G$301,MATCH(17,Alunos!$P$2:$P$301,0))&"","")} | F20: {=IFERROR(INDEX(Alunos!$H$2:$H$301,MATCH(17,Alunos!$P$2:$P$301,0))&"","")} | G20: {=IFERROR(INDEX(Alunos!$K$2:$K$301,MATCH(17,Alunos!$P$2:$P$301,0)),"")} | H20: {=IFERROR(INDEX(Alunos!$L$2:$L$301,MATCH(17,Alunos!$P$2:$P$301,0))&"","")}
A21: =IF(ISNA(MATCH(18,Alunos!$P$2:$P$301,0)),"",18) | B21: {=IFERROR(INDEX(Alunos!$A$2:$A$301,MATCH(18,Alunos!$P$2:$P$301,0))&"","")} | C21: {=IFERROR(INDEX(Alunos!$B$2:$B$301,MATCH(18,Alunos!$P$2:$P$301,0))&"","")} | D21: {=IFERROR(INDEX(Alunos!$C$2:$C$301,MATCH(18,Alunos!$P$2:$P$301,0))&"","")} | E21: {=IFERROR(INDEX(Alunos!$G$2:$G$301,MATCH(18,Alunos!$P$2:$P$301,0))&"","")} | F21: {=IFERROR(INDEX(Alunos!$H$2:$H$301,MATCH(18,Alunos!$P$2:$P$301,0))&"","")} | G21: {=IFERROR(INDEX(Alunos!$K$2:$K$301,MATCH(18,Alunos!$P$2:$P$301,0)),"")} | H21: {=IFERROR(INDEX(Alunos!$L$2:$L$301,MATCH(18,Alunos!$P$2:$P$301,0))&"","")}
A22: =IF(ISNA(MATCH(19,Alunos!$P$2:$P$301,0)),"",19) | B22: {=IFERROR(INDEX(Alunos!$A$2:$A$301,MATCH(19,Alunos!$P$2:$P$301,0))&"","")} | C22: {=IFERROR(INDEX(Alunos!$B$2:$B$301,MATCH(19,Alunos!$P$2:$P$301,0))&"","")} | D22: {=IFERROR(INDEX(Alunos!$C$2:$C$301,MATCH(19,Alunos!$P$2:$P$301,0))&"","")} | E22: {=IFERROR(INDEX(Alunos!$G$2:$G$301,MATCH(19,Alunos!$P$2:$P$301,0))&"","")} | F22: {=IFERROR(INDEX(Alunos!$H$2:$H$301,MATCH(19,Alunos!$P$2:$P$301,0))&"","")} | G22: {=IFERROR(INDEX(Alunos!$K$2:$K$301,MATCH(19,Alunos!$P$2:$P$301,0)),"")} | H22: {=IFERROR(INDEX(Alunos!$L$2:$L$301,MATCH(19,Alunos!$P$2:$P$301,0))&"","")}
A23: =IF(ISNA(MATCH(20,Alunos!$P$2:$P$301,0)),"",20) | B23: {=IFERROR(INDEX(Alunos!$A$2:$A$301,MATCH(20,Alunos!$P$2:$P$301,0))&"","")} | C23: {=IFERROR(INDEX(Alunos!$B$2:$B$301,MATCH(20,Alunos!$P$2:$P$301,0))&"","")} | D23: {=IFERROR(INDEX(Alunos!$C$2:$C$301,MATCH(20,Alunos!$P$2:$P$301,0))&"","")} | E23: {=IFERROR(INDEX(Alunos!$G$2:$G$301,MATCH(20,Alunos!$P$2:$P$301,0))&"","")} | F23: {=IFERROR(INDEX(Alunos!$H$2:$H$301,MATCH(20,Alunos!$P$2:$P$301,0))&"","")} | G23: {=IFERROR(INDEX(Alunos!$K$2:$K$301,MATCH(20,Alunos!$P$2:$P$301,0)),"")} | H23: {=IFERROR(INDEX(Alunos!$L$2:$L$301,MATCH(20,Alunos!$P$2:$P$301,0))&"","")}
A24: =IF(ISNA(MATCH(21,Alunos!$P$2:$P$301,0)),"",21) | B24: {=IFERROR(INDEX(Alunos!$A$2:$A$301,MATCH(21,Alunos!$P$2:$P$301,0))&"","")} | C24: {=IFERROR(INDEX(Alunos!$B$2:$B$301,MATCH(21,Alunos!$P$2:$P$301,0))&"","")} | D24: {=IFERROR(INDEX(Alunos!$C$2:$C$301,MATCH(21,Alunos!$P$2:$P$301,0))&"","")} | E24: {=IFERROR(INDEX(Alunos!$G$2:$G$301,MATCH(21,Alunos!$P$2:$P$301,0))&"","")} | F24: {=IFERROR(INDEX(Alunos!$H$2:$H$301,MATCH(21,Alunos!$P$2:$P$301,0))&"","")} | G24: {=IFERROR(INDEX(Alunos!$K$2:$K$301,MATCH(21,Alunos!$P$2:$P$301,0)),"")} | H24: {=IFERROR(INDEX(Alunos!$L$2:$L$301,MATCH(21,Alunos!$P$2:$P$301,0))&"","")}
A25: =IF(ISNA(MATCH(22,Alunos!$P$2:$P$301,0)),"",22) | B25: {=IFERROR(INDEX(Alunos!$A$2:$A$301,MATCH(22,Alunos!$P$2:$P$301,0))&"","")} | C25: {=IFERROR(INDEX(Alunos!$B$2:$B$301,MATCH(22,Alunos!$P$2:$P$301,0))&"","")} | D25: {=IFERROR(INDEX(Alunos!$C$2:$C$301,MATCH(22,Alunos!$P$2:$P$301,0))&"","")} | E25: {=IFERROR(INDEX(Alunos!$G$2:$G$301,MATCH(22,Alunos!$P$2:$P$301,0))&"","")} | F25: {=IFERROR(INDEX(Alunos!$H$2:$H$301,MATCH(22,Alunos!$P$2:$P$301,0))&"","")} | G25: {=IFERROR(INDEX(Alunos!$K$2:$K$301,MATCH(22,Alunos!$P$2:$P$301,0)),"")} | H25: {=IFERROR(INDEX(Alunos!$L$2:$L$301,MATCH(22,Alunos!$P$2:$P$301,0))&"","")}
A26: =IF(ISNA(MATCH(23,Alunos!$P$2:$P$301,0)),"",23) | B26: {=IFERROR(INDEX(Alunos!$A$2:$A$301,MATCH(23,Alunos!$P$2:$P$301,0))&"","")} | C26: {=IFERROR(INDEX(Alunos!$B$2:$B$301,MATCH(23,Alunos!$P$2:$P$301,0))&"","")} | D26: {=IFERROR(INDEX(Alunos!$C$2:$C$301,MATCH(23,Alunos!$P$2:$P$301,0))&"","")} | E26: {=IFERROR(INDEX(Alunos!$G$2:$G$301,MATCH(23,Alunos!$P$2:$P$301,0))&"","")} | F26: {=IFERROR(INDEX(Alunos!$H$2:$H$301,MATCH(23,Alunos!$P$2:$P$301,0))&"","")} | G26: {=IFERROR(INDEX(Alunos!$K$2:$K$301,MATCH(23,Alunos!$P$2:$P$301,0)),"")} | H26: {=IFERROR(INDEX(Alunos!$L$2:$L$301,MATCH(23,Alunos!$P$2:$P$301,0))&"","")}
A27: =IF(ISNA(MATCH(24,Alunos!$P$2:$P$301,0)),"",24) | B27: {=IFERROR(INDEX(Alunos!$A$2:$A$301,MATCH(24,Alunos!$P$2:$P$301,0))&"","")} | C27: {=IFERROR(INDEX(Alunos!$B$2:$B$301,MATCH(24,Alunos!$P$2:$P$301,0))&"","")} | D27: {=IFERROR(INDEX(Alunos!$C$2:$C$301,MATCH(24,Alunos!$P$2:$P$301,0))&"","")} | E27: {=IFERROR(INDEX(Alunos!$G$2:$G$301,MATCH(24,Alunos!$P$2:$P$301,0))&"","")} | F27: {=IFERROR(INDEX(Alunos!$H$2:$H$301,MATCH(24,Alunos!$P$2:$P$301,0))&"","")} | G27: {=IFERROR(INDEX(Alunos!$K$2:$K$301,MATCH(24,Alunos!$P$2:$P$301,0)),"")} | H27: {=IFERROR(INDEX(Alunos!$L$2:$L$301,MATCH(24,Alunos!$P$2:$P$301,0))&"","")}
A28: =IF(ISNA(MATCH(25,Alunos!$P$2:$P$301,0)),"",25) | B28: {=IFERROR(INDEX(Alunos!$A$2:$A$301,MATCH(25,Alunos!$P$2:$P$301,0))&"","")} | C28: {=IFERROR(INDEX(Alunos!$B$2:$B$301,MATCH(25,Alunos!$P$2:$P$301,0))&"","")} | D28: {=IFERROR(INDEX(Alunos!$C$2:$C$301,MATCH(25,Alunos!$P$2:$P$301,0))&"","")} | E28: {=IFERROR(INDEX(Alunos!$G$2:$G$301,MATCH(25,Alunos!$P$2:$P$301,0))&"","")} | F28: {=IFERROR(INDEX(Alunos!$H$2:$H$301,MATCH(25,Alunos!$P$2:$P$301,0))&"","")} | G28: {=IFERROR(INDEX(Alunos!$K$2:$K$301,MATCH(25,Alunos!$P$2:$P$301,0)),"")} | H28: {=IFERROR(INDEX(Alunos!$L$2:$L$301,MATCH(25,Alunos!$P$2:$P$301,0))&"","")}
A29: =IF(ISNA(MATCH(26,Alunos!$P$2:$P$301,0)),"",26) | B29: {=IFERROR(INDEX(Alunos!$A$2:$A$301,MATCH(26,Alunos!$P$2:$P$301,0))&"","")} | C29: {=IFERROR(INDEX(Alunos!$B$2:$B$301,MATCH(26,Alunos!$P$2:$P$301,0))&"","")} | D29: {=IFERROR(INDEX(Alunos!$C$2:$C$301,MATCH(26,Alunos!$P$2:$P$301,0))&"","")} | E29: {=IFERROR(INDEX(Alunos!$G$2:$G$301,MATCH(26,Alunos!$P$2:$P$301,0))&"","")} | F29: {=IFERROR(INDEX(Alunos!$H$2:$H$301,MATCH(26,Alunos!$P$2:$P$301,0))&"","")} | G29: {=IFERROR(INDEX(Alunos!$K$2:$K$301,MATCH(26,Alunos!$P$2:$P$301,0)),"")} | H29: {=IFERROR(INDEX(Alunos!$L$2:$L$301,MATCH(26,Alunos!$P$2:$P$301,0))&"","")}
A30: =IF(ISNA(MATCH(27,Alunos!$P$2:$P$301,0)),"",27) | B30: {=IFERROR(INDEX(Alunos!$A$2:$A$301,MATCH(27,Alunos!$P$2:$P$301,0))&"","")} | C30: {=IFERROR(INDEX(Alunos!$B$2:$B$301,MATCH(27,Alunos!$P$2:$P$301,0))&"","")} | D30: {=IFERROR(INDEX(Alunos!$C$2:$C$301,MATCH(27,Alunos!$P$2:$P$301,0))&"","")} | E30: {=IFERROR(INDEX(Alunos!$G$2:$G$301,MATCH(27,Alunos!$P$2:$P$301,0))&"","")} | F30: {=IFERROR(INDEX(Alunos!$H$2:$H$301,MATCH(27,Alunos!$P$2:$P$301,0))&"","")} | G30: {=IFERROR(INDEX(Alunos!$K$2:$K$301,MATCH(27,Alunos!$P$2:$P$301,0)),"")} | H30: {=IFERROR(INDEX(Alunos!$L$2:$L$301,MATCH(27,Alunos!$P$2:$P$301,0))&"","")}
A31: =IF(ISNA(MATCH(28,Alunos!$P$2:$P$301,0)),"",28) | B31: {=IFERROR(INDEX(Alunos!$A$2:$A$301,MATCH(28,Alunos!$P$2:$P$301,0))&"","")} | C31: {=IFERROR(INDEX(Alunos!$B$2:$B$301,MATCH(28,Alunos!$P$2:$P$301,0))&"","")} | D31: {=IFERROR(INDEX(Alunos!$C$2:$C$301,MATCH(28,Alunos!$P$2:$P$301,0))&"","")} | E31: {=IFERROR(INDEX(Alunos!$G$2:$G$301,MATCH(28,Alunos!$P$2:$P$301,0))&"","")} | F31: {=IFERROR(INDEX(Alunos!$H$2:$H$301,MATCH(28,Alunos!$P$2:$P$301,0))&"","")} | G31: {=IFERROR(INDEX(Alunos!$K$2:$K$301,MATCH(28,Alunos!$P$2:$P$301,0)),"")} | H31: {=IFERROR(INDEX(Alunos!$L$2:$L$301,MATCH(28,Alunos!$P$2:$P$301,0))&"","")}
A32: =IF(ISNA(MATCH(29,Alunos!$P$2:$P$301,0)),"",29) | B32: {=IFERROR(INDEX(Alunos!$A$2:$A$301,MATCH(29,Alunos!$P$2:$P$301,0))&"","")} | C32: {=IFERROR(INDEX(Alunos!$B$2:$B$301,MATCH(29,Alunos!$P$2:$P$301,0))&"","")} | D32: {=IFERROR(INDEX(Alunos!$C$2:$C$301,MATCH(29,Alunos!$P$2:$P$301,0))&"","")} | E32: {=IFERROR(INDEX(Alunos!$G$2:$G$301,MATCH(29,Alunos!$P$2:$P$301,0))&"","")} | F32: {=IFERROR(INDEX(Alunos!$H$2:$H$301,MATCH(29,Alunos!$P$2:$P$301,0))&"","")} | G32: {=IFERROR(INDEX(Alunos!$K$2:$K$301,MATCH(29,Alunos!$P$2:$P$301,0)),"")} | H32: {=IFERROR(INDEX(Alunos!$L$2:$L$301,MATCH(29,Alunos!$P$2:$P$301,0))&"","")}
A33: =IF(ISNA(MATCH(30,Alunos!$P$2:$P$301,0)),"",30) | B33: {=IFERROR(INDEX(Alunos!$A$2:$A$301,MATCH(30,Alunos!$P$2:$P$301,0))&"","")} | C33: {=IFERROR(INDEX(Alunos!$B$2:$B$301,MATCH(30,Alunos!$P$2:$P$301,0))&"","")} | D33: {=IFERROR(INDEX(Alunos!$C$2:$C$301,MATCH(30,Alunos!$P$2:$P$301,0))&"","")} | E33: {=IFERROR(INDEX(Alunos!$G$2:$G$301,MATCH(30,Alunos!$P$2:$P$301,0))&"","")} | F33: {=IFERROR(INDEX(Alunos!$H$2:$H$301,MATCH(30,Alunos!$P$2:$P$301,0))&"","")} | G33: {=IFERROR(INDEX(Alunos!$K$2:$K$301,MATCH(30,Alunos!$P$2:$P$301,0)),"")} | H33: {=IFERROR(INDEX(Alunos!$L$2:$L$301,MATCH(30,Alunos!$P$2:$P$301,0))&"","")}
A34: =IF(ISNA(MATCH(31,Alunos!$P$2:$P$301,0)),"",31) | B34: {=IFERROR(INDEX(Alunos!$A$2:$A$301,MATCH(31,Alunos!$P$2:$P$301,0))&"","")} | C34: {=IFERROR(INDEX(Alunos!$B$2:$B$301,MATCH(31,Alunos!$P$2:$P$301,0))&"","")} | D34: {=IFERROR(INDEX(Alunos!$C$2:$C$301,MATCH(31,Alunos!$P$2:$P$301,0))&"","")} | E34: {=IFERROR(INDEX(Alunos!$G$2:$G$301,MATCH(31,Alunos!$P$2:$P$301,0))&"","")} | F34: {=IFERROR(INDEX(Alunos!$H$2:$H$301,MATCH(31,Alunos!$P$2:$P$301,0))&"","")} | G34: {=IFERROR(INDEX(Alunos!$K$2:$K$301,MATCH(31,Alunos!$P$2:$P$301,0)),"")} | H34: {=IFERROR(INDEX(Alunos!$L$2:$L$301,MATCH(31,Alunos!$P$2:$P$301,0))&"","")}
A35: =IF(ISNA(MATCH(32,Alunos!$P$2:$P$301,0)),"",32) | B35: {=IFERROR(INDEX(Alunos!$A$2:$A$301,MATCH(32,Alunos!$P$2:$P$301,0))&"","")} | C35: {=IFERROR(INDEX(Alunos!$B$2:$B$301,MATCH(32,Alunos!$P$2:$P$301,0))&"","")} | D35: {=IFERROR(INDEX(Alunos!$C$2:$C$301,MATCH(32,Alunos!$P$2:$P$301,0))&"","")} | E35: {=IFERROR(INDEX(Alunos!$G$2:$G$301,MATCH(32,Alunos!$P$2:$P$301,0))&"","")} | F35: {=IFERROR(INDEX(Alunos!$H$2:$H$301,MATCH(32,Alunos!$P$2:$P$301,0))&"","")} | G35: {=IFERROR(INDEX(Alunos!$K$2:$K$301,MATCH(32,Alunos!$P$2:$P$301,0)),"")} | H35: {=IFERROR(INDEX(Alunos!$L$2:$L$301,MATCH(32,Alunos!$P$2:$P$301,0))&"","")}
A36: =IF(ISNA(MATCH(33,Alunos!$P$2:$P$301,0)),"",33) | B36: {=IFERROR(INDEX(Alunos!$A$2:$A$301,MATCH(33,Alunos!$P$2:$P$301,0))&"","")} | C36: {=IFERROR(INDEX(Alunos!$B$2:$B$301,MATCH(33,Alunos!$P$2:$P$301,0))&"","")} | D36: {=IFERROR(INDEX(Alunos!$C$2:$C$301,MATCH(33,Alunos!$P$2:$P$301,0))&"","")} | E36: {=IFERROR(INDEX(Alunos!$G$2:$G$301,MATCH(33,Alunos!$P$2:$P$301,0))&"","")} | F36: {=IFERROR(INDEX(Alunos!$H$2:$H$301,MATCH(33,Alunos!$P$2:$P$301,0))&"","")} | G36: {=IFERROR(INDEX(Alunos!$K$2:$K$301,MATCH(33,Alunos!$P$2:$P$301,0)),"")} | H36: {=IFERROR(INDEX(Alunos!$L$2:$L$301,MATCH(33,Alunos!$P$2:$P$301,0))&"","")}
A37: =IF(ISNA(MATCH(34,Alunos!$P$2:$P$301,0)),"",34) | B37: {=IFERROR(INDEX(Alunos!$A$2:$A$301,MATCH(34,Alunos!$P$2:$P$301,0))&"","")} | C37: {=IFERROR(INDEX(Alunos!$B$2:$B$301,MATCH(34,Alunos!$P$2:$P$301,0))&"","")} | D37: {=IFERROR(INDEX(Alunos!$C$2:$C$301,MATCH(34,Alunos!$P$2:$P$301,0))&"","")} | E37: {=IFERROR(INDEX(Alunos!$G$2:$G$301,MATCH(34,Alunos!$P$2:$P$301,0))&"","")} | F37: {=IFERROR(INDEX(Alunos!$H$2:$H$301,MATCH(34,Alunos!$P$2:$P$301,0))&"","")} | G37: {=IFERROR(INDEX(Alunos!$K$2:$K$301,MATCH(34,Alunos!$P$2:$P$301,0)),"")} | H37: {=IFERROR(INDEX(Alunos!$L$2:$L$301,MATCH(34,Alunos!$P$2:$P$301,0))&"","")}
A38: =IF(ISNA(MATCH(35,Alunos!$P$2:$P$301,0)),"",35) | B38: {=IFERROR(INDEX(Alunos!$A$2:$A$301,MATCH(35,Alunos!$P$2:$P$301,0))&"","")} | C38: {=IFERROR(INDEX(Alunos!$B$2:$B$301,MATCH(35,Alunos!$P$2:$P$301,0))&"","")} | D38: {=IFERROR(INDEX(Alunos!$C$2:$C$301,MATCH(35,Alunos!$P$2:$P$301,0))&"","")} | E38: {=IFERROR(INDEX(Alunos!$G$2:$G$301,MATCH(35,Alunos!$P$2:$P$301,0))&"","")} | F38: {=IFERROR(INDEX(Alunos!$H$2:$H$301,MATCH(35,Alunos!$P$2:$P$301,0))&"","")} | G38: {=IFERROR(INDEX(Alunos!$K$2:$K$301,MATCH(35,Alunos!$P$2:$P$301,0)),"")} | H38: {=IFERROR(INDEX(Alunos!$L$2:$L$301,MATCH(35,Alunos!$P$2:$P$301,0))&"","")}
A39: =IF(ISNA(MATCH(36,Alunos!$P$2:$P$301,0)),"",36) | B39: {=IFERROR(INDEX(Alunos!$A$2:$A$301,MATCH(36,Alunos!$P$2:$P$301,0))&"","")} | C39: {=IFERROR(INDEX(Alunos!$B$2:$B$301,MATCH(36,Alunos!$P$2:$P$301,0))&"","")} | D39: {=IFERROR(INDEX(Alunos!$C$2:$C$301,MATCH(36,Alunos!$P$2:$P$301,0))&"","")} | E39: {=IFERROR(INDEX(Alunos!$G$2:$G$301,MATCH(36,Alunos!$P$2:$P$301,0))&"","")} | F39: {=IFERROR(INDEX(Alunos!$H$2:$H$301,MATCH(36,Alunos!$P$2:$P$301,0))&"","")} | G39: {=IFERROR(INDEX(Alunos!$K$2:$K$301,MATCH(36,Alunos!$P$2:$P$301,0)),"")} | H39: {=IFERROR(INDEX(Alunos!$L$2:$L$301,MATCH(36,Alunos!$P$2:$P$301,0))&"","")}
A40: =IF(ISNA(MATCH(37,Alunos!$P$2:$P$301,0)),"",37) | B40: {=IFERROR(INDEX(Alunos!$A$2:$A$301,MATCH(37,Alunos!$P$2:$P$301,0))&"","")} | C40: {=IFERROR(INDEX(Alunos!$B$2:$B$301,MATCH(37,Alunos!$P$2:$P$301,0))&"","")} | D40: {=IFERROR(INDEX(Alunos!$C$2:$C$301,MATCH(37,Alunos!$P$2:$P$301,0))&"","")} | E40: {=IFERROR(INDEX(Alunos!$G$2:$G$301,MATCH(37,Alunos!$P$2:$P$301,0))&"","")} | F40: {=IFERROR(INDEX(Alunos!$H$2:$H$301,MATCH(37,Alunos!$P$2:$P$301,0))&"","")} | G40: {=IFERROR(INDEX(Alunos!$K$2:$K$301,MATCH(37,Alunos!$P$2:$P$301,0)),"")} | H40: {=IFERROR(INDEX(Alunos!$L$2:$L$301,MATCH(37,Alunos!$P$2:$P$301,0))&"","")}
A41: =IF(ISNA(MATCH(38,Alunos!$P$2:$P$301,0)),"",38) | B41: {=IFERROR(INDEX(Alunos!$A$2:$A$301,MATCH(38,Alunos!$P$2:$P$301,0))&"","")} | C41: {=IFERROR(INDEX(Alunos!$B$2:$B$301,MATCH(38,Alunos!$P$2:$P$301,0))&"","")} | D41: {=IFERROR(INDEX(Alunos!$C$2:$C$301,MATCH(38,Alunos!$P$2:$P$301,0))&"","")} | E41: {=IFERROR(INDEX(Alunos!$G$2:$G$301,MATCH(38,Alunos!$P$2:$P$301,0))&"","")} | F41: {=IFERROR(INDEX(Alunos!$H$2:$H$301,MATCH(38,Alunos!$P$2:$P$301,0))&"","")} | G41: {=IFERROR(INDEX(Alunos!$K$2:$K$301,MATCH(38,Alunos!$P$2:$P$301,0)),"")} | H41: {=IFERROR(INDEX(Alunos!$L$2:$L$301,MATCH(38,Alunos!$P$2:$P$301,0))&"","")}
A42: =IF(ISNA(MATCH(39,Alunos!$P$2:$P$301,0)),"",39) | B42: {=IFERROR(INDEX(Alunos!$A$2:$A$301,MATCH(39,Alunos!$P$2:$P$301,0))&"","")} | C42: {=IFERROR(INDEX(Alunos!$B$2:$B$301,MATCH(39,Alunos!$P$2:$P$301,0))&"","")} | D42: {=IFERROR(INDEX(Alunos!$C$2:$C$301,MATCH(39,Alunos!$P$2:$P$301,0))&"","")} | E42: {=IFERROR(INDEX(Alunos!$G$2:$G$301,MATCH(39,Alunos!$P$2:$P$301,0))&"","")} | F42: {=IFERROR(INDEX(Alunos!$H$2:$H$301,MATCH(39,Alunos!$P$2:$P$301,0))&"","")} | G42: {=IFERROR(INDEX(Alunos!$K$2:$K$301,MATCH(39,Alunos!$P$2:$P$301,0)),"")} | H42: {=IFERROR(INDEX(Alunos!$L$2:$L$301,MATCH(39,Alunos!$P$2:$P$301,0))&"","")}
A43: =IF(ISNA(MATCH(40,Alunos!$P$2:$P$301,0)),"",40) | B43: {=IFERROR(INDEX(Alunos!$A$2:$A$301,MATCH(40,Alunos!$P$2:$P$301,0))&"","")} | C43: {=IFERROR(INDEX(Alunos!$B$2:$B$301,MATCH(40,Alunos!$P$2:$P$301,0))&"","")} | D43: {=IFERROR(INDEX(Alunos!$C$2:$C$301,MATCH(40,Alunos!$P$2:$P$301,0))&"","")} | E43: {=IFERROR(INDEX(Alunos!$G$2:$G$301,MATCH(40,Alunos!$P$2:$P$301,0))&"","")} | F43: {=IFERROR(INDEX(Alunos!$H$2:$H$301,MATCH(40,Alunos!$P$2:$P$301,0))&"","")} | G43: {=IFERROR(INDEX(Alunos!$K$2:$K$301,MATCH(40,Alunos!$P$2:$P$301,0)),"")} | H43: {=IFERROR(INDEX(Alunos!$L$2:$L$301,MATCH(40,Alunos!$P$2:$P$301,0))&"","")}
A44: =IF(ISNA(MATCH(41,Alunos!$P$2:$P$301,0)),"",41) | B44: {=IFERROR(INDEX(Alunos!$A$2:$A$301,MATCH(41,Alunos!$P$2:$P$301,0))&"","")} | C44: {=IFERROR(INDEX(Alunos!$B$2:$B$301,MATCH(41,Alunos!$P$2:$P$301,0))&"","")} | D44: {=IFERROR(INDEX(Alunos!$C$2:$C$301,MATCH(41,Alunos!$P$2:$P$301,0))&"","")} | E44: {=IFERROR(INDEX(Alunos!$G$2:$G$301,MATCH(41,Alunos!$P$2:$P$301,0))&"","")} | F44: {=IFERROR(INDEX(Alunos!$H$2:$H$301,MATCH(41,Alunos!$P$2:$P$301,0))&"","")} | G44: {=IFERROR(INDEX(Alunos!$K$2:$K$301,MATCH(41,Alunos!$P$2:$P$301,0)),"")} | H44: {=IFERROR(INDEX(Alunos!$L$2:$L$301,MATCH(41,Alunos!$P$2:$P$301,0))&"","")}
A45: =IF(ISNA(MATCH(42,Alunos!$P$2:$P$301,0)),"",42) | B45: {=IFERROR(INDEX(Alunos!$A$2:$A$301,MATCH(42,Alunos!$P$2:$P$301,0))&"","")} | C45: {=IFERROR(INDEX(Alunos!$B$2:$B$301,MATCH(42,Alunos!$P$2:$P$301,0))&"","")} | D45: {=IFERROR(INDEX(Alunos!$C$2:$C$301,MATCH(42,Alunos!$P$2:$P$301,0))&"","")} | E45: {=IFERROR(INDEX(Alunos!$G$2:$G$301,MATCH(42,Alunos!$P$2:$P$301,0))&"","")} | F45: {=IFERROR(INDEX(Alunos!$H$2:$H$301,MATCH(42,Alunos!$P$2:$P$301,0))&"","")} | G45: {=IFERROR(INDEX(Alunos!$K$2:$K$301,MATCH(42,Alunos!$P$2:$P$301,0)),"")} | H45: {=IFERROR(INDEX(Alunos!$L$2:$L$301,MATCH(42,Alunos!$P$2:$P$301,0))&"","")}
A46: =IF(ISNA(MATCH(43,Alunos!$P$2:$P$301,0)),"",43) | B46: {=IFERROR(INDEX(Alunos!$A$2:$A$301,MATCH(43,Alunos!$P$2:$P$301,0))&"","")} | C46: {=IFERROR(INDEX(Alunos!$B$2:$B$301,MATCH(43,Alunos!$P$2:$P$301,0))&"","")} | D46: {=IFERROR(INDEX(Alunos!$C$2:$C$301,MATCH(43,Alunos!$P$2:$P$301,0))&"","")} | E46: {=IFERROR(INDEX(Alunos!$G$2:$G$301,MATCH(43,Alunos!$P$2:$P$301,0))&"","")} | F46: {=IFERROR(INDEX(Alunos!$H$2:$H$301,MATCH(43,Alunos!$P$2:$P$301,0))&"","")} | G46: {=IFERROR(INDEX(Alunos!$K$2:$K$301,MATCH(43,Alunos!$P$2:$P$301,0)),"")} | H46: {=IFERROR(INDEX(Alunos!$L$2:$L$301,MATCH(43,Alunos!$P$2:$P$301,0))&"","")}
A47: =IF(ISNA(MATCH(44,Alunos!$P$2:$P$301,0)),"",44) | B47: {=IFERROR(INDEX(Alunos!$A$2:$A$301,MATCH(44,Alunos!$P$2:$P$301,0))&"","")} | C47: {=IFERROR(INDEX(Alunos!$B$2:$B$301,MATCH(44,Alunos!$P$2:$P$301,0))&"","")} | D47: {=IFERROR(INDEX(Alunos!$C$2:$C$301,MATCH(44,Alunos!$P$2:$P$301,0))&"","")} | E47: {=IFERROR(INDEX(Alunos!$G$2:$G$301,MATCH(44,Alunos!$P$2:$P$301,0))&"","")} | F47: {=IFERROR(INDEX(Alunos!$H$2:$H$301,MATCH(44,Alunos!$P$2:$P$301,0))&"","")} | G47: {=IFERROR(INDEX(Alunos!$K$2:$K$301,MATCH(44,Alunos!$P$2:$P$301,0)),"")} | H47: {=IFERROR(INDEX(Alunos!$L$2:$L$301,MATCH(44,Alunos!$P$2:$P$301,0))&"","")}
A48: =IF(ISNA(MATCH(45,Alunos!$P$2:$P$301,0)),"",45) | B48: {=IFERROR(INDEX(Alunos!$A$2:$A$301,MATCH(45,Alunos!$P$2:$P$301,0))&"","")} | C48: {=IFERROR(INDEX(Alunos!$B$2:$B$301,MATCH(45,Alunos!$P$2:$P$301,0))&"","")} | D48: {=IFERROR(INDEX(Alunos!$C$2:$C$301,MATCH(45,Alunos!$P$2:$P$301,0))&"","")} | E48: {=IFERROR(INDEX(Alunos!$G$2:$G$301,MATCH(45,Alunos!$P$2:$P$301,0))&"","")} | F48: {=IFERROR(INDEX(Alunos!$H$2:$H$301,MATCH(45,Alunos!$P$2:$P$301,0))&"","")} | G48: {=IFERROR(INDEX(Alunos!$K$2:$K$301,MATCH(45,Alunos!$P$2:$P$301,0)),"")} | H48: {=IFERROR(INDEX(Alunos!$L$2:$L$301,MATCH(45,Alunos!$P$2:$P$301,0))&"","")}
A49: =IF(ISNA(MATCH(46,Alunos!$P$2:$P$301,0)),"",46) | B49: {=IFERROR(INDEX(Alunos!$A$2:$A$301,MATCH(46,Alunos!$P$2:$P$301,0))&"","")} | C49: {=IFERROR(INDEX(Alunos!$B$2:$B$301,MATCH(46,Alunos!$P$2:$P$301,0))&"","")} | D49: {=IFERROR(INDEX(Alunos!$C$2:$C$301,MATCH(46,Alunos!$P$2:$P$301,0))&"","")} | E49: {=IFERROR(INDEX(Alunos!$G$2:$G$301,MATCH(46,Alunos!$P$2:$P$301,0))&"","")} | F49: {=IFERROR(INDEX(Alunos!$H$2:$H$301,MATCH(46,Alunos!$P$2:$P$301,0))&"","")} | G49: {=IFERROR(INDEX(Alunos!$K$2:$K$301,MATCH(46,Alunos!$P$2:$P$301,0)),"")} | H49: {=IFERROR(INDEX(Alunos!$L$2:$L$301,MATCH(46,Alunos!$P$2:$P$301,0))&"","")}
A50: =IF(ISNA(MATCH(47,Alunos!$P$2:$P$301,0)),"",47) | B50: {=IFERROR(INDEX(Alunos!$A$2:$A$301,MATCH(47,Alunos!$P$2:$P$301,0))&"","")} | C50: {=IFERROR(INDEX(Alunos!$B$2:$B$301,MATCH(47,Alunos!$P$2:$P$301,0))&"","")} | D50: {=IFERROR(INDEX(Alunos!$C$2:$C$301,MATCH(47,Alunos!$P$2:$P$301,0))&"","")} | E50: {=IFERROR(INDEX(Alunos!$G$2:$G$301,MATCH(47,Alunos!$P$2:$P$301,0))&"","")} | F50: {=IFERROR(INDEX(Alunos!$H$2:$H$301,MATCH(47,Alunos!$P$2:$P$301,0))&"","")} | G50: {=IFERROR(INDEX(Alunos!$K$2:$K$301,MATCH(47,Alunos!$P$2:$P$301,0)),"")} | H50: {=IFERROR(INDEX(Alunos!$L$2:$L$301,MATCH(47,Alunos!$P$2:$P$301,0))&"","")}
A51: =IF(ISNA(MATCH(48,Alunos!$P$2:$P$301,0)),"",48) | B51: {=IFERROR(INDEX(Alunos!$A$2:$A$301,MATCH(48,Alunos!$P$2:$P$301,0))&"","")} | C51: {=IFERROR(INDEX(Alunos!$B$2:$B$301,MATCH(48,Alunos!$P$2:$P$301,0))&"","")} | D51: {=IFERROR(INDEX(Alunos!$C$2:$C$301,MATCH(48,Alunos!$P$2:$P$301,0))&"","")} | E51: {=IFERROR(INDEX(Alunos!$G$2:$G$301,MATCH(48,Alunos!$P$2:$P$301,0))&"","")} | F51: {=IFERROR(INDEX(Alunos!$H$2:$H$301,MATCH(48,Alunos!$P$2:$P$301,0))&"","")} | G51: {=IFERROR(INDEX(Alunos!$K$2:$K$301,MATCH(48,Alunos!$P$2:$P$301,0)),"")} | H51: {=IFERROR(INDEX(Alunos!$L$2:$L$301,MATCH(48,Alunos!$P$2:$P$301,0))&"","")}
A52: =IF(ISNA(MATCH(49,Alunos!$P$2:$P$301,0)),"",49) | B52: {=IFERROR(INDEX(Alunos!$A$2:$A$301,MATCH(49,Alunos!$P$2:$P$301,0))&"","")} | C52: {=IFERROR(INDEX(Alunos!$B$2:$B$301,MATCH(49,Alunos!$P$2:$P$301,0))&"","")} | D52: {=IFERROR(INDEX(Alunos!$C$2:$C$301,MATCH(49,Alunos!$P$2:$P$301,0))&"","")} | E52: {=IFERROR(INDEX(Alunos!$G$2:$G$301,MATCH(49,Alunos!$P$2:$P$301,0))&"","")} | F52: {=IFERROR(INDEX(Alunos!$H$2:$H$301,MATCH(49,Alunos!$P$2:$P$301,0))&"","")} | G52: {=IFERROR(INDEX(Alunos!$K$2:$K$301,MATCH(49,Alunos!$P$2:$P$301,0)),"")} | H52: {=IFERROR(INDEX(Alunos!$L$2:$L$301,MATCH(49,Alunos!$P$2:$P$301,0))&"","")}
A53: =IF(ISNA(MATCH(50,Alunos!$P$2:$P$301,0)),"",50) | B53: {=IFERROR(INDEX(Alunos!$A$2:$A$301,MATCH(50,Alunos!$P$2:$P$301,0))&"","")} | C53: {=IFERROR(INDEX(Alunos!$B$2:$B$301,MATCH(50,Alunos!$P$2:$P$301,0))&"","")} | D53: {=IFERROR(INDEX(Alunos!$C$2:$C$301,MATCH(50,Alunos!$P$2:$P$301,0))&"","")} | E53: {=IFERROR(INDEX(Alunos!$G$2:$G$301,MATCH(50,Alunos!$P$2:$P$301,0))&"","")} | F53: {=IFERROR(INDEX(Alunos!$H$2:$H$301,MATCH(50,Alunos!$P$2:$P$301,0))&"","")} | G53: {=IFERROR(INDEX(Alunos!$K$2:$K$301,MATCH(50,Alunos!$P$2:$P$301,0)),"")} | H53: {=IFERROR(INDEX(Alunos!$L$2:$L$301,MATCH(50,Alunos!$P$2:$P$301,0))&"","")}
A54: =IF(ISNA(MATCH(51,Alunos!$P$2:$P$301,0)),"",51) | B54: {=IFERROR(INDEX(Alunos!$A$2:$A$301,MATCH(51,Alunos!$P$2:$P$301,0))&"","")} | C54: {=IFERROR(INDEX(Alunos!$B$2:$B$301,MATCH(51,Alunos!$P$2:$P$301,0))&"","")} | D54: {=IFERROR(INDEX(Alunos!$C$2:$C$301,MATCH(51,Alunos!$P$2:$P$301,0))&"","")} | E54: {=IFERROR(INDEX(Alunos!$G$2:$G$301,MATCH(51,Alunos!$P$2:$P$301,0))&"","")} | F54: {=IFERROR(INDEX(Alunos!$H$2:$H$301,MATCH(51,Alunos!$P$2:$P$301,0))&"","")} | G54: {=IFERROR(INDEX(Alunos!$K$2:$K$301,MATCH(51,Alunos!$P$2:$P$301,0)),"")} | H54: {=IFERROR(INDEX(Alunos!$L$2:$L$301,MATCH(51,Alunos!$P$2:$P$301,0))&"","")}
A55: =IF(ISNA(MATCH(52,Alunos!$P$2:$P$301,0)),"",52) | B55: {=IFERROR(INDEX(Alunos!$A$2:$A$301,MATCH(52,Alunos!$P$2:$P$301,0))&"","")} | C55: {=IFERROR(INDEX(Alunos!$B$2:$B$301,MATCH(52,Alunos!$P$2:$P$301,0))&"","")} | D55: {=IFERROR(INDEX(Alunos!$C$2:$C$301,MATCH(52,Alunos!$P$2:$P$301,0))&"","")} | E55: {=IFERROR(INDEX(Alunos!$G$2:$G$301,MATCH(52,Alunos!$P$2:$P$301,0))&"","")} | F55: {=IFERROR(INDEX(Alunos!$H$2:$H$301,MATCH(52,Alunos!$P$2:$P$301,0))&"","")} | G55: {=IFERROR(INDEX(Alunos!$K$2:$K$301,MATCH(52,Alunos!$P$2:$P$301,0)),"")} | H55: {=IFERROR(INDEX(Alunos!$L$2:$L$301,MATCH(52,Alunos!$P$2:$P$301,0))&"","")}
A56: =IF(ISNA(MATCH(53,Alunos!$P$2:$P$301,0)),"",53) | B56: {=IFERROR(INDEX(Alunos!$A$2:$A$301,MATCH(53,Alunos!$P$2:$P$301,0))&"","")} | C56: {=IFERROR(INDEX(Alunos!$B$2:$B$301,MATCH(53,Alunos!$P$2:$P$301,0))&"","")} | D56: {=IFERROR(INDEX(Alunos!$C$2:$C$301,MATCH(53,Alunos!$P$2:$P$301,0))&"","")} | E56: {=IFERROR(INDEX(Alunos!$G$2:$G$301,MATCH(53,Alunos!$P$2:$P$301,0))&"","")} | F56: {=IFERROR(INDEX(Alunos!$H$2:$H$301,MATCH(53,Alunos!$P$2:$P$301,0))&"","")} | G56: {=IFERROR(INDEX(Alunos!$K$2:$K$301,MATCH(53,Alunos!$P$2:$P$301,0)),"")} | H56: {=IFERROR(INDEX(Alunos!$L$2:$L$301,MATCH(53,Alunos!$P$2:$P$301,0))&"","")}
A57: =IF(ISNA(MATCH(54,Alunos!$P$2:$P$301,0)),"",54) | B57: {=IFERROR(INDEX(Alunos!$A$2:$A$301,MATCH(54,Alunos!$P$2:$P$301,0))&"","")} | C57: {=IFERROR(INDEX(Alunos!$B$2:$B$301,MATCH(54,Alunos!$P$2:$P$301,0))&"","")} | D57: {=IFERROR(INDEX(Alunos!$C$2:$C$301,MATCH(54,Alunos!$P$2:$P$301,0))&"","")} | E57: {=IFERROR(INDEX(Alunos!$G$2:$G$301,MATCH(54,Alunos!$P$2:$P$301,0))&"","")} | F57: {=IFERROR(INDEX(Alunos!$H$2:$H$301,MATCH(54,Alunos!$P$2:$P$301,0))&"","")} | G57: {=IFERROR(INDEX(Alunos!$K$2:$K$301,MATCH(54,Alunos!$P$2:$P$301,0)),"")} | H57: {=IFERROR(INDEX(Alunos!$L$2:$L$301,MATCH(54,Alunos!$P$2:$P$301,0))&"","")}
A58: =IF(ISNA(MATCH(55,Alunos!$P$2:$P$301,0)),"",55) | B58: {=IFERROR(INDEX(Alunos!$A$2:$A$301,MATCH(55,Alunos!$P$2:$P$301,0))&"","")} | C58: {=IFERROR(INDEX(Alunos!$B$2:$B$301,MATCH(55,Alunos!$P$2:$P$301,0))&"","")} | D58: {=IFERROR(INDEX(Alunos!$C$2:$C$301,MATCH(55,Alunos!$P$2:$P$301,0))&"","")} | E58: {=IFERROR(INDEX(Alunos!$G$2:$G$301,MATCH(55,Alunos!$P$2:$P$301,0))&"","")} | F58: {=IFERROR(INDEX(Alunos!$H$2:$H$301,MATCH(55,Alunos!$P$2:$P$301,0))&"","")} | G58: {=IFERROR(INDEX(Alunos!$K$2:$K$301,MATCH(55,Alunos!$P$2:$P$301,0)),"")} | H58: {=IFERROR(INDEX(Alunos!$L$2:$L$301,MATCH(55,Alunos!$P$2:$P$301,0))&"","")}
A59: =IF(ISNA(MATCH(56,Alunos!$P$2:$P$301,0)),"",56) | B59: {=IFERROR(INDEX(Alunos!$A$2:$A$301,MATCH(56,Alunos!$P$2:$P$301,0))&"","")} | C59: {=IFERROR(INDEX(Alunos!$B$2:$B$301,MATCH(56,Alunos!$P$2:$P$301,0))&"","")} | D59: {=IFERROR(INDEX(Alunos!$C$2:$C$301,MATCH(56,Alunos!$P$2:$P$301,0))&"","")} | E59: {=IFERROR(INDEX(Alunos!$G$2:$G$301,MATCH(56,Alunos!$P$2:$P$301,0))&"","")} | F59: {=IFERROR(INDEX(Alunos!$H$2:$H$301,MATCH(56,Alunos!$P$2:$P$301,0))&"","")} | G59: {=IFERROR(INDEX(Alunos!$K$2:$K$301,MATCH(56,Alunos!$P$2:$P$301,0)),"")} | H59: {=IFERROR(INDEX(Alunos!$L$2:$L$301,MATCH(56,Alunos!$P$2:$P$301,0))&"","")}
A60: =IF(ISNA(MATCH(57,Alunos!$P$2:$P$301,0)),"",57) | B60: {=IFERROR(INDEX(Alunos!$A$2:$A$301,MATCH(57,Alunos!$P$2:$P$301,0))&"","")} | C60: {=IFERROR(INDEX(Alunos!$B$2:$B$301,MATCH(57,Alunos!$P$2:$P$301,0))&"","")} | D60: {=IFERROR(INDEX(Alunos!$C$2:$C$301,MATCH(57,Alunos!$P$2:$P$301,0))&"","")} | E60: {=IFERROR(INDEX(Alunos!$G$2:$G$301,MATCH(57,Alunos!$P$2:$P$301,0))&"","")} | F60: {=IFERROR(INDEX(Alunos!$H$2:$H$301,MATCH(57,Alunos!$P$2:$P$301,0))&"","")} | G60: {=IFERROR(INDEX(Alunos!$K$2:$K$301,MATCH(57,Alunos!$P$2:$P$301,0)),"")} | H60: {=IFERROR(INDEX(Alunos!$L$2:$L$301,MATCH(57,Alunos!$P$2:$P$301,0))&"","")}
A61: =IF(ISNA(MATCH(58,Alunos!$P$2:$P$301,0)),"",58) | B61: {=IFERROR(INDEX(Alunos!$A$2:$A$301,MATCH(58,Alunos!$P$2:$P$301,0))&"","")} | C61: {=IFERROR(INDEX(Alunos!$B$2:$B$301,MATCH(58,Alunos!$P$2:$P$301,0))&"","")} | D61: {=IFERROR(INDEX(Alunos!$C$2:$C$301,MATCH(58,Alunos!$P$2:$P$301,0))&"","")} | E61: {=IFERROR(INDEX(Alunos!$G$2:$G$301,MATCH(58,Alunos!$P$2:$P$301,0))&"","")} | F61: {=IFERROR(INDEX(Alunos!$H$2:$H$301,MATCH(58,Alunos!$P$2:$P$301,0))&"","")} | G61: {=IFERROR(INDEX(Alunos!$K$2:$K$301,MATCH(58,Alunos!$P$2:$P$301,0)),"")} | H61: {=IFERROR(INDEX(Alunos!$L$2:$L$301,MATCH(58,Alunos!$P$2:$P$301,0))&"","")}
A62: =IF(ISNA(MATCH(59,Alunos!$P$2:$P$301,0)),"",59) | B62: {=IFERROR(INDEX(Alunos!$A$2:$A$301,MATCH(59,Alunos!$P$2:$P$301,0))&"","")} | C62: {=IFERROR(INDEX(Alunos!$B$2:$B$301,MATCH(59,Alunos!$P$2:$P$301,0))&"","")} | D62: {=IFERROR(INDEX(Alunos!$C$2:$C$301,MATCH(59,Alunos!$P$2:$P$301,0))&"","")} | E62: {=IFERROR(INDEX(Alunos!$G$2:$G$301,MATCH(59,Alunos!$P$2:$P$301,0))&"","")} | F62: {=IFERROR(INDEX(Alunos!$H$2:$H$301,MATCH(59,Alunos!$P$2:$P$301,0))&"","")} | G62: {=IFERROR(INDEX(Alunos!$K$2:$K$301,MATCH(59,Alunos!$P$2:$P$301,0)),"")} | H62: {=IFERROR(INDEX(Alunos!$L$2:$L$301,MATCH(59,Alunos!$P$2:$P$301,0))&"","")}
A63: =IF(ISNA(MATCH(60,Alunos!$P$2:$P$301,0)),"",60) | B63: {=IFERROR(INDEX(Alunos!$A$2:$A$301,MATCH(60,Alunos!$P$2:$P$301,0))&"","")} | C63: {=IFERROR(INDEX(Alunos!$B$2:$B$301,MATCH(60,Alunos!$P$2:$P$301,0))&"","")} | D63: {=IFERROR(INDEX(Alunos!$C$2:$C$301,MATCH(60,Alunos!$P$2:$P$301,0))&"","")} | E63: {=IFERROR(INDEX(Alunos!$G$2:$G$301,MATCH(60,Alunos!$P$2:$P$301,0))&"","")} | F63: {=IFERROR(INDEX(Alunos!$H$2:$H$301,MATCH(60,Alunos!$P$2:$P$301,0))&"","")} | G63: {=IFERROR(INDEX(Alunos!$K$2:$K$301,MATCH(60,Alunos!$P$2:$P$301,0)),"")} | H63: {=IFERROR(INDEX(Alunos!$L$2:$L$301,MATCH(60,Alunos!$P$2:$P$301,0))&"","")}
A64: =IF(ISNA(MATCH(61,Alunos!$P$2:$P$301,0)),"",61) | B64: {=IFERROR(INDEX(Alunos!$A$2:$A$301,MATCH(61,Alunos!$P$2:$P$301,0))&"","")} | C64: {=IFERROR(INDEX(Alunos!$B$2:$B$301,MATCH(61,Alunos!$P$2:$P$301,0))&"","")} | D64: {=IFERROR(INDEX(Alunos!$C$2:$C$301,MATCH(61,Alunos!$P$2:$P$301,0))&"","")} | E64: {=IFERROR(INDEX(Alunos!$G$2:$G$301,MATCH(61,Alunos!$P$2:$P$301,0))&"","")} | F64: {=IFERROR(INDEX(Alunos!$H$2:$H$301,MATCH(61,Alunos!$P$2:$P$301,0))&"","")} | G64: {=IFERROR(INDEX(Alunos!$K$2:$K$301,MATCH(61,Alunos!$P$2:$P$301,0)),"")} | H64: {=IFERROR(INDEX(Alunos!$L$2:$L$301,MATCH(61,Alunos!$P$2:$P$301,0))&"","")}
A65: =IF(ISNA(MATCH(62,Alunos!$P$2:$P$301,0)),"",62) | B65: {=IFERROR(INDEX(Alunos!$A$2:$A$301,MATCH(62,Alunos!$P$2:$P$301,0))&"","")} | C65: {=IFERROR(INDEX(Alunos!$B$2:$B$301,MATCH(62,Alunos!$P$2:$P$301,0))&"","")} | D65: {=IFERROR(INDEX(Alunos!$C$2:$C$301,MATCH(62,Alunos!$P$2:$P$301,0))&"","")} | E65: {=IFERROR(INDEX(Alunos!$G$2:$G$301,MATCH(62,Alunos!$P$2:$P$301,0))&"","")} | F65: {=IFERROR(INDEX(Alunos!$H$2:$H$301,MATCH(62,Alunos!$P$2:$P$301,0))&"","")} | G65: {=IFERROR(INDEX(Alunos!$K$2:$K$301,MATCH(62,Alunos!$P$2:$P$301,0)),"")} | H65: {=IFERROR(INDEX(Alunos!$L$2:$L$301,MATCH(62,Alunos!$P$2:$P$301,0))&"","")}
A66: =IF(ISNA(MATCH(63,Alunos!$P$2:$P$301,0)),"",63) | B66: {=IFERROR(INDEX(Alunos!$A$2:$A$301,MATCH(63,Alunos!$P$2:$P$301,0))&"","")} | C66: {=IFERROR(INDEX(Alunos!$B$2:$B$301,MATCH(63,Alunos!$P$2:$P$301,0))&"","")} | D66: {=IFERROR(INDEX(Alunos!$C$2:$C$301,MATCH(63,Alunos!$P$2:$P$301,0))&"","")} | E66: {=IFERROR(INDEX(Alunos!$G$2:$G$301,MATCH(63,Alunos!$P$2:$P$301,0))&"","")} | F66: {=IFERROR(INDEX(Alunos!$H$2:$H$301,MATCH(63,Alunos!$P$2:$P$301,0))&"","")} | G66: {=IFERROR(INDEX(Alunos!$K$2:$K$301,MATCH(63,Alunos!$P$2:$P$301,0)),"")} | H66: {=IFERROR(INDEX(Alunos!$L$2:$L$301,MATCH(63,Alunos!$P$2:$P$301,0))&"","")}
A67: =IF(ISNA(MATCH(64,Alunos!$P$2:$P$301,0)),"",64) | B67: {=IFERROR(INDEX(Alunos!$A$2:$A$301,MATCH(64,Alunos!$P$2:$P$301,0))&"","")} | C67: {=IFERROR(INDEX(Alunos!$B$2:$B$301,MATCH(64,Alunos!$P$2:$P$301,0))&"","")} | D67: {=IFERROR(INDEX(Alunos!$C$2:$C$301,MATCH(64,Alunos!$P$2:$P$301,0))&"","")} | E67: {=IFERROR(INDEX(Alunos!$G$2:$G$301,MATCH(64,Alunos!$P$2:$P$301,0))&"","")} | F67: {=IFERROR(INDEX(Alunos!$H$2:$H$301,MATCH(64,Alunos!$P$2:$P$301,0))&"","")} | G67: {=IFERROR(INDEX(Alunos!$K$2:$K$301,MATCH(64,Alunos!$P$2:$P$301,0)),"")} | H67: {=IFERROR(INDEX(Alunos!$L$2:$L$301,MATCH(64,Alunos!$P$2:$P$301,0))&"","")}
A68: =IF(ISNA(MATCH(65,Alunos!$P$2:$P$301,0)),"",65) | B68: {=IFERROR(INDEX(Alunos!$A$2:$A$301,MATCH(65,Alunos!$P$2:$P$301,0))&"","")} | C68: {=IFERROR(INDEX(Alunos!$B$2:$B$301,MATCH(65,Alunos!$P$2:$P$301,0))&"","")} | D68: {=IFERROR(INDEX(Alunos!$C$2:$C$301,MATCH(65,Alunos!$P$2:$P$301,0))&"","")} | E68: {=IFERROR(INDEX(Alunos!$G$2:$G$301,MATCH(65,Alunos!$P$2:$P$301,0))&"","")} | F68: {=IFERROR(INDEX(Alunos!$H$2:$H$301,MATCH(65,Alunos!$P$2:$P$301,0))&"","")} | G68: {=IFERROR(INDEX(Alunos!$K$2:$K$301,MATCH(65,Alunos!$P$2:$P$301,0)),"")} | H68: {=IFERROR(INDEX(Alunos!$L$2:$L$301,MATCH(65,Alunos!$P$2:$P$301,0))&"","")}
A69: =IF(ISNA(MATCH(66,Alunos!$P$2:$P$301,0)),"",66) | B69: {=IFERROR(INDEX(Alunos!$A$2:$A$301,MATCH(66,Alunos!$P$2:$P$301,0))&"","")} | C69: {=IFERROR(INDEX(Alunos!$B$2:$B$301,MATCH(66,Alunos!$P$2:$P$301,0))&"","")} | D69: {=IFERROR(INDEX(Alunos!$C$2:$C$301,MATCH(66,Alunos!$P$2:$P$301,0))&"","")} | E69: {=IFERROR(INDEX(Alunos!$G$2:$G$301,MATCH(66,Alunos!$P$2:$P$301,0))&"","")} | F69: {=IFERROR(INDEX(Alunos!$H$2:$H$301,MATCH(66,Alunos!$P$2:$P$301,0))&"","")} | G69: {=IFERROR(INDEX(Alunos!$K$2:$K$301,MATCH(66,Alunos!$P$2:$P$301,0)),"")} | H69: {=IFERROR(INDEX(Alunos!$L$2:$L$301,MATCH(66,Alunos!$P$2:$P$301,0))&"","")}
A70: =IF(ISNA(MATCH(67,Alunos!$P$2:$P$301,0)),"",67) | B70: {=IFERROR(INDEX(Alunos!$A$2:$A$301,MATCH(67,Alunos!$P$2:$P$301,0))&"","")} | C70: {=IFERROR(INDEX(Alunos!$B$2:$B$301,MATCH(67,Alunos!$P$2:$P$301,0))&"","")} | D70: {=IFERROR(INDEX(Alunos!$C$2:$C$301,MATCH(67,Alunos!$P$2:$P$301,0))&"","")} | E70: {=IFERROR(INDEX(Alunos!$G$2:$G$301,MATCH(67,Alunos!$P$2:$P$301,0))&"","")} | F70: {=IFERROR(INDEX(Alunos!$H$2:$H$301,MATCH(67,Alunos!$P$2:$P$301,0))&"","")} | G70: {=IFERROR(INDEX(Alunos!$K$2:$K$301,MATCH(67,Alunos!$P$2:$P$301,0)),"")} | H70: {=IFERROR(INDEX(Alunos!$L$2:$L$301,MATCH(67,Alunos!$P$2:$P$301,0))&"","")}
A71: =IF(ISNA(MATCH(68,Alunos!$P$2:$P$301,0)),"",68) | B71: {=IFERROR(INDEX(Alunos!$A$2:$A$301,MATCH(68,Alunos!$P$2:$P$301,0))&"","")} | C71: {=IFERROR(INDEX(Alunos!$B$2:$B$301,MATCH(68,Alunos!$P$2:$P$301,0))&"","")} | D71: {=IFERROR(INDEX(Alunos!$C$2:$C$301,MATCH(68,Alunos!$P$2:$P$301,0))&"","")} | E71: {=IFERROR(INDEX(Alunos!$G$2:$G$301,MATCH(68,Alunos!$P$2:$P$301,0))&"","")} | F71: {=IFERROR(INDEX(Alunos!$H$2:$H$301,MATCH(68,Alunos!$P$2:$P$301,0))&"","")} | G71: {=IFERROR(INDEX(Alunos!$K$2:$K$301,MATCH(68,Alunos!$P$2:$P$301,0)),"")} | H71: {=IFERROR(INDEX(Alunos!$L$2:$L$301,MATCH(68,Alunos!$P$2:$P$301,0))&"","")}
A72: =IF(ISNA(MATCH(69,Alunos!$P$2:$P$301,0)),"",69) | B72: {=IFERROR(INDEX(Alunos!$A$2:$A$301,MATCH(69,Alunos!$P$2:$P$301,0))&"","")} | C72: {=IFERROR(INDEX(Alunos!$B$2:$B$301,MATCH(69,Alunos!$P$2:$P$301,0))&"","")} | D72: {=IFERROR(INDEX(Alunos!$C$2:$C$301,MATCH(69,Alunos!$P$2:$P$301,0))&"","")} | E72: {=IFERROR(INDEX(Alunos!$G$2:$G$301,MATCH(69,Alunos!$P$2:$P$301,0))&"","")} | F72: {=IFERROR(INDEX(Alunos!$H$2:$H$301,MATCH(69,Alunos!$P$2:$P$301,0))&"","")} | G72: {=IFERROR(INDEX(Alunos!$K$2:$K$301,MATCH(69,Alunos!$P$2:$P$301,0)),"")} | H72: {=IFERROR(INDEX(Alunos!$L$2:$L$301,MATCH(69,Alunos!$P$2:$P$301,0))&"","")}
A73: =IF(ISNA(MATCH(70,Alunos!$P$2:$P$301,0)),"",70) | B73: {=IFERROR(INDEX(Alunos!$A$2:$A$301,MATCH(70,Alunos!$P$2:$P$301,0))&"","")} | C73: {=IFERROR(INDEX(Alunos!$B$2:$B$301,MATCH(70,Alunos!$P$2:$P$301,0))&"","")} | D73: {=IFERROR(INDEX(Alunos!$C$2:$C$301,MATCH(70,Alunos!$P$2:$P$301,0))&"","")} | E73: {=IFERROR(INDEX(Alunos!$G$2:$G$301,MATCH(70,Alunos!$P$2:$P$301,0))&"","")} | F73: {=IFERROR(INDEX(Alunos!$H$2:$H$301,MATCH(70,Alunos!$P$2:$P$301,0))&"","")} | G73: {=IFERROR(INDEX(Alunos!$K$2:$K$301,MATCH(70,Alunos!$P$2:$P$301,0)),"")} | H73: {=IFERROR(INDEX(Alunos!$L$2:$L$301,MATCH(70,Alunos!$P$2:$P$301,0))&"","")}
A74: =IF(ISNA(MATCH(71,Alunos!$P$2:$P$301,0)),"",71) | B74: {=IFERROR(INDEX(Alunos!$A$2:$A$301,MATCH(71,Alunos!$P$2:$P$301,0))&"","")} | C74: {=IFERROR(INDEX(Alunos!$B$2:$B$301,MATCH(71,Alunos!$P$2:$P$301,0))&"","")} | D74: {=IFERROR(INDEX(Alunos!$C$2:$C$301,MATCH(71,Alunos!$P$2:$P$301,0))&"","")} | E74: {=IFERROR(INDEX(Alunos!$G$2:$G$301,MATCH(71,Alunos!$P$2:$P$301,0))&"","")} | F74: {=IFERROR(INDEX(Alunos!$H$2:$H$301,MATCH(71,Alunos!$P$2:$P$301,0))&"","")} | G74: {=IFERROR(INDEX(Alunos!$K$2:$K$301,MATCH(71,Alunos!$P$2:$P$301,0)),"")} | H74: {=IFERROR(INDEX(Alunos!$L$2:$L$301,MATCH(71,Alunos!$P$2:$P$301,0))&"","")}
A75: =IF(ISNA(MATCH(72,Alunos!$P$2:$P$301,0)),"",72) | B75: {=IFERROR(INDEX(Alunos!$A$2:$A$301,MATCH(72,Alunos!$P$2:$P$301,0))&"","")} | C75: {=IFERROR(INDEX(Alunos!$B$2:$B$301,MATCH(72,Alunos!$P$2:$P$301,0))&"","")} | D75: {=IFERROR(INDEX(Alunos!$C$2:$C$301,MATCH(72,Alunos!$P$2:$P$301,0))&"","")} | E75: {=IFERROR(INDEX(Alunos!$G$2:$G$301,MATCH(72,Alunos!$P$2:$P$301,0))&"","")} | F75: {=IFERROR(INDEX(Alunos!$H$2:$H$301,MATCH(72,Alunos!$P$2:$P$301,0))&"","")} | G75: {=IFERROR(INDEX(Alunos!$K$2:$K$301,MATCH(72,Alunos!$P$2:$P$301,0)),"")} | H75: {=IFERROR(INDEX(Alunos!$L$2:$L$301,MATCH(72,Alunos!$P$2:$P$301,0))&"","")}
A76: =IF(ISNA(MATCH(73,Alunos!$P$2:$P$301,0)),"",73) | B76: {=IFERROR(INDEX(Alunos!$A$2:$A$301,MATCH(73,Alunos!$P$2:$P$301,0))&"","")} | C76: {=IFERROR(INDEX(Alunos!$B$2:$B$301,MATCH(73,Alunos!$P$2:$P$301,0))&"","")} | D76: {=IFERROR(INDEX(Alunos!$C$2:$C$301,MATCH(73,Alunos!$P$2:$P$301,0))&"","")} | E76: {=IFERROR(INDEX(Alunos!$G$2:$G$301,MATCH(73,Alunos!$P$2:$P$301,0))&"","")} | F76: {=IFERROR(INDEX(Alunos!$H$2:$H$301,MATCH(73,Alunos!$P$2:$P$301,0))&"","")} | G76: {=IFERROR(INDEX(Alunos!$K$2:$K$301,MATCH(73,Alunos!$P$2:$P$301,0)),"")} | H76: {=IFERROR(INDEX(Alunos!$L$2:$L$301,MATCH(73,Alunos!$P$2:$P$301,0))&"","")}
A77: =IF(ISNA(MATCH(74,Alunos!$P$2:$P$301,0)),"",74) | B77: {=IFERROR(INDEX(Alunos!$A$2:$A$301,MATCH(74,Alunos!$P$2:$P$301,0))&"","")} | C77: {=IFERROR(INDEX(Alunos!$B$2:$B$301,MATCH(74,Alunos!$P$2:$P$301,0))&"","")} | D77: {=IFERROR(INDEX(Alunos!$C$2:$C$301,MATCH(74,Alunos!$P$2:$P$301,0))&"","")} | E77: {=IFERROR(INDEX(Alunos!$G$2:$G$301,MATCH(74,Alunos!$P$2:$P$301,0))&"","")} | F77: {=IFERROR(INDEX(Alunos!$H$2:$H$301,MATCH(74,Alunos!$P$2:$P$301,0))&"","")} | G77: {=IFERROR(INDEX(Alunos!$K$2:$K$301,MATCH(74,Alunos!$P$2:$P$301,0)),"")} | H77: {=IFERROR(INDEX(Alunos!$L$2:$L$301,MATCH(74,Alunos!$P$2:$P$301,0))&"","")}
A78: =IF(ISNA(MATCH(75,Alunos!$P$2:$P$301,0)),"",75) | B78: {=IFERROR(INDEX(Alunos!$A$2:$A$301,MATCH(75,Alunos!$P$2:$P$301,0))&"","")} | C78: {=IFERROR(INDEX(Alunos!$B$2:$B$301,MATCH(75,Alunos!$P$2:$P$301,0))&"","")} | D78: {=IFERROR(INDEX(Alunos!$C$2:$C$301,MATCH(75,Alunos!$P$2:$P$301,0))&"","")} | E78: {=IFERROR(INDEX(Alunos!$G$2:$G$301,MATCH(75,Alunos!$P$2:$P$301,0))&"","")} | F78: {=IFERROR(INDEX(Alunos!$H$2:$H$301,MATCH(75,Alunos!$P$2:$P$301,0))&"","")} | G78: {=IFERROR(INDEX(Alunos!$K$2:$K$301,MATCH(75,Alunos!$P$2:$P$301,0)),"")} | H78: {=IFERROR(INDEX(Alunos!$L$2:$L$301,MATCH(75,Alunos!$P$2:$P$301,0))&"","")}
A79: =IF(ISNA(MATCH(76,Alunos!$P$2:$P$301,0)),"",76) | B79: {=IFERROR(INDEX(Alunos!$A$2:$A$301,MATCH(76,Alunos!$P$2:$P$301,0))&"","")} | C79: {=IFERROR(INDEX(Alunos!$B$2:$B$301,MATCH(76,Alunos!$P$2:$P$301,0))&"","")} | D79: {=IFERROR(INDEX(Alunos!$C$2:$C$301,MATCH(76,Alunos!$P$2:$P$301,0))&"","")} | E79: {=IFERROR(INDEX(Alunos!$G$2:$G$301,MATCH(76,Alunos!$P$2:$P$301,0))&"","")} | F79: {=IFERROR(INDEX(Alunos!$H$2:$H$301,MATCH(76,Alunos!$P$2:$P$301,0))&"","")} | G79: {=IFERROR(INDEX(Alunos!$K$2:$K$301,MATCH(76,Alunos!$P$2:$P$301,0)),"")} | H79: {=IFERROR(INDEX(Alunos!$L$2:$L$301,MATCH(76,Alunos!$P$2:$P$301,0))&"","")}
A80: =IF(ISNA(MATCH(77,Alunos!$P$2:$P$301,0)),"",77) | B80: {=IFERROR(INDEX(Alunos!$A$2:$A$301,MATCH(77,Alunos!$P$2:$P$301,0))&"","")} | C80: {=IFERROR(INDEX(Alunos!$B$2:$B$301,MATCH(77,Alunos!$P$2:$P$301,0))&"","")} | D80: {=IFERROR(INDEX(Alunos!$C$2:$C$301,MATCH(77,Alunos!$P$2:$P$301,0))&"","")} | E80: {=IFERROR(INDEX(Alunos!$G$2:$G$301,MATCH(77,Alunos!$P$2:$P$301,0))&"","")} | F80: {=IFERROR(INDEX(Alunos!$H$2:$H$301,MATCH(77,Alunos!$P$2:$P$301,0))&"","")} | G80: {=IFERROR(INDEX(Alunos!$K$2:$K$301,MATCH(77,Alunos!$P$2:$P$301,0)),"")} | H80: {=IFERROR(INDEX(Alunos!$L$2:$L$301,MATCH(77,Alunos!$P$2:$P$301,0))&"","")}
A81: =IF(ISNA(MATCH(78,Alunos!$P$2:$P$301,0)),"",78) | B81: {=IFERROR(INDEX(Alunos!$A$2:$A$301,MATCH(78,Alunos!$P$2:$P$301,0))&"","")} | C81: {=IFERROR(INDEX(Alunos!$B$2:$B$301,MATCH(78,Alunos!$P$2:$P$301,0))&"","")} | D81: {=IFERROR(INDEX(Alunos!$C$2:$C$301,MATCH(78,Alunos!$P$2:$P$301,0))&"","")} | E81: {=IFERROR(INDEX(Alunos!$G$2:$G$301,MATCH(78,Alunos!$P$2:$P$301,0))&"","")} | F81: {=IFERROR(INDEX(Alunos!$H$2:$H$301,MATCH(78,Alunos!$P$2:$P$301,0))&"","")} | G81: {=IFERROR(INDEX(Alunos!$K$2:$K$301,MATCH(78,Alunos!$P$2:$P$301,0)),"")} | H81: {=IFERROR(INDEX(Alunos!$L$2:$L$301,MATCH(78,Alunos!$P$2:$P$301,0))&"","")}
A82: =IF(ISNA(MATCH(79,Alunos!$P$2:$P$301,0)),"",79) | B82: {=IFERROR(INDEX(Alunos!$A$2:$A$301,MATCH(79,Alunos!$P$2:$P$301,0))&"","")} | C82: {=IFERROR(INDEX(Alunos!$B$2:$B$301,MATCH(79,Alunos!$P$2:$P$301,0))&"","")} | D82: {=IFERROR(INDEX(Alunos!$C$2:$C$301,MATCH(79,Alunos!$P$2:$P$301,0))&"","")} | E82: {=IFERROR(INDEX(Alunos!$G$2:$G$301,MATCH(79,Alunos!$P$2:$P$301,0))&"","")} | F82: {=IFERROR(INDEX(Alunos!$H$2:$H$301,MATCH(79,Alunos!$P$2:$P$301,0))&"","")} | G82: {=IFERROR(INDEX(Alunos!$K$2:$K$301,MATCH(79,Alunos!$P$2:$P$301,0)),"")} | H82: {=IFERROR(INDEX(Alunos!$L$2:$L$301,MATCH(79,Alunos!$P$2:$P$301,0))&"","")}
A83: =IF(ISNA(MATCH(80,Alunos!$P$2:$P$301,0)),"",80) | B83: {=IFERROR(INDEX(Alunos!$A$2:$A$301,MATCH(80,Alunos!$P$2:$P$301,0))&"","")} | C83: {=IFERROR(INDEX(Alunos!$B$2:$B$301,MATCH(80,Alunos!$P$2:$P$301,0))&"","")} | D83: {=IFERROR(INDEX(Alunos!$C$2:$C$301,MATCH(80,Alunos!$P$2:$P$301,0))&"","")} | E83: {=IFERROR(INDEX(Alunos!$G$2:$G$301,MATCH(80,Alunos!$P$2:$P$301,0))&"","")} | F83: {=IFERROR(INDEX(Alunos!$H$2:$H$301,MATCH(80,Alunos!$P$2:$P$301,0))&"","")} | G83: {=IFERROR(INDEX(Alunos!$K$2:$K$301,MATCH(80,Alunos!$P$2:$P$301,0)),"")} | H83: {=IFERROR(INDEX(Alunos!$L$2:$L$301,MATCH(80,Alunos!$P$2:$P$301,0))&"","")}
A84: =IF(ISNA(MATCH(81,Alunos!$P$2:$P$301,0)),"",81) | B84: {=IFERROR(INDEX(Alunos!$A$2:$A$301,MATCH(81,Alunos!$P$2:$P$301,0))&"","")} | C84: {=IFERROR(INDEX(Alunos!$B$2:$B$301,MATCH(81,Alunos!$P$2:$P$301,0))&"","")} | D84: {=IFERROR(INDEX(Alunos!$C$2:$C$301,MATCH(81,Alunos!$P$2:$P$301,0))&"","")} | E84: {=IFERROR(INDEX(Alunos!$G$2:$G$301,MATCH(81,Alunos!$P$2:$P$301,0))&"","")} | F84: {=IFERROR(INDEX(Alunos!$H$2:$H$301,MATCH(81,Alunos!$P$2:$P$301,0))&"","")} | G84: {=IFERROR(INDEX(Alunos!$K$2:$K$301,MATCH(81,Alunos!$P$2:$P$301,0)),"")} | H84: {=IFERROR(INDEX(Alunos!$L$2:$L$301,MATCH(81,Alunos!$P$2:$P$301,0))&"","")}
A85: =IF(ISNA(MATCH(82,Alunos!$P$2:$P$301,0)),"",82) | B85: {=IFERROR(INDEX(Alunos!$A$2:$A$301,MATCH(82,Alunos!$P$2:$P$301,0))&"","")} | C85: {=IFERROR(INDEX(Alunos!$B$2:$B$301,MATCH(82,Alunos!$P$2:$P$301,0))&"","")} | D85: {=IFERROR(INDEX(Alunos!$C$2:$C$301,MATCH(82,Alunos!$P$2:$P$301,0))&"","")} | E85: {=IFERROR(INDEX(Alunos!$G$2:$G$301,MATCH(82,Alunos!$P$2:$P$301,0))&"","")} | F85: {=IFERROR(INDEX(Alunos!$H$2:$H$301,MATCH(82,Alunos!$P$2:$P$301,0))&"","")} | G85: {=IFERROR(INDEX(Alunos!$K$2:$K$301,MATCH(82,Alunos!$P$2:$P$301,0)),"")} | H85: {=IFERROR(INDEX(Alunos!$L$2:$L$301,MATCH(82,Alunos!$P$2:$P$301,0))&"","")}
A86: =IF(ISNA(MATCH(83,Alunos!$P$2:$P$301,0)),"",83) | B86: {=IFERROR(INDEX(Alunos!$A$2:$A$301,MATCH(83,Alunos!$P$2:$P$301,0))&"","")} | C86: {=IFERROR(INDEX(Alunos!$B$2:$B$301,MATCH(83,Alunos!$P$2:$P$301,0))&"","")} | D86: {=IFERROR(INDEX(Alunos!$C$2:$C$301,MATCH(83,Alunos!$P$2:$P$301,0))&"","")} | E86: {=IFERROR(INDEX(Alunos!$G$2:$G$301,MATCH(83,Alunos!$P$2:$P$301,0))&"","")} | F86: {=IFERROR(INDEX(Alunos!$H$2:$H$301,MATCH(83,Alunos!$P$2:$P$301,0))&"","")} | G86: {=IFERROR(INDEX(Alunos!$K$2:$K$301,MATCH(83,Alunos!$P$2:$P$301,0)),"")} | H86: {=IFERROR(INDEX(Alunos!$L$2:$L$301,MATCH(83,Alunos!$P$2:$P$301,0))&"","")}
A87: =IF(ISNA(MATCH(84,Alunos!$P$2:$P$301,0)),"",84) | B87: {=IFERROR(INDEX(Alunos!$A$2:$A$301,MATCH(84,Alunos!$P$2:$P$301,0))&"","")} | C87: {=IFERROR(INDEX(Alunos!$B$2:$B$301,MATCH(84,Alunos!$P$2:$P$301,0))&"","")} | D87: {=IFERROR(INDEX(Alunos!$C$2:$C$301,MATCH(84,Alunos!$P$2:$P$301,0))&"","")} | E87: {=IFERROR(INDEX(Alunos!$G$2:$G$301,MATCH(84,Alunos!$P$2:$P$301,0))&"","")} | F87: {=IFERROR(INDEX(Alunos!$H$2:$H$301,MATCH(84,Alunos!$P$2:$P$301,0))&"","")} | G87: {=IFERROR(INDEX(Alunos!$K$2:$K$301,MATCH(84,Alunos!$P$2:$P$301,0)),"")} | H87: {=IFERROR(INDEX(Alunos!$L$2:$L$301,MATCH(84,Alunos!$P$2:$P$301,0))&"","")}
A88: =IF(ISNA(MATCH(85,Alunos!$P$2:$P$301,0)),"",85) | B88: {=IFERROR(INDEX(Alunos!$A$2:$A$301,MATCH(85,Alunos!$P$2:$P$301,0))&"","")} | C88: {=IFERROR(INDEX(Alunos!$B$2:$B$301,MATCH(85,Alunos!$P$2:$P$301,0))&"","")} | D88: {=IFERROR(INDEX(Alunos!$C$2:$C$301,MATCH(85,Alunos!$P$2:$P$301,0))&"","")} | E88: {=IFERROR(INDEX(Alunos!$G$2:$G$301,MATCH(85,Alunos!$P$2:$P$301,0))&"","")} | F88: {=IFERROR(INDEX(Alunos!$H$2:$H$301,MATCH(85,Alunos!$P$2:$P$301,0))&"","")} | G88: {=IFERROR(INDEX(Alunos!$K$2:$K$301,MATCH(85,Alunos!$P$2:$P$301,0)),"")} | H88: {=IFERROR(INDEX(Alunos!$L$2:$L$301,MATCH(85,Alunos!$P$2:$P$301,0))&"","")}
A89: =IF(ISNA(MATCH(86,Alunos!$P$2:$P$301,0)),"",86) | B89: {=IFERROR(INDEX(Alunos!$A$2:$A$301,MATCH(86,Alunos!$P$2:$P$301,0))&"","")} | C89: {=IFERROR(INDEX(Alunos!$B$2:$B$301,MATCH(86,Alunos!$P$2:$P$301,0))&"","")} | D89: {=IFERROR(INDEX(Alunos!$C$2:$C$301,MATCH(86,Alunos!$P$2:$P$301,0))&"","")} | E89: {=IFERROR(INDEX(Alunos!$G$2:$G$301,MATCH(86,Alunos!$P$2:$P$301,0))&"","")} | F89: {=IFERROR(INDEX(Alunos!$H$2:$H$301,MATCH(86,Alunos!$P$2:$P$301,0))&"","")} | G89: {=IFERROR(INDEX(Alunos!$K$2:$K$301,MATCH(86,Alunos!$P$2:$P$301,0)),"")} | H89: {=IFERROR(INDEX(Alunos!$L$2:$L$301,MATCH(86,Alunos!$P$2:$P$301,0))&"","")}
A90: =IF(ISNA(MATCH(87,Alunos!$P$2:$P$301,0)),"",87) | B90: {=IFERROR(INDEX(Alunos!$A$2:$A$301,MATCH(87,Alunos!$P$2:$P$301,0))&"","")} | C90: {=IFERROR(INDEX(Alunos!$B$2:$B$301,MATCH(87,Alunos!$P$2:$P$301,0))&"","")} | D90: {=IFERROR(INDEX(Alunos!$C$2:$C$301,MATCH(87,Alunos!$P$2:$P$301,0))&"","")} | E90: {=IFERROR(INDEX(Alunos!$G$2:$G$301,MATCH(87,Alunos!$P$2:$P$301,0))&"","")} | F90: {=IFERROR(INDEX(Alunos!$H$2:$H$301,MATCH(87,Alunos!$P$2:$P$301,0))&"","")} | G90: {=IFERROR(INDEX(Alunos!$K$2:$K$301,MATCH(87,Alunos!$P$2:$P$301,0)),"")} | H90: {=IFERROR(INDEX(Alunos!$L$2:$L$301,MATCH(87,Alunos!$P$2:$P$301,0))&"","")}
A91: =IF(ISNA(MATCH(88,Alunos!$P$2:$P$301,0)),"",88) | B91: {=IFERROR(INDEX(Alunos!$A$2:$A$301,MATCH(88,Alunos!$P$2:$P$301,0))&"","")} | C91: {=IFERROR(INDEX(Alunos!$B$2:$B$301,MATCH(88,Alunos!$P$2:$P$301,0))&"","")} | D91: {=IFERROR(INDEX(Alunos!$C$2:$C$301,MATCH(88,Alunos!$P$2:$P$301,0))&"","")} | E91: {=IFERROR(INDEX(Alunos!$G$2:$G$301,MATCH(88,Alunos!$P$2:$P$301,0))&"","")} | F91: {=IFERROR(INDEX(Alunos!$H$2:$H$301,MATCH(88,Alunos!$P$2:$P$301,0))&"","")} | G91: {=IFERROR(INDEX(Alunos!$K$2:$K$301,MATCH(88,Alunos!$P$2:$P$301,0)),"")} | H91: {=IFERROR(INDEX(Alunos!$L$2:$L$301,MATCH(88,Alunos!$P$2:$P$301,0))&"","")}
A92: =IF(ISNA(MATCH(89,Alunos!$P$2:$P$301,0)),"",89) | B92: {=IFERROR(INDEX(Alunos!$A$2:$A$301,MATCH(89,Alunos!$P$2:$P$301,0))&"","")} | C92: {=IFERROR(INDEX(Alunos!$B$2:$B$301,MATCH(89,Alunos!$P$2:$P$301,0))&"","")} | D92: {=IFERROR(INDEX(Alunos!$C$2:$C$301,MATCH(89,Alunos!$P$2:$P$301,0))&"","")} | E92: {=IFERROR(INDEX(Alunos!$G$2:$G$301,MATCH(89,Alunos!$P$2:$P$301,0))&"","")} | F92: {=IFERROR(INDEX(Alunos!$H$2:$H$301,MATCH(89,Alunos!$P$2:$P$301,0))&"","")} | G92: {=IFERROR(INDEX(Alunos!$K$2:$K$301,MATCH(89,Alunos!$P$2:$P$301,0)),"")} | H92: {=IFERROR(INDEX(Alunos!$L$2:$L$301,MATCH(89,Alunos!$P$2:$P$301,0))&"","")}
A93: =IF(ISNA(MATCH(90,Alunos!$P$2:$P$301,0)),"",90) | B93: {=IFERROR(INDEX(Alunos!$A$2:$A$301,MATCH(90,Alunos!$P$2:$P$301,0))&"","")} | C93: {=IFERROR(INDEX(Alunos!$B$2:$B$301,MATCH(90,Alunos!$P$2:$P$301,0))&"","")} | D93: {=IFERROR(INDEX(Alunos!$C$2:$C$301,MATCH(90,Alunos!$P$2:$P$301,0))&"","")} | E93: {=IFERROR(INDEX(Alunos!$G$2:$G$301,MATCH(90,Alunos!$P$2:$P$301,0))&"","")} | F93: {=IFERROR(INDEX(Alunos!$H$2:$H$301,MATCH(90,Alunos!$P$2:$P$301,0))&"","")} | G93: {=IFERROR(INDEX(Alunos!$K$2:$K$301,MATCH(90,Alunos!$P$2:$P$301,0)),"")} | H93: {=IFERROR(INDEX(Alunos!$L$2:$L$301,MATCH(90,Alunos!$P$2:$P$301,0))&"","")}
A94: =IF(ISNA(MATCH(91,Alunos!$P$2:$P$301,0)),"",91) | B94: {=IFERROR(INDEX(Alunos!$A$2:$A$301,MATCH(91,Alunos!$P$2:$P$301,0))&"","")} | C94: {=IFERROR(INDEX(Alunos!$B$2:$B$301,MATCH(91,Alunos!$P$2:$P$301,0))&"","")} | D94: {=IFERROR(INDEX(Alunos!$C$2:$C$301,MATCH(91,Alunos!$P$2:$P$301,0))&"","")} | E94: {=IFERROR(INDEX(Alunos!$G$2:$G$301,MATCH(91,Alunos!$P$2:$P$301,0))&"","")} | F94: {=IFERROR(INDEX(Alunos!$H$2:$H$301,MATCH(91,Alunos!$P$2:$P$301,0))&"","")} | G94: {=IFERROR(INDEX(Alunos!$K$2:$K$301,MATCH(91,Alunos!$P$2:$P$301,0)),"")} | H94: {=IFERROR(INDEX(Alunos!$L$2:$L$301,MATCH(91,Alunos!$P$2:$P$301,0))&"","")}
A95: =IF(ISNA(MATCH(92,Alunos!$P$2:$P$301,0)),"",92) | B95: {=IFERROR(INDEX(Alunos!$A$2:$A$301,MATCH(92,Alunos!$P$2:$P$301,0))&"","")} | C95: {=IFERROR(INDEX(Alunos!$B$2:$B$301,MATCH(92,Alunos!$P$2:$P$301,0))&"","")} | D95: {=IFERROR(INDEX(Alunos!$C$2:$C$301,MATCH(92,Alunos!$P$2:$P$301,0))&"","")} | E95: {=IFERROR(INDEX(Alunos!$G$2:$G$301,MATCH(92,Alunos!$P$2:$P$301,0))&"","")} | F95: {=IFERROR(INDEX(Alunos!$H$2:$H$301,MATCH(92,Alunos!$P$2:$P$301,0))&"","")} | G95: {=IFERROR(INDEX(Alunos!$K$2:$K$301,MATCH(92,Alunos!$P$2:$P$301,0)),"")} | H95: {=IFERROR(INDEX(Alunos!$L$2:$L$301,MATCH(92,Alunos!$P$2:$P$301,0))&"","")}
A96: =IF(ISNA(MATCH(93,Alunos!$P$2:$P$301,0)),"",93) | B96: {=IFERROR(INDEX(Alunos!$A$2:$A$301,MATCH(93,Alunos!$P$2:$P$301,0))&"","")} | C96: {=IFERROR(INDEX(Alunos!$B$2:$B$301,MATCH(93,Alunos!$P$2:$P$301,0))&"","")} | D96: {=IFERROR(INDEX(Alunos!$C$2:$C$301,MATCH(93,Alunos!$P$2:$P$301,0))&"","")} | E96: {=IFERROR(INDEX(Alunos!$G$2:$G$301,MATCH(93,Alunos!$P$2:$P$301,0))&"","")} | F96: {=IFERROR(INDEX(Alunos!$H$2:$H$301,MATCH(93,Alunos!$P$2:$P$301,0))&"","")} | G96: {=IFERROR(INDEX(Alunos!$K$2:$K$301,MATCH(93,Alunos!$P$2:$P$301,0)),"")} | H96: {=IFERROR(INDEX(Alunos!$L$2:$L$301,MATCH(93,Alunos!$P$2:$P$301,0))&"","")}
A97: =IF(ISNA(MATCH(94,Alunos!$P$2:$P$301,0)),"",94) | B97: {=IFERROR(INDEX(Alunos!$A$2:$A$301,MATCH(94,Alunos!$P$2:$P$301,0))&"","")} | C97: {=IFERROR(INDEX(Alunos!$B$2:$B$301,MATCH(94,Alunos!$P$2:$P$301,0))&"","")} | D97: {=IFERROR(INDEX(Alunos!$C$2:$C$301,MATCH(94,Alunos!$P$2:$P$301,0))&"","")} | E97: {=IFERROR(INDEX(Alunos!$G$2:$G$301,MATCH(94,Alunos!$P$2:$P$301,0))&"","")} | F97: {=IFERROR(INDEX(Alunos!$H$2:$H$301,MATCH(94,Alunos!$P$2:$P$301,0))&"","")} | G97: {=IFERROR(INDEX(Alunos!$K$2:$K$301,MATCH(94,Alunos!$P$2:$P$301,0)),"")} | H97: {=IFERROR(INDEX(Alunos!$L$2:$L$301,MATCH(94,Alunos!$P$2:$P$301,0))&"","")}
A98: =IF(ISNA(MATCH(95,Alunos!$P$2:$P$301,0)),"",95) | B98: {=IFERROR(INDEX(Alunos!$A$2:$A$301,MATCH(95,Alunos!$P$2:$P$301,0))&"","")} | C98: {=IFERROR(INDEX(Alunos!$B$2:$B$301,MATCH(95,Alunos!$P$2:$P$301,0))&"","")} | D98: {=IFERROR(INDEX(Alunos!$C$2:$C$301,MATCH(95,Alunos!$P$2:$P$301,0))&"","")} | E98: {=IFERROR(INDEX(Alunos!$G$2:$G$301,MATCH(95,Alunos!$P$2:$P$301,0))&"","")} | F98: {=IFERROR(INDEX(Alunos!$H$2:$H$301,MATCH(95,Alunos!$P$2:$P$301,0))&"","")} | G98: {=IFERROR(INDEX(Alunos!$K$2:$K$301,MATCH(95,Alunos!$P$2:$P$301,0)),"")} | H98: {=IFERROR(INDEX(Alunos!$L$2:$L$301,MATCH(95,Alunos!$P$2:$P$301,0))&"","")}
A99: =IF(ISNA(MATCH(96,Alunos!$P$2:$P$301,0)),"",96) | B99: {=IFERROR(INDEX(Alunos!$A$2:$A$301,MATCH(96,Alunos!$P$2:$P$301,0))&"","")} | C99: {=IFERROR(INDEX(Alunos!$B$2:$B$301,MATCH(96,Alunos!$P$2:$P$301,0))&"","")} | D99: {=IFERROR(INDEX(Alunos!$C$2:$C$301,MATCH(96,Alunos!$P$2:$P$301,0))&"","")} | E99: {=IFERROR(INDEX(Alunos!$G$2:$G$301,MATCH(96,Alunos!$P$2:$P$301,0))&"","")} | F99: {=IFERROR(INDEX(Alunos!$H$2:$H$301,MATCH(96,Alunos!$P$2:$P$301,0))&"","")} | G99: {=IFERROR(INDEX(Alunos!$K$2:$K$301,MATCH(96,Alunos!$P$2:$P$301,0)),"")} | H99: {=IFERROR(INDEX(Alunos!$L$2:$L$301,MATCH(96,Alunos!$P$2:$P$301,0))&"","")}
A100: =IF(ISNA(MATCH(97,Alunos!$P$2:$P$301,0)),"",97) | B100: {=IFERROR(INDEX(Alunos!$A$2:$A$301,MATCH(97,Alunos!$P$2:$P$301,0))&"","")} | C100: {=IFERROR(INDEX(Alunos!$B$2:$B$301,MATCH(97,Alunos!$P$2:$P$301,0))&"","")} | D100: {=IFERROR(INDEX(Alunos!$C$2:$C$301,MATCH(97,Alunos!$P$2:$P$301,0))&"","")} | E100: {=IFERROR(INDEX(Alunos!$G$2:$G$301,MATCH(97,Alunos!$P$2:$P$301,0))&"","")} | F100: {=IFERROR(INDEX(Alunos!$H$2:$H$301,MATCH(97,Alunos!$P$2:$P$301,0))&"","")} | G100: {=IFERROR(INDEX(Alunos!$K$2:$K$301,MATCH(97,Alunos!$P$2:$P$301,0)),"")} | H100: {=IFERROR(INDEX(Alunos!$L$2:$L$301,MATCH(97,Alunos!$P$2:$P$301,0))&"","")}
...

Sheet Boletos
A1: ="Boletos "&Config!B4&" – gerados automaticamente (12 por aluno). Preencha as colunas em bege com os dados da plataforma de cobrança. Se o valor pago ficar vazio, a planilha usa o valor atualizado."
A2: Aluno | B2: Responsável | C2: Mês ref. | D2: Vencimento | E2: Valor do boleto | F2: Nº do boleto (plataforma) | G2: Data do pagamento | H2: Valor pago | I2: Cancelado? | J2: Status | K2: Dias de atraso | L2: Valor atualizado (multa+juros) | M2: Mês pag.
A3: {=IF(OR(Alunos!$A$2="",1<IF(Alunos!$M$2="",1,MATCH(Alunos!$M$2,{"Jan";"Fev";"Mar";"Abr";"Mai";"Jun";"Jul";"Ago";"Set";"Out";"Nov";"Dez"},0)),1>IF(Alunos!$N$2="",12,MATCH(Alunos!$N$2,{"Jan";"Fev";"Mar";"Abr";"Mai";"Jun";"Jul";"Ago";"Set";"Out";"Nov";"Dez"},0))),"",Alunos!$A$2)} | B3: =IF(OR(A3="",Alunos!$C$2=""),"",Alunos!$C$2) | C3: =IF(A3="","","Jan") | D3: =IF(OR(A3="",Config!$B$5=""),"",DATE(Config!$B$4,1,Config!$B$5)) | E3: =IF(OR(A3="",Alunos!$K$2=""),"",Alunos!$K$2) | F3: BOL-202601-001 | G3: 46027 | J3: =IF(OR(A3="",E3=""),"",IF(I3="Sim","Cancelado",IF(G3<>"","Pago",IF(D3="","A vencer",IF(TODAY()>D3,"Vencido","A vencer"))))) | K3: =IF(J3="Pago",IF(D3="",0,MAX(0,G3-D3)),IF(J3="Vencido",TODAY()-D3,"")) | L3: =IF(OR(J3="",J3="Cancelado"),"",IF(N(K3)>0,E3*(1+N(Config!$B$6))+E3*N(Config!$B$7)/30*K3,E3)) | M3: =IF(G3="","",IF(YEAR(G3)=Config!$B$4,MONTH(G3),"")) | N3: =IF(J3="Pago",IF(H3<>"",H3,L3),"") | O3: =IF(J3="Vencido",ROW(),"")
A4: {=IF(OR(Alunos!$A$2="",2<IF(Alunos!$M$2="",1,MATCH(Alunos!$M$2,{"Jan";"Fev";"Mar";"Abr";"Mai";"Jun";"Jul";"Ago";"Set";"Out";"Nov";"Dez"},0)),2>IF(Alunos!$N$2="",12,MATCH(Alunos!$N$2,{"Jan";"Fev";"Mar";"Abr";"Mai";"Jun";"Jul";"Ago";"Set";"Out";"Nov";"Dez"},0))),"",Alunos!$A$2)} | B4: =IF(OR(A4="",Alunos!$C$2=""),"",Alunos!$C$2) | C4: =IF(A4="","","Fev") | D4: =IF(OR(A4="",Config!$B$5=""),"",DATE(Config!$B$4,2,Config!$B$5)) | E4: =IF(OR(A4="",Alunos!$K$2=""),"",Alunos!$K$2) | F4: BOL-202602-001 | G4: 46063 | J4: =IF(OR(A4="",E4=""),"",IF(I4="Sim","Cancelado",IF(G4<>"","Pago",IF(D4="","A vencer",IF(TODAY()>D4,"Vencido","A vencer"))))) | K4: =IF(J4="Pago",IF(D4="",0,MAX(0,G4-D4)),IF(J4="Vencido",TODAY()-D4,"")) | L4: =IF(OR(J4="",J4="Cancelado"),"",IF(N(K4)>0,E4*(1+N(Config!$B$6))+E4*N(Config!$B$7)/30*K4,E4)) | M4: =IF(G4="","",IF(YEAR(G4)=Config!$B$4,MONTH(G4),"")) | N4: =IF(J4="Pago",IF(H4<>"",H4,L4),"") | O4: =IF(J4="Vencido",ROW(),"")
A5: {=IF(OR(Alunos!$A$2="",3<IF(Alunos!$M$2="",1,MATCH(Alunos!$M$2,{"Jan";"Fev";"Mar";"Abr";"Mai";"Jun";"Jul";"Ago";"Set";"Out";"Nov";"Dez"},0)),3>IF(Alunos!$N$2="",12,MATCH(Alunos!$N$2,{"Jan";"Fev";"Mar";"Abr";"Mai";"Jun";"Jul";"Ago";"Set";"Out";"Nov";"Dez"},0))),"",Alunos!$A$2)} | B5: =IF(OR(A5="",Alunos!$C$2=""),"",Alunos!$C$2) | C5: =IF(A5="","","Mar") | D5: =IF(OR(A5="",Config!$B$5=""),"",DATE(Config!$B$4,3,Config!$B$5)) | E5: =IF(OR(A5="",Alunos!$K$2=""),"",Alunos!$K$2) | F5: BOL-202603-001 | G5: 46098 | J5: =IF(OR(A5="",E5=""),"",IF(I5="Sim","Cancelado",IF(G5<>"","Pago",IF(D5="","A vencer",IF(TODAY()>D5,"Vencido","A vencer"))))) | K5: =IF(J5="Pago",IF(D5="",0,MAX(0,G5-D5)),IF(J5="Vencido",TODAY()-D5,"")) | L5: =IF(OR(J5="",J5="Cancelado"),"",IF(N(K5)>0,E5*(1+N(Config!$B$6))+E5*N(Config!$B$7)/30*K5,E5)) | M5: =IF(G5="","",IF(YEAR(G5)=Config!$B$4,MONTH(G5),"")) | N5: =IF(J5="Pago",IF(H5<>"",H5,L5),"") | O5: =IF(J5="Vencido",ROW(),"")
A6: {=IF(OR(Alunos!$A$2="",4<IF(Alunos!$M$2="",1,MATCH(Alunos!$M$2,{"Jan";"Fev";"Mar";"Abr";"Mai";"Jun";"Jul";"Ago";"Set";"Out";"Nov";"Dez"},0)),4>IF(Alunos!$N$2="",12,MATCH(Alunos!$N$2,{"Jan";"Fev";"Mar";"Abr";"Mai";"Jun";"Jul";"Ago";"Set";"Out";"Nov";"Dez"},0))),"",Alunos!$A$2)} | B6: =IF(OR(A6="",Alunos!$C$2=""),"",Alunos!$C$2) | C6: =IF(A6="","","Abr") | D6: =IF(OR(A6="",Config!$B$5=""),"",DATE(Config!$B$4,4,Config!$B$5)) | E6: =IF(OR(A6="",Alunos!$K$2=""),"",Alunos!$K$2) | F6: BOL-202604-001 | G6: 46117 | J6: =IF(OR(A6="",E6=""),"",IF(I6="Sim","Cancelado",IF(G6<>"","Pago",IF(D6="","A vencer",IF(TODAY()>D6,"Vencido","A vencer"))))) | K6: =IF(J6="Pago",IF(D6="",0,MAX(0,G6-D6)),IF(J6="Vencido",TODAY()-D6,"")) | L6: =IF(OR(J6="",J6="Cancelado"),"",IF(N(K6)>0,E6*(1+N(Config!$B$6))+E6*N(Config!$B$7)/30*K6,E6)) | M6: =IF(G6="","",IF(YEAR(G6)=Config!$B$4,MONTH(G6),"")) | N6: =IF(J6="Pago",IF(H6<>"",H6,L6),"") | O6: =IF(J6="Vencido",ROW(),"")
A7: {=IF(OR(Alunos!$A$2="",5<IF(Alunos!$M$2="",1,MATCH(Alunos!$M$2,{"Jan";"Fev";"Mar";"Abr";"Mai";"Jun";"Jul";"Ago";"Set";"Out";"Nov";"Dez"},0)),5>IF(Alunos!$N$2="",12,MATCH(Alunos!$N$2,{"Jan";"Fev";"Mar";"Abr";"Mai";"Jun";"Jul";"Ago";"Set";"Out";"Nov";"Dez"},0))),"",Alunos!$A$2)} | B7: =IF(OR(A7="",Alunos!$C$2=""),"",Alunos!$C$2) | C7: =IF(A7="","","Mai") | D7: =IF(OR(A7="",Config!$B$5=""),"",DATE(Config!$B$4,5,Config!$B$5)) | E7: =IF(OR(A7="",Alunos!$K$2=""),"",Alunos!$K$2) | F7: BOL-202605-001 | G7: 46159 | J7: =IF(OR(A7="",E7=""),"",IF(I7="Sim","Cancelado",IF(G7<>"","Pago",IF(D7="","A vencer",IF(TODAY()>D7,"Vencido","A vencer"))))) | K7: =IF(J7="Pago",IF(D7="",0,MAX(0,G7-D7)),IF(J7="Vencido",TODAY()-D7,"")) | L7: =IF(OR(J7="",J7="Cancelado"),"",IF(N(K7)>0,E7*(1+N(Config!$B$6))+E7*N(Config!$B$7)/30*K7,E7)) | M7: =IF(G7="","",IF(YEAR(G7)=Config!$B$4,MONTH(G7),"")) | N7: =IF(J7="Pago",IF(H7<>"",H7,L7),"") | O7: =IF(J7="Vencido",ROW(),"")
A8: {=IF(OR(Alunos!$A$2="",6<IF(Alunos!$M$2="",1,MATCH(Alunos!$M$2,{"Jan";"Fev";"Mar";"Abr";"Mai";"Jun";"Jul";"Ago";"Set";"Out";"Nov";"Dez"},0)),6>IF(Alunos!$N$2="",12,MATCH(Alunos!$N$2,{"Jan";"Fev";"Mar";"Abr";"Mai";"Jun";"Jul";"Ago";"Set";"Out";"Nov";"Dez"},0))),"",Alunos!$A$2)} | B8: =IF(OR(A8="",Alunos!$C$2=""),"",Alunos!$C$2) | C8: =IF(A8="","","Jun") | D8: =IF(OR(A8="",Config!$B$5=""),"",DATE(Config!$B$4,6,Config!$B$5)) | E8: =IF(OR(A8="",Alunos!$K$2=""),"",Alunos!$K$2) | F8: BOL-202606-001 | G8: 46186 | J8: =IF(OR(A8="",E8=""),"",IF(I8="Sim","Cancelado",IF(G8<>"","Pago",IF(D8="","A vencer",IF(TODAY()>D8,"Vencido","A vencer"))))) | K8: =IF(J8="Pago",IF(D8="",0,MAX(0,G8-D8)),IF(J8="Vencido",TODAY()-D8,"")) | L8: =IF(OR(J8="",J8="Cancelado"),"",IF(N(K8)>0,E8*(1+N(Config!$B$6))+E8*N(Config!$B$7)/30*K8,E8)) | M8: =IF(G8="","",IF(YEAR(G8)=Config!$B$4,MONTH(G8),"")) | N8: =IF(J8="Pago",IF(H8<>"",H8,L8),"") | O8: =IF(J8="Vencido",ROW(),"")
A9: {=IF(OR(Alunos!$A$2="",7<IF(Alunos!$M$2="",1,MATCH(Alunos!$M$2,{"Jan";"Fev";"Mar";"Abr";"Mai";"Jun";"Jul";"Ago";"Set";"Out";"Nov";"Dez"},0)),7>IF(Alunos!$N$2="",12,MATCH(Alunos!$N$2,{"Jan";"Fev";"Mar";"Abr";"Mai";"Jun";"Jul";"Ago";"Set";"Out";"Nov";"Dez"},0))),"",Alunos!$A$2)} | B9: =IF(OR(A9="",Alunos!$C$2=""),"",Alunos!$C$2) | C9: =IF(A9="","","Jul") | D9: =IF(OR(A9="",Config!$B$5=""),"",DATE(Config!$B$4,7,Config!$B$5)) | E9: =IF(OR(A9="",Alunos!$K$2=""),"",Alunos!$K$2) | F9: BOL-202607-001 | G9: 46211 | J9: =IF(OR(A9="",E9=""),"",IF(I9="Sim","Cancelado",IF(G9<>"","Pago",IF(D9="","A vencer",IF(TODAY()>D9,"Vencido","A vencer"))))) | K9: =IF(J9="Pago",IF(D9="",0,MAX(0,G9-D9)),IF(J9="Vencido",TODAY()-D9,"")) | L9: =IF(OR(J9="",J9="Cancelado"),"",IF(N(K9)>0,E9*(1+N(Config!$B$6))+E9*N(Config!$B$7)/30*K9,E9)) | M9: =IF(G9="","",IF(YEAR(G9)=Config!$B$4,MONTH(G9),"")) | N9: =IF(J9="Pago",IF(H9<>"",H9,L9),"") | O9: =IF(J9="Vencido",ROW(),"")
A10: {=IF(OR(Alunos!$A$2="",8<IF(Alunos!$M$2="",1,MATCH(Alunos!$M$2,{"Jan";"Fev";"Mar";"Abr";"Mai";"Jun";"Jul";"Ago";"Set";"Out";"Nov";"Dez"},0)),8>IF(Alunos!$N$2="",12,MATCH(Alunos!$N$2,{"Jan";"Fev";"Mar";"Abr";"Mai";"Jun";"Jul";"Ago";"Set";"Out";"Nov";"Dez"},0))),"",Alunos!$A$2)} | B10: =IF(OR(A10="",Alunos!$C$2=""),"",Alunos!$C$2) | C10: =IF(A10="","","Ago") | D10: =IF(OR(A10="",Config!$B$5=""),"",DATE(Config!$B$4,8,Config!$B$5)) | E10: =IF(OR(A10="",Alunos!$K$2=""),"",Alunos!$K$2) | F10: BOL-202608-001 | G10: 46259 | J10: =IF(OR(A10="",E10=""),"",IF(I10="Sim","Cancelado",IF(G10<>"","Pago",IF(D10="","A vencer",IF(TODAY()>D10,"Vencido","A vencer"))))) | K10: =IF(J10="Pago",IF(D10="",0,MAX(0,G10-D10)),IF(J10="Vencido",TODAY()-D10,"")) | L10: =IF(OR(J10="",J10="Cancelado"),"",IF(N(K10)>0,E10*(1+N(Config!$B$6))+E10*N(Config!$B$7)/30*K10,E10)) | M10: =IF(G10="","",IF(YEAR(G10)=Config!$B$4,MONTH(G10),"")) | N10: =IF(J10="Pago",IF(H10<>"",H10,L10),"") | O10: =IF(J10="Vencido",ROW(),"")
A11: {=IF(OR(Alunos!$A$2="",9<IF(Alunos!$M$2="",1,MATCH(Alunos!$M$2,{"Jan";"Fev";"Mar";"Abr";"Mai";"Jun";"Jul";"Ago";"Set";"Out";"Nov";"Dez"},0)),9>IF(Alunos!$N$2="",12,MATCH(Alunos!$N$2,{"Jan";"Fev";"Mar";"Abr";"Mai";"Jun";"Jul";"Ago";"Set";"Out";"Nov";"Dez"},0))),"",Alunos!$A$2)} | B11: =IF(OR(A11="",Alunos!$C$2=""),"",Alunos!$C$2) | C11: =IF(A11="","","Set") | D11: =IF(OR(A11="",Config!$B$5=""),"",DATE(Config!$B$4,9,Config!$B$5)) | E11: =IF(OR(A11="",Alunos!$K$2=""),"",Alunos!$K$2) | F11: BOL-202609-001 | G11: 46274 | J11: =IF(OR(A11="",E11=""),"",IF(I11="Sim","Cancelado",IF(G11<>"","Pago",IF(D11="","A vencer",IF(TODAY()>D11,"Vencido","A vencer"))))) | K11: =IF(J11="Pago",IF(D11="",0,MAX(0,G11-D11)),IF(J11="Vencido",TODAY()-D11,"")) | L11: =IF(OR(J11="",J11="Cancelado"),"",IF(N(K11)>0,E11*(1+N(Config!$B$6))+E11*N(Config!$B$7)/30*K11,E11)) | M11: =IF(G11="","",IF(YEAR(G11)=Config!$B$4,MONTH(G11),"")) | N11: =IF(J11="Pago",IF(H11<>"",H11,L11),"") | O11: =IF(J11="Vencido",ROW(),"")
A12: {=IF(OR(Alunos!$A$2="",10<IF(Alunos!$M$2="",1,MATCH(Alunos!$M$2,{"Jan";"Fev";"Mar";"Abr";"Mai";"Jun";"Jul";"Ago";"Set";"Out";"Nov";"Dez"},0)),10>IF(Alunos!$N$2="",12,MATCH(Alunos!$N$2,{"Jan";"Fev";"Mar";"Abr";"Mai";"Jun";"Jul";"Ago";"Set";"Out";"Nov";"Dez"},0))),"",Alunos!$A$2)} | B12: =IF(OR(A12="",Alunos!$C$2=""),"",Alunos!$C$2) | C12: =IF(A12="","","Out") | D12: =IF(OR(A12="",Config!$B$5=""),"",DATE(Config!$B$4,10,Config!$B$5)) | E12: =IF(OR(A12="",Alunos!$K$2=""),"",Alunos!$K$2) | F12: BOL-202610-001 | G12: 46299 | J12: =IF(OR(A12="",E12=""),"",IF(I12="Sim","Cancelado",IF(G12<>"","Pago",IF(D12="","A vencer",IF(TODAY()>D12,"Vencido","A vencer"))))) | K12: =IF(J12="Pago",IF(D12="",0,MAX(0,G12-D12)),IF(J12="Vencido",TODAY()-D12,"")) | L12: =IF(OR(J12="",J12="Cancelado"),"",IF(N(K12)>0,E12*(1+N(Config!$B$6))+E12*N(Config!$B$7)/30*K12,E12)) | M12: =IF(G12="","",IF(YEAR(G12)=Config!$B$4,MONTH(G12),"")) | N12: =IF(J12="Pago",IF(H12<>"",H12,L12),"") | O12: =IF(J12="Vencido",ROW(),"")
A13: {=IF(OR(Alunos!$A$2="",11<IF(Alunos!$M$2="",1,MATCH(Alunos!$M$2,{"Jan";"Fev";"Mar";"Abr";"Mai";"Jun";"Jul";"Ago";"Set";"Out";"Nov";"Dez"},0)),11>IF(Alunos!$N$2="",12,MATCH(Alunos!$N$2,{"Jan";"Fev";"Mar";"Abr";"Mai";"Jun";"Jul";"Ago";"Set";"Out";"Nov";"Dez"},0))),"",Alunos!$A$2)} | B13: =IF(OR(A13="",Alunos!$C$2=""),"",Alunos!$C$2) | C13: =IF(A13="","","Nov") | D13: =IF(OR(A13="",Config!$B$5=""),"",DATE(Config!$B$4,11,Config!$B$5)) | E13: =IF(OR(A13="",Alunos!$K$2=""),"",Alunos!$K$2) | J13: =IF(OR(A13="",E13=""),"",IF(I13="Sim","Cancelado",IF(G13<>"","Pago",IF(D13="","A vencer",IF(TODAY()>D13,"Vencido","A vencer"))))) | K13: =IF(J13="Pago",IF(D13="",0,MAX(0,G13-D13)),IF(J13="Vencido",TODAY()-D13,"")) | L13: =IF(OR(J13="",J13="Cancelado"),"",IF(N(K13)>0,E13*(1+N(Config!$B$6))+E13*N(Config!$B$7)/30*K13,E13)) | M13: =IF(G13="","",IF(YEAR(G13)=Config!$B$4,MONTH(G13),"")) | N13: =IF(J13="Pago",IF(H13<>"",H13,L13),"") | O13: =IF(J13="Vencido",ROW(),"")
A14: {=IF(OR(Alunos!$A$2="",12<IF(Alunos!$M$2="",1,MATCH(Alunos!$M$2,{"Jan";"Fev";"Mar";"Abr";"Mai";"Jun";"Jul";"Ago";"Set";"Out";"Nov";"Dez"},0)),12>IF(Alunos!$N$2="",12,MATCH(Alunos!$N$2,{"Jan";"Fev";"Mar";"Abr";"Mai";"Jun";"Jul";"Ago";"Set";"Out";"Nov";"Dez"},0))),"",Alunos!$A$2)} | B14: =IF(OR(A14="",Alunos!$C$2=""),"",Alunos!$C$2) | C14: =IF(A14="","","Dez") | D14: =IF(OR(A14="",Config!$B$5=""),"",DATE(Config!$B$4,12,Config!$B$5)) | E14: =IF(OR(A14="",Alunos!$K$2=""),"",Alunos!$K$2) | J14: =IF(OR(A14="",E14=""),"",IF(I14="Sim","Cancelado",IF(G14<>"","Pago",IF(D14="","A vencer",IF(TODAY()>D14,"Vencido","A vencer"))))) | K14: =IF(J14="Pago",IF(D14="",0,MAX(0,G14-D14)),IF(J14="Vencido",TODAY()-D14,"")) | L14: =IF(OR(J14="",J14="Cancelado"),"",IF(N(K14)>0,E14*(1+N(Config!$B$6))+E14*N(Config!$B$7)/30*K14,E14)) | M14: =IF(G14="","",IF(YEAR(G14)=Config!$B$4,MONTH(G14),"")) | N14: =IF(J14="Pago",IF(H14<>"",H14,L14),"") | O14: =IF(J14="Vencido",ROW(),"")
A15: {=IF(OR(Alunos!$A$3="",1<IF(Alunos!$M$3="",1,MATCH(Alunos!$M$3,{"Jan";"Fev";"Mar";"Abr";"Mai";"Jun";"Jul";"Ago";"Set";"Out";"Nov";"Dez"},0)),1>IF(Alunos!$N$3="",12,MATCH(Alunos!$N$3,{"Jan";"Fev";"Mar";"Abr";"Mai";"Jun";"Jul";"Ago";"Set";"Out";"Nov";"Dez"},0))),"",Alunos!$A$3)} | B15: =IF(OR(A15="",Alunos!$C$3=""),"",Alunos!$C$3) | C15: =IF(A15="","","Jan") | D15: =IF(OR(A15="",Config!$B$5=""),"",DATE(Config!$B$4,1,Config!$B$5)) | E15: =IF(OR(A15="",Alunos!$K$3=""),"",Alunos!$K$3) | F15: BOL-202601-002 | G15: 46027 | J15: =IF(OR(A15="",E15=""),"",IF(I15="Sim","Cancelado",IF(G15<>"","Pago",IF(D15="","A vencer",IF(TODAY()>D15,"Vencido","A vencer"))))) | K15: =IF(J15="Pago",IF(D15="",0,MAX(0,G15-D15)),IF(J15="Vencido",TODAY()-D15,"")) | L15: =IF(OR(J15="",J15="Cancelado"),"",IF(N(K15)>0,E15*(1+N(Config!$B$6))+E15*N(Config!$B$7)/30*K15,E15)) | M15: =IF(G15="","",IF(YEAR(G15)=Config!$B$4,MONTH(G15),"")) | N15: =IF(J15="Pago",IF(H15<>"",H15,L15),"") | O15: =IF(J15="Vencido",ROW(),"")
A16: {=IF(OR(Alunos!$A$3="",2<IF(Alunos!$M$3="",1,MATCH(Alunos!$M$3,{"Jan";"Fev";"Mar";"Abr";"Mai";"Jun";"Jul";"Ago";"Set";"Out";"Nov";"Dez"},0)),2>IF(Alunos!$N$3="",12,MATCH(Alunos!$N$3,{"Jan";"Fev";"Mar";"Abr";"Mai";"Jun";"Jul";"Ago";"Set";"Out";"Nov";"Dez"},0))),"",Alunos!$A$3)} | B16: =IF(OR(A16="",Alunos!$C$3=""),"",Alunos!$C$3) | C16: =IF(A16="","","Fev") | D16: =IF(OR(A16="",Config!$B$5=""),"",DATE(Config!$B$4,2,Config!$B$5)) | E16: =IF(OR(A16="",Alunos!$K$3=""),"",Alunos!$K$3) | F16: BOL-202602-002 | G16: 46057 | J16: =IF(OR(A16="",E16=""),"",IF(I16="Sim","Cancelado",IF(G16<>"","Pago",IF(D16="","A vencer",IF(TODAY()>D16,"Vencido","A vencer"))))) | K16: =IF(J16="Pago",IF(D16="",0,MAX(0,G16-D16)),IF(J16="Vencido",TODAY()-D16,"")) | L16: =IF(OR(J16="",J16="Cancelado"),"",IF(N(K16)>0,E16*(1+N(Config!$B$6))+E16*N(Config!$B$7)/30*K16,E16)) | M16: =IF(G16="","",IF(YEAR(G16)=Config!$B$4,MONTH(G16),"")) | N16: =IF(J16="Pago",IF(H16<>"",H16,L16),"") | O16: =IF(J16="Vencido",ROW(),"")
A17: {=IF(OR(Alunos!$A$3="",3<IF(Alunos!$M$3="",1,MATCH(Alunos!$M$3,{"Jan";"Fev";"Mar";"Abr";"Mai";"Jun";"Jul";"Ago";"Set";"Out";"Nov";"Dez"},0)),3>IF(Alunos!$N$3="",12,MATCH(Alunos!$N$3,{"Jan";"Fev";"Mar";"Abr";"Mai";"Jun";"Jul";"Ago";"Set";"Out";"Nov";"Dez"},0))),"",Alunos!$A$3)} | B17: =IF(OR(A17="",Alunos!$C$3=""),"",Alunos!$C$3) | C17: =IF(A17="","","Mar") | D17: =IF(OR(A17="",Config!$B$5=""),"",DATE(Config!$B$4,3,Config!$B$5)) | E17: =IF(OR(A17="",Alunos!$K$3=""),"",Alunos!$K$3) | F17: BOL-202603-002 | G17: 46098 | J17: =IF(OR(A17="",E17=""),"",IF(I17="Sim","Cancelado",IF(G17<>"","Pago",IF(D17="","A vencer",IF(TODAY()>D17,"Vencido","A vencer"))))) | K17: =IF(J17="Pago",IF(D17="",0,MAX(0,G17-D17)),IF(J17="Vencido",TODAY()-D17,"")) | L17: =IF(OR(J17="",J17="Cancelado"),"",IF(N(K17)>0,E17*(1+N(Config!$B$6))+E17*N(Config!$B$7)/30*K17,E17)) | M17: =IF(G17="","",IF(YEAR(G17)=Config!$B$4,MONTH(G17),"")) | N17: =IF(J17="Pago",IF(H17<>"",H17,L17),"") | O17: =IF(J17="Vencido",ROW(),"")
A18: {=IF(OR(Alunos!$A$3="",4<IF(Alunos!$M$3="",1,MATCH(Alunos!$M$3,{"Jan";"Fev";"Mar";"Abr";"Mai";"Jun";"Jul";"Ago";"Set";"Out";"Nov";"Dez"},0)),4>IF(Alunos!$N$3="",12,MATCH(Alunos!$N$3,{"Jan";"Fev";"Mar";"Abr";"Mai";"Jun";"Jul";"Ago";"Set";"Out";"Nov";"Dez"},0))),"",Alunos!$A$3)} | B18: =IF(OR(A18="",Alunos!$C$3=""),"",Alunos!$C$3) | C18: =IF(A18="","","Abr") | D18: =IF(OR(A18="",Config!$B$5=""),"",DATE(Config!$B$4,4,Config!$B$5)) | E18: =IF(OR(A18="",Alunos!$K$3=""),"",Alunos!$K$3) | F18: BOL-202604-002 | G18: 46129 | J18: =IF(OR(A18="",E18=""),"",IF(I18="Sim","Cancelado",IF(G18<>"","Pago",IF(D18="","A vencer",IF(TODAY()>D18,"Vencido","A vencer"))))) | K18: =IF(J18="Pago",IF(D18="",0,MAX(0,G18-D18)),IF(J18="Vencido",TODAY()-D18,"")) | L18: =IF(OR(J18="",J18="Cancelado"),"",IF(N(K18)>0,E18*(1+N(Config!$B$6))+E18*N(Config!$B$7)/30*K18,E18)) | M18: =IF(G18="","",IF(YEAR(G18)=Config!$B$4,MONTH(G18),"")) | N18: =IF(J18="Pago",IF(H18<>"",H18,L18),"") | O18: =IF(J18="Vencido",ROW(),"")
A19: {=IF(OR(Alunos!$A$3="",5<IF(Alunos!$M$3="",1,MATCH(Alunos!$M$3,{"Jan";"Fev";"Mar";"Abr";"Mai";"Jun";"Jul";"Ago";"Set";"Out";"Nov";"Dez"},0)),5>IF(Alunos!$N$3="",12,MATCH(Alunos!$N$3,{"Jan";"Fev";"Mar";"Abr";"Mai";"Jun";"Jul";"Ago";"Set";"Out";"Nov";"Dez"},0))),"",Alunos!$A$3)} | B19: =IF(OR(A19="",Alunos!$C$3=""),"",Alunos!$C$3) | C19: =IF(A19="","","Mai") | D19: =IF(OR(A19="",Config!$B$5=""),"",DATE(Config!$B$4,5,Config!$B$5)) | E19: =IF(OR(A19="",Alunos!$K$3=""),"",Alunos!$K$3) | F19: BOL-202605-002 | G19: 46151 | J19: =IF(OR(A19="",E19=""),"",IF(I19="Sim","Cancelado",IF(G19<>"","Pago",IF(D19="","A vencer",IF(TODAY()>D19,"Vencido","A vencer"))))) | K19: =IF(J19="Pago",IF(D19="",0,MAX(0,G19-D19)),IF(J19="Vencido",TODAY()-D19,"")) | L19: =IF(OR(J19="",J19="Cancelado"),"",IF(N(K19)>0,E19*(1+N(Config!$B$6))+E19*N(Config!$B$7)/30*K19,E19)) | M19: =IF(G19="","",IF(YEAR(G19)=Config!$B$4,MONTH(G19),"")) | N19: =IF(J19="Pago",IF(H19<>"",H19,L19),"") | O19: =IF(J19="Vencido",ROW(),"")
A20: {=IF(OR(Alunos!$A$3="",6<IF(Alunos!$M$3="",1,MATCH(Alunos!$M$3,{"Jan";"Fev";"Mar";"Abr";"Mai";"Jun";"Jul";"Ago";"Set";"Out";"Nov";"Dez"},0)),6>IF(Alunos!$N$3="",12,MATCH(Alunos!$N$3,{"Jan";"Fev";"Mar";"Abr";"Mai";"Jun";"Jul";"Ago";"Set";"Out";"Nov";"Dez"},0))),"",Alunos!$A$3)} | B20: =IF(OR(A20="",Alunos!$C$3=""),"",Alunos!$C$3) | C20: =IF(A20="","","Jun") | D20: =IF(OR(A20="",Config!$B$5=""),"",DATE(Config!$B$4,6,Config!$B$5)) | E20: =IF(OR(A20="",Alunos!$K$3=""),"",Alunos!$K$3) | F20: BOL-202606-002 | G20: 46190 | J20: =IF(OR(A20="",E20=""),"",IF(I20="Sim","Cancelado",IF(G20<>"","Pago",IF(D20="","A vencer",IF(TODAY()>D20,"Vencido","A vencer"))))) | K20: =IF(J20="Pago",IF(D20="",0,MAX(0,G20-D20)),IF(J20="Vencido",TODAY()-D20,"")) | L20: =IF(OR(J20="",J20="Cancelado"),"",IF(N(K20)>0,E20*(1+N(Config!$B$6))+E20*N(Config!$B$7)/30*K20,E20)) | M20: =IF(G20="","",IF(YEAR(G20)=Config!$B$4,MONTH(G20),"")) | N20: =IF(J20="Pago",IF(H20<>"",H20,L20),"") | O20: =IF(J20="Vencido",ROW(),"")
A21: {=IF(OR(Alunos!$A$3="",7<IF(Alunos!$M$3="",1,MATCH(Alunos!$M$3,{"Jan";"Fev";"Mar";"Abr";"Mai";"Jun";"Jul";"Ago";"Set";"Out";"Nov";"Dez"},0)),7>IF(Alunos!$N$3="",12,MATCH(Alunos!$N$3,{"Jan";"Fev";"Mar";"Abr";"Mai";"Jun";"Jul";"Ago";"Set";"Out";"Nov";"Dez"},0))),"",Alunos!$A$3)} | B21: =IF(OR(A21="",Alunos!$C$3=""),"",Alunos!$C$3) | C21: =IF(A21="","","Jul") | D21: =IF(OR(A21="",Config!$B$5=""),"",DATE(Config!$B$4,7,Config!$B$5)) | E21: =IF(OR(A21="",Alunos!$K$3=""),"",Alunos!$K$3) | F21: BOL-202607-002 | G21: 46216 | J21: =IF(OR(A21="",E21=""),"",IF(I21="Sim","Cancelado",IF(G21<>"","Pago",IF(D21="","A vencer",IF(TODAY()>D21,"Vencido","A vencer"))))) | K21: =IF(J21="Pago",IF(D21="",0,MAX(0,G21-D21)),IF(J21="Vencido",TODAY()-D21,"")) | L21: =IF(OR(J21="",J21="Cancelado"),"",IF(N(K21)>0,E21*(1+N(Config!$B$6))+E21*N(Config!$B$7)/30*K21,E21)) | M21: =IF(G21="","",IF(YEAR(G21)=Config!$B$4,MONTH(G21),"")) | N21: =IF(J21="Pago",IF(H21<>"",H21,L21),"") | O21: =IF(J21="Vencido",ROW(),"")
A22: {=IF(OR(Alunos!$A$3="",8<IF(Alunos!$M$3="",1,MATCH(Alunos!$M$3,{"Jan";"Fev";"Mar";"Abr";"Mai";"Jun";"Jul";"Ago";"Set";"Out";"Nov";"Dez"},0)),8>IF(Alunos!$N$3="",12,MATCH(Alunos!$N$3,{"Jan";"Fev";"Mar";"Abr";"Mai";"Jun";"Jul";"Ago";"Set";"Out";"Nov";"Dez"},0))),"",Alunos!$A$3)} | B22: =IF(OR(A22="",Alunos!$C$3=""),"",Alunos!$C$3) | C22: =IF(A22="","","Ago") | D22: =IF(OR(A22="",Config!$B$5=""),"",DATE(Config!$B$4,8,Config!$B$5)) | E22: =IF(OR(A22="",Alunos!$K$3=""),"",Alunos!$K$3) | F22: BOL-202608-002 | G22: 46240 | J22: =IF(OR(A22="",E22=""),"",IF(I22="Sim","Cancelado",IF(G22<>"","Pago",IF(D22="","A vencer",IF(TODAY()>D22,"Vencido","A vencer"))))) | K22: =IF(J22="Pago",IF(D22="",0,MAX(0,G22-D22)),IF(J22="Vencido",TODAY()-D22,"")) | L22: =IF(OR(J22="",J22="Cancelado"),"",IF(N(K22)>0,E22*(1+N(Config!$B$6))+E22*N(Config!$B$7)/30*K22,E22)) | M22: =IF(G22="","",IF(YEAR(G22)=Config!$B$4,MONTH(G22),"")) | N22: =IF(J22="Pago",IF(H22<>"",H22,L22),"") | O22: =IF(J22="Vencido",ROW(),"")
A23: {=IF(OR(Alunos!$A$3="",9<IF(Alunos!$M$3="",1,MATCH(Alunos!$M$3,{"Jan";"Fev";"Mar";"Abr";"Mai";"Jun";"Jul";"Ago";"Set";"Out";"Nov";"Dez"},0)),9>IF(Alunos!$N$3="",12,MATCH(Alunos!$N$3,{"Jan";"Fev";"Mar";"Abr";"Mai";"Jun";"Jul";"Ago";"Set";"Out";"Nov";"Dez"},0))),"",Alunos!$A$3)} | B23: =IF(OR(A23="",Alunos!$C$3=""),"",Alunos!$C$3) | C23: =IF(A23="","","Set") | D23: =IF(OR(A23="",Config!$B$5=""),"",DATE(Config!$B$4,9,Config!$B$5)) | E23: =IF(OR(A23="",Alunos!$K$3=""),"",Alunos!$K$3) | F23: BOL-202609-002 | G23: 46270 | J23: =IF(OR(A23="",E23=""),"",IF(I23="Sim","Cancelado",IF(G23<>"","Pago",IF(D23="","A vencer",IF(TODAY()>D23,"Vencido","A vencer"))))) | K23: =IF(J23="Pago",IF(D23="",0,MAX(0,G23-D23)),IF(J23="Vencido",TODAY()-D23,"")) | L23: =IF(OR(J23="",J23="Cancelado"),"",IF(N(K23)>0,E23*(1+N(Config!$B$6))+E23*N(Config!$B$7)/30*K23,E23)) | M23: =IF(G23="","",IF(YEAR(G23)=Config!$B$4,MONTH(G23),"")) | N23: =IF(J23="Pago",IF(H23<>"",H23,L23),"") | O23: =IF(J23="Vencido",ROW(),"")
A24: {=IF(OR(Alunos!$A$3="",10<IF(Alunos!$M$3="",1,MATCH(Alunos!$M$3,{"Jan";"Fev";"Mar";"Abr";"Mai";"Jun";"Jul";"Ago";"Set";"Out";"Nov";"Dez"},0)),10>IF(Alunos!$N$3="",12,MATCH(Alunos!$N$3,{"Jan";"Fev";"Mar";"Abr";"Mai";"Jun";"Jul";"Ago";"Set";"Out";"Nov";"Dez"},0))),"",Alunos!$A$3)} | B24: =IF(OR(A24="",Alunos!$C$3=""),"",Alunos!$C$3) | C24: =IF(A24="","","Out") | D24: =IF(OR(A24="",Config!$B$5=""),"",DATE(Config!$B$4,10,Config!$B$5)) | E24: =IF(OR(A24="",Alunos!$K$3=""),"",Alunos!$K$3) | F24: BOL-202610-002 | G24: 46305 | J24: =IF(OR(A24="",E24=""),"",IF(I24="Sim","Cancelado",IF(G24<>"","Pago",IF(D24="","A vencer",IF(TODAY()>D24,"Vencido","A vencer"))))) | K24: =IF(J24="Pago",IF(D24="",0,MAX(0,G24-D24)),IF(J24="Vencido",TODAY()-D24,"")) | L24: =IF(OR(J24="",J24="Cancelado"),"",IF(N(K24)>0,E24*(1+N(Config!$B$6))+E24*N(Config!$B$7)/30*K24,E24)) | M24: =IF(G24="","",IF(YEAR(G24)=Config!$B$4,MONTH(G24),"")) | N24: =IF(J24="Pago",IF(H24<>"",H24,L24),"") | O24: =IF(J24="Vencido",ROW(),"")
A25: {=IF(OR(Alunos!$A$3="",11<IF(Alunos!$M$3="",1,MATCH(Alunos!$M$3,{"Jan";"Fev";"Mar";"Abr";"Mai";"Jun";"Jul";"Ago";"Set";"Out";"Nov";"Dez"},0)),11>IF(Alunos!$N$3="",12,MATCH(Alunos!$N$3,{"Jan";"Fev";"Mar";"Abr";"Mai";"Jun";"Jul";"Ago";"Set";"Out";"Nov";"Dez"},0))),"",Alunos!$A$3)} | B25: =IF(OR(A25="",Alunos!$C$3=""),"",Alunos!$C$3) | C25: =IF(A25="","","Nov") | D25: =IF(OR(A25="",Config!$B$5=""),"",DATE(Config!$B$4,11,Config!$B$5)) | E25: =IF(OR(A25="",Alunos!$K$3=""),"",Alunos!$K$3) | J25: =IF(OR(A25="",E25=""),"",IF(I25="Sim","Cancelado",IF(G25<>"","Pago",IF(D25="","A vencer",IF(TODAY()>D25,"Vencido","A vencer"))))) | K25: =IF(J25="Pago",IF(D25="",0,MAX(0,G25-D25)),IF(J25="Vencido",TODAY()-D25,"")) | L25: =IF(OR(J25="",J25="Cancelado"),"",IF(N(K25)>0,E25*(1+N(Config!$B$6))+E25*N(Config!$B$7)/30*K25,E25)) | M25: =IF(G25="","",IF(YEAR(G25)=Config!$B$4,MONTH(G25),"")) | N25: =IF(J25="Pago",IF(H25<>"",H25,L25),"") | O25: =IF(J25="Vencido",ROW(),"")
A26: {=IF(OR(Alunos!$A$3="",12<IF(Alunos!$M$3="",1,MATCH(Alunos!$M$3,{"Jan";"Fev";"Mar";"Abr";"Mai";"Jun";"Jul";"Ago";"Set";"Out";"Nov";"Dez"},0)),12>IF(Alunos!$N$3="",12,MATCH(Alunos!$N$3,{"Jan";"Fev";"Mar";"Abr";"Mai";"Jun";"Jul";"Ago";"Set";"Out";"Nov";"Dez"},0))),"",Alunos!$A$3)} | B26: =IF(OR(A26="",Alunos!$C$3=""),"",Alunos!$C$3) | C26: =IF(A26="","","Dez") | D26: =IF(OR(A26="",Config!$B$5=""),"",DATE(Config!$B$4,12,Config!$B$5)) | E26: =IF(OR(A26="",Alunos!$K$3=""),"",Alunos!$K$3) | J26: =IF(OR(A26="",E26=""),"",IF(I26="Sim","Cancelado",IF(G26<>"","Pago",IF(D26="","A vencer",IF(TODAY()>D26,"Vencido","A vencer"))))) | K26: =IF(J26="Pago",IF(D26="",0,MAX(0,G26-D26)),IF(J26="Vencido",TODAY()-D26,"")) | L26: =IF(OR(J26="",J26="Cancelado"),"",IF(N(K26)>0,E26*(1+N(Config!$B$6))+E26*N(Config!$B$7)/30*K26,E26)) | M26: =IF(G26="","",IF(YEAR(G26)=Config!$B$4,MONTH(G26),"")) | N26: =IF(J26="Pago",IF(H26<>"",H26,L26),"") | O26: =IF(J26="Vencido",ROW(),"")
A27: {=IF(OR(Alunos!$A$4="",1<IF(Alunos!$M$4="",1,MATCH(Alunos!$M$4,{"Jan";"Fev";"Mar";"Abr";"Mai";"Jun";"Jul";"Ago";"Set";"Out";"Nov";"Dez"},0)),1>IF(Alunos!$N$4="",12,MATCH(Alunos!$N$4,{"Jan";"Fev";"Mar";"Abr";"Mai";"Jun";"Jul";"Ago";"Set";"Out";"Nov";"Dez"},0))),"",Alunos!$A$4)} | B27: =IF(OR(A27="",Alunos!$C$4=""),"",Alunos!$C$4) | C27: =IF(A27="","","Jan") | D27: =IF(OR(A27="",Config!$B$5=""),"",DATE(Config!$B$4,1,Config!$B$5)) | E27: =IF(OR(A27="",Alunos!$K$4=""),"",Alunos!$K$4) | F27: BOL-202601-003 | G27: 46039 | J27: =IF(OR(A27="",E27=""),"",IF(I27="Sim","Cancelado",IF(G27<>"","Pago",IF(D27="","A vencer",IF(TODAY()>D27,"Vencido","A vencer"))))) | K27: =IF(J27="Pago",IF(D27="",0,MAX(0,G27-D27)),IF(J27="Vencido",TODAY()-D27,"")) | L27: =IF(OR(J27="",J27="Cancelado"),"",IF(N(K27)>0,E27*(1+N(Config!$B$6))+E27*N(Config!$B$7)/30*K27,E27)) | M27: =IF(G27="","",IF(YEAR(G27)=Config!$B$4,MONTH(G27),"")) | N27: =IF(J27="Pago",IF(H27<>"",H27,L27),"") | O27: =IF(J27="Vencido",ROW(),"")
A28: {=IF(OR(Alunos!$A$4="",2<IF(Alunos!$M$4="",1,MATCH(Alunos!$M$4,{"Jan";"Fev";"Mar";"Abr";"Mai";"Jun";"Jul";"Ago";"Set";"Out";"Nov";"Dez"},0)),2>IF(Alunos!$N$4="",12,MATCH(Alunos!$N$4,{"Jan";"Fev";"Mar";"Abr";"Mai";"Jun";"Jul";"Ago";"Set";"Out";"Nov";"Dez"},0))),"",Alunos!$A$4)} | B28: =IF(OR(A28="",Alunos!$C$4=""),"",Alunos!$C$4) | C28: =IF(A28="","","Fev") | D28: =IF(OR(A28="",Config!$B$5=""),"",DATE(Config!$B$4,2,Config!$B$5)) | E28: =IF(OR(A28="",Alunos!$K$4=""),"",Alunos!$K$4) | F28: BOL-202602-003 | G28: 46062 | J28: =IF(OR(A28="",E28=""),"",IF(I28="Sim","Cancelado",IF(G28<>"","Pago",IF(D28="","A vencer",IF(TODAY()>D28,"Vencido","A vencer"))))) | K28: =IF(J28="Pago",IF(D28="",0,MAX(0,G28-D28)),IF(J28="Vencido",TODAY()-D28,"")) | L28: =IF(OR(J28="",J28="Cancelado"),"",IF(N(K28)>0,E28*(1+N(Config!$B$6))+E28*N(Config!$B$7)/30*K28,E28)) | M28: =IF(G28="","",IF(YEAR(G28)=Config!$B$4,MONTH(G28),"")) | N28: =IF(J28="Pago",IF(H28<>"",H28,L28),"") | O28: =IF(J28="Vencido",ROW(),"")
A29: {=IF(OR(Alunos!$A$4="",3<IF(Alunos!$M$4="",1,MATCH(Alunos!$M$4,{"Jan";"Fev";"Mar";"Abr";"Mai";"Jun";"Jul";"Ago";"Set";"Out";"Nov";"Dez"},0)),3>IF(Alunos!$N$4="",12,MATCH(Alunos!$N$4,{"Jan";"Fev";"Mar";"Abr";"Mai";"Jun";"Jul";"Ago";"Set";"Out";"Nov";"Dez"},0))),"",Alunos!$A$4)} | B29: =IF(OR(A29="",Alunos!$C$4=""),"",Alunos!$C$4) | C29: =IF(A29="","","Mar") | D29: =IF(OR(A29="",Config!$B$5=""),"",DATE(Config!$B$4,3,Config!$B$5)) | E29: =IF(OR(A29="",Alunos!$K$4=""),"",Alunos!$K$4) | F29: BOL-202603-003 | G29: 46094 | J29: =IF(OR(A29="",E29=""),"",IF(I29="Sim","Cancelado",IF(G29<>"","Pago",IF(D29="","A vencer",IF(TODAY()>D29,"Vencido","A vencer"))))) | K29: =IF(J29="Pago",IF(D29="",0,MAX(0,G29-D29)),IF(J29="Vencido",TODAY()-D29,"")) | L29: =IF(OR(J29="",J29="Cancelado"),"",IF(N(K29)>0,E29*(1+N(Config!$B$6))+E29*N(Config!$B$7)/30*K29,E29)) | M29: =IF(G29="","",IF(YEAR(G29)=Config!$B$4,MONTH(G29),"")) | N29: =IF(J29="Pago",IF(H29<>"",H29,L29),"") | O29: =IF(J29="Vencido",ROW(),"")
A30: {=IF(OR(Alunos!$A$4="",4<IF(Alunos!$M$4="",1,MATCH(Alunos!$M$4,{"Jan";"Fev";"Mar";"Abr";"Mai";"Jun";"Jul";"Ago";"Set";"Out";"Nov";"Dez"},0)),4>IF(Alunos!$N$4="",12,MATCH(Alunos!$N$4,{"Jan";"Fev";"Mar";"Abr";"Mai";"Jun";"Jul";"Ago";"Set";"Out";"Nov";"Dez"},0))),"",Alunos!$A$4)} | B30: =IF(OR(A30="",Alunos!$C$4=""),"",Alunos!$C$4) | C30: =IF(A30="","","Abr") | D30: =IF(OR(A30="",Config!$B$5=""),"",DATE(Config!$B$4,4,Config!$B$5)) | E30: =IF(OR(A30="",Alunos!$K$4=""),"",Alunos!$K$4) | F30: BOL-202604-003 | G30: 46137 | J30: =IF(OR(A30="",E30=""),"",IF(I30="Sim","Cancelado",IF(G30<>"","Pago",IF(D30="","A vencer",IF(TODAY()>D30,"Vencido","A vencer"))))) | K30: =IF(J30="Pago",IF(D30="",0,MAX(0,G30-D30)),IF(J30="Vencido",TODAY()-D30,"")) | L30: =IF(OR(J30="",J30="Cancelado"),"",IF(N(K30)>0,E30*(1+N(Config!$B$6))+E30*N(Config!$B$7)/30*K30,E30)) | M30: =IF(G30="","",IF(YEAR(G30)=Config!$B$4,MONTH(G30),"")) | N30: =IF(J30="Pago",IF(H30<>"",H30,L30),"") | O30: =IF(J30="Vencido",ROW(),"")
A31: {=IF(OR(Alunos!$A$4="",5<IF(Alunos!$M$4="",1,MATCH(Alunos!$M$4,{"Jan";"Fev";"Mar";"Abr";"Mai";"Jun";"Jul";"Ago";"Set";"Out";"Nov";"Dez"},0)),5>IF(Alunos!$N$4="",12,MATCH(Alunos!$N$4,{"Jan";"Fev";"Mar";"Abr";"Mai";"Jun";"Jul";"Ago";"Set";"Out";"Nov";"Dez"},0))),"",Alunos!$A$4)} | B31: =IF(OR(A31="",Alunos!$C$4=""),"",Alunos!$C$4) | C31: =IF(A31="","","Mai") | D31: =IF(OR(A31="",Config!$B$5=""),"",DATE(Config!$B$4,5,Config!$B$5)) | E31: =IF(OR(A31="",Alunos!$K$4=""),"",Alunos!$K$4) | F31: BOL-202605-003 | G31: 46147 | J31: =IF(OR(A31="",E31=""),"",IF(I31="Sim","Cancelado",IF(G31<>"","Pago",IF(D31="","A vencer",IF(TODAY()>D31,"Vencido","A vencer"))))) | K31: =IF(J31="Pago",IF(D31="",0,MAX(0,G31-D31)),IF(J31="Vencido",TODAY()-D31,"")) | L31: =IF(OR(J31="",J31="Cancelado"),"",IF(N(K31)>0,E31*(1+N(Config!$B$6))+E31*N(Config!$B$7)/30*K31,E31)) | M31: =IF(G31="","",IF(YEAR(G31)=Config!$B$4,MONTH(G31),"")) | N31: =IF(J31="Pago",IF(H31<>"",H31,L31),"") | O31: =IF(J31="Vencido",ROW(),"")
A32: {=IF(OR(Alunos!$A$4="",6<IF(Alunos!$M$4="",1,MATCH(Alunos!$M$4,{"Jan";"Fev";"Mar";"Abr";"Mai";"Jun";"Jul";"Ago";"Set";"Out";"Nov";"Dez"},0)),6>IF(Alunos!$N$4="",12,MATCH(Alunos!$N$4,{"Jan";"Fev";"Mar";"Abr";"Mai";"Jun";"Jul";"Ago";"Set";"Out";"Nov";"Dez"},0))),"",Alunos!$A$4)} | B32: =IF(OR(A32="",Alunos!$C$4=""),"",Alunos!$C$4) | C32: =IF(A32="","","Jun") | D32: =IF(OR(A32="",Config!$B$5=""),"",DATE(Config!$B$4,6,Config!$B$5)) | E32: =IF(OR(A32="",Alunos!$K$4=""),"",Alunos!$K$4) | F32: BOL-202606-003 | G32: 46198 | J32: =IF(OR(A32="",E32=""),"",IF(I32="Sim","Cancelado",IF(G32<>"","Pago",IF(D32="","A vencer",IF(TODAY()>D32,"Vencido","A vencer"))))) | K32: =IF(J32="Pago",IF(D32="",0,MAX(0,G32-D32)),IF(J32="Vencido",TODAY()-D32,"")) | L32: =IF(OR(J32="",J32="Cancelado"),"",IF(N(K32)>0,E32*(1+N(Config!$B$6))+E32*N(Config!$B$7)/30*K32,E32)) | M32: =IF(G32="","",IF(YEAR(G32)=Config!$B$4,MONTH(G32),"")) | N32: =IF(J32="Pago",IF(H32<>"",H32,L32),"") | O32: =IF(J32="Vencido",ROW(),"")
A33: {=IF(OR(Alunos!$A$4="",7<IF(Alunos!$M$4="",1,MATCH(Alunos!$M$4,{"Jan";"Fev";"Mar";"Abr";"Mai";"Jun";"Jul";"Ago";"Set";"Out";"Nov";"Dez"},0)),7>IF(Alunos!$N$4="",12,MATCH(Alunos!$N$4,{"Jan";"Fev";"Mar";"Abr";"Mai";"Jun";"Jul";"Ago";"Set";"Out";"Nov";"Dez"},0))),"",Alunos!$A$4)} | B33: =IF(OR(A33="",Alunos!$C$4=""),"",Alunos!$C$4) | C33: =IF(A33="","","Jul") | D33: =IF(OR(A33="",Config!$B$5=""),"",DATE(Config!$B$4,7,Config!$B$5)) | E33: =IF(OR(A33="",Alunos!$K$4=""),"",Alunos!$K$4) | F33: BOL-202607-003 | G33: 46228 | J33: =IF(OR(A33="",E33=""),"",IF(I33="Sim","Cancelado",IF(G33<>"","Pago",IF(D33="","A vencer",IF(TODAY()>D33,"Vencido","A vencer"))))) | K33: =IF(J33="Pago",IF(D33="",0,MAX(0,G33-D33)),IF(J33="Vencido",TODAY()-D33,"")) | L33: =IF(OR(J33="",J33="Cancelado"),"",IF(N(K33)>0,E33*(1+N(Config!$B$6))+E33*N(Config!$B$7)/30*K33,E33)) | M33: =IF(G33="","",IF(YEAR(G33)=Config!$B$4,MONTH(G33),"")) | N33: =IF(J33="Pago",IF(H33<>"",H33,L33),"") | O33: =IF(J33="Vencido",ROW(),"")
A34: {=IF(OR(Alunos!$A$4="",8<IF(Alunos!$M$4="",1,MATCH(Alunos!$M$4,{"Jan";"Fev";"Mar";"Abr";"Mai";"Jun";"Jul";"Ago";"Set";"Out";"Nov";"Dez"},0)),8>IF(Alunos!$N$4="",12,MATCH(Alunos!$N$4,{"Jan";"Fev";"Mar";"Abr";"Mai";"Jun";"Jul";"Ago";"Set";"Out";"Nov";"Dez"},0))),"",Alunos!$A$4)} | B34: =IF(OR(A34="",Alunos!$C$4=""),"",Alunos!$C$4) | C34: =IF(A34="","","Ago") | D34: =IF(OR(A34="",Config!$B$5=""),"",DATE(Config!$B$4,8,Config!$B$5)) | E34: =IF(OR(A34="",Alunos!$K$4=""),"",Alunos!$K$4) | F34: BOL-202608-003 | G34: 46243 | J34: =IF(OR(A34="",E34=""),"",IF(I34="Sim","Cancelado",IF(G34<>"","Pago",IF(D34="","A vencer",IF(TODAY()>D34,"Vencido","A vencer"))))) | K34: =IF(J34="Pago",IF(D34="",0,MAX(0,G34-D34)),IF(J34="Vencido",TODAY()-D34,"")) | L34: =IF(OR(J34="",J34="Cancelado"),"",IF(N(K34)>0,E34*(1+N(Config!$B$6))+E34*N(Config!$B$7)/30*K34,E34)) | M34: =IF(G34="","",IF(YEAR(G34)=Config!$B$4,MONTH(G34),"")) | N34: =IF(J34="Pago",IF(H34<>"",H34,L34),"") | O34: =IF(J34="Vencido",ROW(),"")
A35: {=IF(OR(Alunos!$A$4="",9<IF(Alunos!$M$4="",1,MATCH(Alunos!$M$4,{"Jan";"Fev";"Mar";"Abr";"Mai";"Jun";"Jul";"Ago";"Set";"Out";"Nov";"Dez"},0)),9>IF(Alunos!$N$4="",12,MATCH(Alunos!$N$4,{"Jan";"Fev";"Mar";"Abr";"Mai";"Jun";"Jul";"Ago";"Set";"Out";"Nov";"Dez"},0))),"",Alunos!$A$4)} | B35: =IF(OR(A35="",Alunos!$C$4=""),"",Alunos!$C$4) | C35: =IF(A35="","","Set") | D35: =IF(OR(A35="",Config!$B$5=""),"",DATE(Config!$B$4,9,Config!$B$5)) | E35: =IF(OR(A35="",Alunos!$K$4=""),"",Alunos!$K$4) | F35: BOL-202609-003 | G35: 46272 | J35: =IF(OR(A35="",E35=""),"",IF(I35="Sim","Cancelado",IF(G35<>"","Pago",IF(D35="","A vencer",IF(TODAY()>D35,"Vencido","A vencer"))))) | K35: =IF(J35="Pago",IF(D35="",0,MAX(0,G35-D35)),IF(J35="Vencido",TODAY()-D35,"")) | L35: =IF(OR(J35="",J35="Cancelado"),"",IF(N(K35)>0,E35*(1+N(Config!$B$6))+E35*N(Config!$B$7)/30*K35,E35)) | M35: =IF(G35="","",IF(YEAR(G35)=Config!$B$4,MONTH(G35),"")) | N35: =IF(J35="Pago",IF(H35<>"",H35,L35),"") | O35: =IF(J35="Vencido",ROW(),"")
A36: {=IF(OR(Alunos!$A$4="",10<IF(Alunos!$M$4="",1,MATCH(Alunos!$M$4,{"Jan";"Fev";"Mar";"Abr";"Mai";"Jun";"Jul";"Ago";"Set";"Out";"Nov";"Dez"},0)),10>IF(Alunos!$N$4="",12,MATCH(Alunos!$N$4,{"Jan";"Fev";"Mar";"Abr";"Mai";"Jun";"Jul";"Ago";"Set";"Out";"Nov";"Dez"},0))),"",Alunos!$A$4)} | B36: =IF(OR(A36="",Alunos!$C$4=""),"",Alunos!$C$4) | C36: =IF(A36="","","Out") | D36: =IF(OR(A36="",Config!$B$5=""),"",DATE(Config!$B$4,10,Config!$B$5)) | E36: =IF(OR(A36="",Alunos!$K$4=""),"",Alunos!$K$4) | F36: BOL-202610-003 | G36: 46304 | J36: =IF(OR(A36="",E36=""),"",IF(I36="Sim","Cancelado",IF(G36<>"","Pago",IF(D36="","A vencer",IF(TODAY()>D36,"Vencido","A vencer"))))) | K36: =IF(J36="Pago",IF(D36="",0,MAX(0,G36-D36)),IF(J36="Vencido",TODAY()-D36,"")) | L36: =IF(OR(J36="",J36="Cancelado"),"",IF(N(K36)>0,E36*(1+N(Config!$B$6))+E36*N(Config!$B$7)/30*K36,E36)) | M36: =IF(G36="","",IF(YEAR(G36)=Config!$B$4,MONTH(G36),"")) | N36: =IF(J36="Pago",IF(H36<>"",H36,L36),"") | O36: =IF(J36="Vencido",ROW(),"")
A37: {=IF(OR(Alunos!$A$4="",11<IF(Alunos!$M$4="",1,MATCH(Alunos!$M$4,{"Jan";"Fev";"Mar";"Abr";"Mai";"Jun";"Jul";"Ago";"Set";"Out";"Nov";"Dez"},0)),11>IF(Alunos!$N$4="",12,MATCH(Alunos!$N$4,{"Jan";"Fev";"Mar";"Abr";"Mai";"Jun";"Jul";"Ago";"Set";"Out";"Nov";"Dez"},0))),"",Alunos!$A$4)} | B37: =IF(OR(A37="",Alunos!$C$4=""),"",Alunos!$C$4) | C37: =IF(A37="","","Nov") | D37: =IF(OR(A37="",Config!$B$5=""),"",DATE(Config!$B$4,11,Config!$B$5)) | E37: =IF(OR(A37="",Alunos!$K$4=""),"",Alunos!$K$4) | J37: =IF(OR(A37="",E37=""),"",IF(I37="Sim","Cancelado",IF(G37<>"","Pago",IF(D37="","A vencer",IF(TODAY()>D37,"Vencido","A vencer"))))) | K37: =IF(J37="Pago",IF(D37="",0,MAX(0,G37-D37)),IF(J37="Vencido",TODAY()-D37,"")) | L37: =IF(OR(J37="",J37="Cancelado"),"",IF(N(K37)>0,E37*(1+N(Config!$B$6))+E37*N(Config!$B$7)/30*K37,E37)) | M37: =IF(G37="","",IF(YEAR(G37)=Config!$B$4,MONTH(G37),"")) | N37: =IF(J37="Pago",IF(H37<>"",H37,L37),"") | O37: =IF(J37="Vencido",ROW(),"")
A38: {=IF(OR(Alunos!$A$4="",12<IF(Alunos!$M$4="",1,MATCH(Alunos!$M$4,{"Jan";"Fev";"Mar";"Abr";"Mai";"Jun";"Jul";"Ago";"Set";"Out";"Nov";"Dez"},0)),12>IF(Alunos!$N$4="",12,MATCH(Alunos!$N$4,{"Jan";"Fev";"Mar";"Abr";"Mai";"Jun";"Jul";"Ago";"Set";"Out";"Nov";"Dez"},0))),"",Alunos!$A$4)} | B38: =IF(OR(A38="",Alunos!$C$4=""),"",Alunos!$C$4) | C38: =IF(A38="","","Dez") | D38: =IF(OR(A38="",Config!$B$5=""),"",DATE(Config!$B$4,12,Config!$B$5)) | E38: =IF(OR(A38="",Alunos!$K$4=""),"",Alunos!$K$4) | J38: =IF(OR(A38="",E38=""),"",IF(I38="Sim","Cancelado",IF(G38<>"","Pago",IF(D38="","A vencer",IF(TODAY()>D38,"Vencido","A vencer"))))) | K38: =IF(J38="Pago",IF(D38="",0,MAX(0,G38-D38)),IF(J38="Vencido",TODAY()-D38,"")) | L38: =IF(OR(J38="",J38="Cancelado"),"",IF(N(K38)>0,E38*(1+N(Config!$B$6))+E38*N(Config!$B$7)/30*K38,E38)) | M38: =IF(G38="","",IF(YEAR(G38)=Config!$B$4,MONTH(G38),"")) | N38: =IF(J38="Pago",IF(H38<>"",H38,L38),"") | O38: =IF(J38="Vencido",ROW(),"")
A39: {=IF(OR(Alunos!$A$5="",1<IF(Alunos!$M$5="",1,MATCH(Alunos!$M$5,{"Jan";"Fev";"Mar";"Abr";"Mai";"Jun";"Jul";"Ago";"Set";"Out";"Nov";"Dez"},0)),1>IF(Alunos!$N$5="",12,MATCH(Alunos!$N$5,{"Jan";"Fev";"Mar";"Abr";"Mai";"Jun";"Jul";"Ago";"Set";"Out";"Nov";"Dez"},0))),"",Alunos!$A$5)} | B39: =IF(OR(A39="",Alunos!$C$5=""),"",Alunos!$C$5) | C39: =IF(A39="","","Jan") | D39: =IF(OR(A39="",Config!$B$5=""),"",DATE(Config!$B$4,1,Config!$B$5)) | E39: =IF(OR(A39="",Alunos!$K$5=""),"",Alunos!$K$5) | F39: BOL-202601-004 | G39: 46028 | J39: =IF(OR(A39="",E39=""),"",IF(I39="Sim","Cancelado",IF(G39<>"","Pago",IF(D39="","A vencer",IF(TODAY()>D39,"Vencido","A vencer"))))) | K39: =IF(J39="Pago",IF(D39="",0,MAX(0,G39-D39)),IF(J39="Vencido",TODAY()-D39,"")) | L39: =IF(OR(J39="",J39="Cancelado"),"",IF(N(K39)>0,E39*(1+N(Config!$B$6))+E39*N(Config!$B$7)/30*K39,E39)) | M39: =IF(G39="","",IF(YEAR(G39)=Config!$B$4,MONTH(G39),"")) | N39: =IF(J39="Pago",IF(H39<>"",H39,L39),"") | O39: =IF(J39="Vencido",ROW(),"")
A40: {=IF(OR(Alunos!$A$5="",2<IF(Alunos!$M$5="",1,MATCH(Alunos!$M$5,{"Jan";"Fev";"Mar";"Abr";"Mai";"Jun";"Jul";"Ago";"Set";"Out";"Nov";"Dez"},0)),2>IF(Alunos!$N$5="",12,MATCH(Alunos!$N$5,{"Jan";"Fev";"Mar";"Abr";"Mai";"Jun";"Jul";"Ago";"Set";"Out";"Nov";"Dez"},0))),"",Alunos!$A$5)} | B40: =IF(OR(A40="",Alunos!$C$5=""),"",Alunos!$C$5) | C40: =IF(A40="","","Fev") | D40: =IF(OR(A40="",Config!$B$5=""),"",DATE(Config!$B$4,2,Config!$B$5)) | E40: =IF(OR(A40="",Alunos!$K$5=""),"",Alunos!$K$5) | F40: BOL-202602-004 | G40: 46070 | J40: =IF(OR(A40="",E40=""),"",IF(I40="Sim","Cancelado",IF(G40<>"","Pago",IF(D40="","A vencer",IF(TODAY()>D40,"Vencido","A vencer"))))) | K40: =IF(J40="Pago",IF(D40="",0,MAX(0,G40-D40)),IF(J40="Vencido",TODAY()-D40,"")) | L40: =IF(OR(J40="",J40="Cancelado"),"",IF(N(K40)>0,E40*(1+N(Config!$B$6))+E40*N(Config!$B$7)/30*K40,E40)) | M40: =IF(G40="","",IF(YEAR(G40)=Config!$B$4,MONTH(G40),"")) | N40: =IF(J40="Pago",IF(H40<>"",H40,L40),"") | O40: =IF(J40="Vencido",ROW(),"")
A41: {=IF(OR(Alunos!$A$5="",3<IF(Alunos!$M$5="",1,MATCH(Alunos!$M$5,{"Jan";"Fev";"Mar";"Abr";"Mai";"Jun";"Jul";"Ago";"Set";"Out";"Nov";"Dez"},0)),3>IF(Alunos!$N$5="",12,MATCH(Alunos!$N$5,{"Jan";"Fev";"Mar";"Abr";"Mai";"Jun";"Jul";"Ago";"Set";"Out";"Nov";"Dez"},0))),"",Alunos!$A$5)} | B41: =IF(OR(A41="",Alunos!$C$5=""),"",Alunos!$C$5) | C41: =IF(A41="","","Mar") | D41: =IF(OR(A41="",Config!$B$5=""),"",DATE(Config!$B$4,3,Config!$B$5)) | E41: =IF(OR(A41="",Alunos!$K$5=""),"",Alunos!$K$5) | F41: BOL-202603-004 | G41: 46086 | J41: =IF(OR(A41="",E41=""),"",IF(I41="Sim","Cancelado",IF(G41<>"","Pago",IF(D41="","A vencer",IF(TODAY()>D41,"Vencido","A vencer"))))) | K41: =IF(J41="Pago",IF(D41="",0,MAX(0,G41-D41)),IF(J41="Vencido",TODAY()-D41,"")) | L41: =IF(OR(J41="",J41="Cancelado"),"",IF(N(K41)>0,E41*(1+N(Config!$B$6))+E41*N(Config!$B$7)/30*K41,E41)) | M41: =IF(G41="","",IF(YEAR(G41)=Config!$B$4,MONTH(G41),"")) | N41: =IF(J41="Pago",IF(H41<>"",H41,L41),"") | O41: =IF(J41="Vencido",ROW(),"")
A42: {=IF(OR(Alunos!$A$5="",4<IF(Alunos!$M$5="",1,MATCH(Alunos!$M$5,{"Jan";"Fev";"Mar";"Abr";"Mai";"Jun";"Jul";"Ago";"Set";"Out";"Nov";"Dez"},0)),4>IF(Alunos!$N$5="",12,MATCH(Alunos!$N$5,{"Jan";"Fev";"Mar";"Abr";"Mai";"Jun";"Jul";"Ago";"Set";"Out";"Nov";"Dez"},0))),"",Alunos!$A$5)} | B42: =IF(OR(A42="",Alunos!$C$5=""),"",Alunos!$C$5) | C42: =IF(A42="","","Abr") | D42: =IF(OR(A42="",Config!$B$5=""),"",DATE(Config!$B$4,4,Config!$B$5)) | E42: =IF(OR(A42="",Alunos!$K$5=""),"",Alunos!$K$5) | F42: BOL-202604-004 | G42: 46117 | J42: =IF(OR(A42="",E42=""),"",IF(I42="Sim","Cancelado",IF(G42<>"","Pago",IF(D42="","A vencer",IF(TODAY()>D42,"Vencido","A vencer"))))) | K42: =IF(J42="Pago",IF(D42="",0,MAX(0,G42-D42)),IF(J42="Vencido",TODAY()-D42,"")) | L42: =IF(OR(J42="",J42="Cancelado"),"",IF(N(K42)>0,E42*(1+N(Config!$B$6))+E42*N(Config!$B$7)/30*K42,E42)) | M42: =IF(G42="","",IF(YEAR(G42)=Config!$B$4,MONTH(G42),"")) | N42: =IF(J42="Pago",IF(H42<>"",H42,L42),"") | O42: =IF(J42="Vencido",ROW(),"")
A43: {=IF(OR(Alunos!$A$5="",5<IF(Alunos!$M$5="",1,MATCH(Alunos!$M$5,{"Jan";"Fev";"Mar";"Abr";"Mai";"Jun";"Jul";"Ago";"Set";"Out";"Nov";"Dez"},0)),5>IF(Alunos!$N$5="",12,MATCH(Alunos!$N$5,{"Jan";"Fev";"Mar";"Abr";"Mai";"Jun";"Jul";"Ago";"Set";"Out";"Nov";"Dez"},0))),"",Alunos!$A$5)} | B43: =IF(OR(A43="",Alunos!$C$5=""),"",Alunos!$C$5) | C43: =IF(A43="","","Mai") | D43: =IF(OR(A43="",Config!$B$5=""),"",DATE(Config!$B$4,5,Config!$B$5)) | E43: =IF(OR(A43="",Alunos!$K$5=""),"",Alunos!$K$5) | F43: BOL-202605-004 | G43: 46147 | J43: =IF(OR(A43="",E43=""),"",IF(I43="Sim","Cancelado",IF(G43<>"","Pago",IF(D43="","A vencer",IF(TODAY()>D43,"Vencido","A vencer"))))) | K43: =IF(J43="Pago",IF(D43="",0,MAX(0,G43-D43)),IF(J43="Vencido",TODAY()-D43,"")) | L43: =IF(OR(J43="",J43="Cancelado"),"",IF(N(K43)>0,E43*(1+N(Config!$B$6))+E43*N(Config!$B$7)/30*K43,E43)) | M43: =IF(G43="","",IF(YEAR(G43)=Config!$B$4,MONTH(G43),"")) | N43: =IF(J43="Pago",IF(H43<>"",H43,L43),"") | O43: =IF(J43="Vencido",ROW(),"")
A44: {=IF(OR(Alunos!$A$5="",6<IF(Alunos!$M$5="",1,MATCH(Alunos!$M$5,{"Jan";"Fev";"Mar";"Abr";"Mai";"Jun";"Jul";"Ago";"Set";"Out";"Nov";"Dez"},0)),6>IF(Alunos!$N$5="",12,MATCH(Alunos!$N$5,{"Jan";"Fev";"Mar";"Abr";"Mai";"Jun";"Jul";"Ago";"Set";"Out";"Nov";"Dez"},0))),"",Alunos!$A$5)} | B44: =IF(OR(A44="",Alunos!$C$5=""),"",Alunos!$C$5) | C44: =IF(A44="","","Jun") | D44: =IF(OR(A44="",Config!$B$5=""),"",DATE(Config!$B$4,6,Config!$B$5)) | E44: =IF(OR(A44="",Alunos!$K$5=""),"",Alunos!$K$5) | F44: BOL-202606-004 | G44: 46180 | J44: =IF(OR(A44="",E44=""),"",IF(I44="Sim","Cancelado",IF(G44<>"","Pago",IF(D44="","A vencer",IF(TODAY()>D44,"Vencido","A vencer"))))) | K44: =IF(J44="Pago",IF(D44="",0,MAX(0,G44-D44)),IF(J44="Vencido",TODAY()-D44,"")) | L44: =IF(OR(J44="",J44="Cancelado"),"",IF(N(K44)>0,E44*(1+N(Config!$B$6))+E44*N(Config!$B$7)/30*K44,E44)) | M44: =IF(G44="","",IF(YEAR(G44)=Config!$B$4,MONTH(G44),"")) | N44: =IF(J44="Pago",IF(H44<>"",H44,L44),"") | O44: =IF(J44="Vencido",ROW(),"")
A45: {=IF(OR(Alunos!$A$5="",7<IF(Alunos!$M$5="",1,MATCH(Alunos!$M$5,{"Jan";"Fev";"Mar";"Abr";"Mai";"Jun";"Jul";"Ago";"Set";"Out";"Nov";"Dez"},0)),7>IF(Alunos!$N$5="",12,MATCH(Alunos!$N$5,{"Jan";"Fev";"Mar";"Abr";"Mai";"Jun";"Jul";"Ago";"Set";"Out";"Nov";"Dez"},0))),"",Alunos!$A$5)} | B45: =IF(OR(A45="",Alunos!$C$5=""),"",Alunos!$C$5) | C45: =IF(A45="","","Jul") | D45: =IF(OR(A45="",Config!$B$5=""),"",DATE(Config!$B$4,7,Config!$B$5)) | E45: =IF(OR(A45="",Alunos!$K$5=""),"",Alunos!$K$5) | F45: BOL-202607-004 | G45: 46220 | J45: =IF(OR(A45="",E45=""),"",IF(I45="Sim","Cancelado",IF(G45<>"","Pago",IF(D45="","A vencer",IF(TODAY()>D45,"Vencido","A vencer"))))) | K45: =IF(J45="Pago",IF(D45="",0,MAX(0,G45-D45)),IF(J45="Vencido",TODAY()-D45,"")) | L45: =IF(OR(J45="",J45="Cancelado"),"",IF(N(K45)>0,E45*(1+N(Config!$B$6))+E45*N(Config!$B$7)/30*K45,E45)) | M45: =IF(G45="","",IF(YEAR(G45)=Config!$B$4,MONTH(G45),"")) | N45: =IF(J45="Pago",IF(H45<>"",H45,L45),"") | O45: =IF(J45="Vencido",ROW(),"")
A46: {=IF(OR(Alunos!$A$5="",8<IF(Alunos!$M$5="",1,MATCH(Alunos!$M$5,{"Jan";"Fev";"Mar";"Abr";"Mai";"Jun";"Jul";"Ago";"Set";"Out";"Nov";"Dez"},0)),8>IF(Alunos!$N$5="",12,MATCH(Alunos!$N$5,{"Jan";"Fev";"Mar";"Abr";"Mai";"Jun";"Jul";"Ago";"Set";"Out";"Nov";"Dez"},0))),"",Alunos!$A$5)} | B46: =IF(OR(A46="",Alunos!$C$5=""),"",Alunos!$C$5) | C46: =IF(A46="","","Ago") | D46: =IF(OR(A46="",Config!$B$5=""),"",DATE(Config!$B$4,8,Config!$B$5)) | E46: =IF(OR(A46="",Alunos!$K$5=""),"",Alunos!$K$5) | J46: =IF(OR(A46="",E46=""),"",IF(I46="Sim","Cancelado",IF(G46<>"","Pago",IF(D46="","A vencer",IF(TODAY()>D46,"Vencido","A vencer"))))) | K46: =IF(J46="Pago",IF(D46="",0,MAX(0,G46-D46)),IF(J46="Vencido",TODAY()-D46,"")) | L46: =IF(OR(J46="",J46="Cancelado"),"",IF(N(K46)>0,E46*(1+N(Config!$B$6))+E46*N(Config!$B$7)/30*K46,E46)) | M46: =IF(G46="","",IF(YEAR(G46)=Config!$B$4,MONTH(G46),"")) | N46: =IF(J46="Pago",IF(H46<>"",H46,L46),"") | O46: =IF(J46="Vencido",ROW(),"")
A47: {=IF(OR(Alunos!$A$5="",9<IF(Alunos!$M$5="",1,MATCH(Alunos!$M$5,{"Jan";"Fev";"Mar";"Abr";"Mai";"Jun";"Jul";"Ago";"Set";"Out";"Nov";"Dez"},0)),9>IF(Alunos!$N$5="",12,MATCH(Alunos!$N$5,{"Jan";"Fev";"Mar";"Abr";"Mai";"Jun";"Jul";"Ago";"Set";"Out";"Nov";"Dez"},0))),"",Alunos!$A$5)} | B47: =IF(OR(A47="",Alunos!$C$5=""),"",Alunos!$C$5) | C47: =IF(A47="","","Set") | D47: =IF(OR(A47="",Config!$B$5=""),"",DATE(Config!$B$4,9,Config!$B$5)) | E47: =IF(OR(A47="",Alunos!$K$5=""),"",Alunos!$K$5) | J47: =IF(OR(A47="",E47=""),"",IF(I47="Sim","Cancelado",IF(G47<>"","Pago",IF(D47="","A vencer",IF(TODAY()>D47,"Vencido","A vencer"))))) | K47: =IF(J47="Pago",IF(D47="",0,MAX(0,G47-D47)),IF(J47="Vencido",TODAY()-D47,"")) | L47: =IF(OR(J47="",J47="Cancelado"),"",IF(N(K47)>0,E47*(1+N(Config!$B$6))+E47*N(Config!$B$7)/30*K47,E47)) | M47: =IF(G47="","",IF(YEAR(G47)=Config!$B$4,MONTH(G47),"")) | N47: =IF(J47="Pago",IF(H47<>"",H47,L47),"") | O47: =IF(J47="Vencido",ROW(),"")
A48: {=IF(OR(Alunos!$A$5="",10<IF(Alunos!$M$5="",1,MATCH(Alunos!$M$5,{"Jan";"Fev";"Mar";"Abr";"Mai";"Jun";"Jul";"Ago";"Set";"Out";"Nov";"Dez"},0)),10>IF(Alunos!$N$5="",12,MATCH(Alunos!$N$5,{"Jan";"Fev";"Mar";"Abr";"Mai";"Jun";"Jul";"Ago";"Set";"Out";"Nov";"Dez"},0))),"",Alunos!$A$5)} | B48: =IF(OR(A48="",Alunos!$C$5=""),"",Alunos!$C$5) | C48: =IF(A48="","","Out") | D48: =IF(OR(A48="",Config!$B$5=""),"",DATE(Config!$B$4,10,Config!$B$5)) | E48: =IF(OR(A48="",Alunos!$K$5=""),"",Alunos!$K$5) | J48: =IF(OR(A48="",E48=""),"",IF(I48="Sim","Cancelado",IF(G48<>"","Pago",IF(D48="","A vencer",IF(TODAY()>D48,"Vencido","A vencer"))))) | K48: =IF(J48="Pago",IF(D48="",0,MAX(0,G48-D48)),IF(J48="Vencido",TODAY()-D48,"")) | L48: =IF(OR(J48="",J48="Cancelado"),"",IF(N(K48)>0,E48*(1+N(Config!$B$6))+E48*N(Config!$B$7)/30*K48,E48)) | M48: =IF(G48="","",IF(YEAR(G48)=Config!$B$4,MONTH(G48),"")) | N48: =IF(J48="Pago",IF(H48<>"",H48,L48),"") | O48: =IF(J48="Vencido",ROW(),"")
A49: {=IF(OR(Alunos!$A$5="",11<IF(Alunos!$M$5="",1,MATCH(Alunos!$M$5,{"Jan";"Fev";"Mar";"Abr";"Mai";"Jun";"Jul";"Ago";"Set";"Out";"Nov";"Dez"},0)),11>IF(Alunos!$N$5="",12,MATCH(Alunos!$N$5,{"Jan";"Fev";"Mar";"Abr";"Mai";"Jun";"Jul";"Ago";"Set";"Out";"Nov";"Dez"},0))),"",Alunos!$A$5)} | B49: =IF(OR(A49="",Alunos!$C$5=""),"",Alunos!$C$5) | C49: =IF(A49="","","Nov") | D49: =IF(OR(A49="",Config!$B$5=""),"",DATE(Config!$B$4,11,Config!$B$5)) | E49: =IF(OR(A49="",Alunos!$K$5=""),"",Alunos!$K$5) | J49: =IF(OR(A49="",E49=""),"",IF(I49="Sim","Cancelado",IF(G49<>"","Pago",IF(D49="","A vencer",IF(TODAY()>D49,"Vencido","A vencer"))))) | K49: =IF(J49="Pago",IF(D49="",0,MAX(0,G49-D49)),IF(J49="Vencido",TODAY()-D49,"")) | L49: =IF(OR(J49="",J49="Cancelado"),"",IF(N(K49)>0,E49*(1+N(Config!$B$6))+E49*N(Config!$B$7)/30*K49,E49)) | M49: =IF(G49="","",IF(YEAR(G49)=Config!$B$4,MONTH(G49),"")) | N49: =IF(J49="Pago",IF(H49<>"",H49,L49),"") | O49: =IF(J49="Vencido",ROW(),"")
A50: {=IF(OR(Alunos!$A$5="",12<IF(Alunos!$M$5="",1,MATCH(Alunos!$M$5,{"Jan";"Fev";"Mar";"Abr";"Mai";"Jun";"Jul";"Ago";"Set";"Out";"Nov";"Dez"},0)),12>IF(Alunos!$N$5="",12,MATCH(Alunos!$N$5,{"Jan";"Fev";"Mar";"Abr";"Mai";"Jun";"Jul";"Ago";"Set";"Out";"Nov";"Dez"},0))),"",Alunos!$A$5)} | B50: =IF(OR(A50="",Alunos!$C$5=""),"",Alunos!$C$5) | C50: =IF(A50="","","Dez") | D50: =IF(OR(A50="",Config!$B$5=""),"",DATE(Config!$B$4,12,Config!$B$5)) | E50: =IF(OR(A50="",Alunos!$K$5=""),"",Alunos!$K$5) | J50: =IF(OR(A50="",E50=""),"",IF(I50="Sim","Cancelado",IF(G50<>"","Pago",IF(D50="","A vencer",IF(TODAY()>D50,"Vencido","A vencer"))))) | K50: =IF(J50="Pago",IF(D50="",0,MAX(0,G50-D50)),IF(J50="Vencido",TODAY()-D50,"")) | L50: =IF(OR(J50="",J50="Cancelado"),"",IF(N(K50)>0,E50*(1+N(Config!$B$6))+E50*N(Config!$B$7)/30*K50,E50)) | M50: =IF(G50="","",IF(YEAR(G50)=Config!$B$4,MONTH(G50),"")) | N50: =IF(J50="Pago",IF(H50<>"",H50,L50),"") | O50: =IF(J50="Vencido",ROW(),"")
A51: {=IF(OR(Alunos!$A$6="",1<IF(Alunos!$M$6="",1,MATCH(Alunos!$M$6,{"Jan";"Fev";"Mar";"Abr";"Mai";"Jun";"Jul";"Ago";"Set";"Out";"Nov";"Dez"},0)),1>IF(Alunos!$N$6="",12,MATCH(Alunos!$N$6,{"Jan";"Fev";"Mar";"Abr";"Mai";"Jun";"Jul";"Ago";"Set";"Out";"Nov";"Dez"},0))),"",Alunos!$A$6)} | B51: =IF(OR(A51="",Alunos!$C$6=""),"",Alunos!$C$6) | C51: =IF(A51="","","Jan") | D51: =IF(OR(A51="",Config!$B$5=""),"",DATE(Config!$B$4,1,Config!$B$5)) | E51: =IF(OR(A51="",Alunos!$K$6=""),"",Alunos!$K$6) | F51: BOL-202601-005 | G51: 46039 | J51: =IF(OR(A51="",E51=""),"",IF(I51="Sim","Cancelado",IF(G51<>"","Pago",IF(D51="","A vencer",IF(TODAY()>D51,"Vencido","A vencer"))))) | K51: =IF(J51="Pago",IF(D51="",0,MAX(0,G51-D51)),IF(J51="Vencido",TODAY()-D51,"")) | L51: =IF(OR(J51="",J51="Cancelado"),"",IF(N(K51)>0,E51*(1+N(Config!$B$6))+E51*N(Config!$B$7)/30*K51,E51)) | M51: =IF(G51="","",IF(YEAR(G51)=Config!$B$4,MONTH(G51),"")) | N51: =IF(J51="Pago",IF(H51<>"",H51,L51),"") | O51: =IF(J51="Vencido",ROW(),"")
A52: {=IF(OR(Alunos!$A$6="",2<IF(Alunos!$M$6="",1,MATCH(Alunos!$M$6,{"Jan";"Fev";"Mar";"Abr";"Mai";"Jun";"Jul";"Ago";"Set";"Out";"Nov";"Dez"},0)),2>IF(Alunos!$N$6="",12,MATCH(Alunos!$N$6,{"Jan";"Fev";"Mar";"Abr";"Mai";"Jun";"Jul";"Ago";"Set";"Out";"Nov";"Dez"},0))),"",Alunos!$A$6)} | B52: =IF(OR(A52="",Alunos!$C$6=""),"",Alunos!$C$6) | C52: =IF(A52="","","Fev") | D52: =IF(OR(A52="",Config!$B$5=""),"",DATE(Config!$B$4,2,Config!$B$5)) | E52: =IF(OR(A52="",Alunos!$K$6=""),"",Alunos!$K$6) | F52: BOL-202602-005 | G52: 46062 | J52: =IF(OR(A52="",E52=""),"",IF(I52="Sim","Cancelado",IF(G52<>"","Pago",IF(D52="","A vencer",IF(TODAY()>D52,"Vencido","A vencer"))))) | K52: =IF(J52="Pago",IF(D52="",0,MAX(0,G52-D52)),IF(J52="Vencido",TODAY()-D52,"")) | L52: =IF(OR(J52="",J52="Cancelado"),"",IF(N(K52)>0,E52*(1+N(Config!$B$6))+E52*N(Config!$B$7)/30*K52,E52)) | M52: =IF(G52="","",IF(YEAR(G52)=Config!$B$4,MONTH(G52),"")) | N52: =IF(J52="Pago",IF(H52<>"",H52,L52),"") | O52: =IF(J52="Vencido",ROW(),"")
A53: {=IF(OR(Alunos!$A$6="",3<IF(Alunos!$M$6="",1,MATCH(Alunos!$M$6,{"Jan";"Fev";"Mar";"Abr";"Mai";"Jun";"Jul";"Ago";"Set";"Out";"Nov";"Dez"},0)),3>IF(Alunos!$N$6="",12,MATCH(Alunos!$N$6,{"Jan";"Fev";"Mar";"Abr";"Mai";"Jun";"Jul";"Ago";"Set";"Out";"Nov";"Dez"},0))),"",Alunos!$A$6)} | B53: =IF(OR(A53="",Alunos!$C$6=""),"",Alunos!$C$6) | C53: =IF(A53="","","Mar") | D53: =IF(OR(A53="",Config!$B$5=""),"",DATE(Config!$B$4,3,Config!$B$5)) | E53: =IF(OR(A53="",Alunos!$K$6=""),"",Alunos!$K$6) | F53: BOL-202603-005 | G53: 46086 | J53: =IF(OR(A53="",E53=""),"",IF(I53="Sim","Cancelado",IF(G53<>"","Pago",IF(D53="","A vencer",IF(TODAY()>D53,"Vencido","A vencer"))))) | K53: =IF(J53="Pago",IF(D53="",0,MAX(0,G53-D53)),IF(J53="Vencido",TODAY()-D53,"")) | L53: =IF(OR(J53="",J53="Cancelado"),"",IF(N(K53)>0,E53*(1+N(Config!$B$6))+E53*N(Config!$B$7)/30*K53,E53)) | M53: =IF(G53="","",IF(YEAR(G53)=Config!$B$4,MONTH(G53),"")) | N53: =IF(J53="Pago",IF(H53<>"",H53,L53),"") | O53: =IF(J53="Vencido",ROW(),"")
A54: {=IF(OR(Alunos!$A$6="",4<IF(Alunos!$M$6="",1,MATCH(Alunos!$M$6,{"Jan";"Fev";"Mar";"Abr";"Mai";"Jun";"Jul";"Ago";"Set";"Out";"Nov";"Dez"},0)),4>IF(Alunos!$N$6="",12,MATCH(Alunos!$N$6,{"Jan";"Fev";"Mar";"Abr";"Mai";"Jun";"Jul";"Ago";"Set";"Out";"Nov";"Dez"},0))),"",Alunos!$A$6)} | B54: =IF(OR(A54="",Alunos!$C$6=""),"",Alunos!$C$6) | C54: =IF(A54="","","Abr") | D54: =IF(OR(A54="",Config!$B$5=""),"",DATE(Config!$B$4,4,Config!$B$5)) | E54: =IF(OR(A54="",Alunos!$K$6=""),"",Alunos!$K$6) | F54: BOL-202604-005 | G54: 46116 | J54: =IF(OR(A54="",E54=""),"",IF(I54="Sim","Cancelado",IF(G54<>"","Pago",IF(D54="","A vencer",IF(TODAY()>D54,"Vencido","A vencer"))))) | K54: =IF(J54="Pago",IF(D54="",0,MAX(0,G54-D54)),IF(J54="Vencido",TODAY()-D54,"")) | L54: =IF(OR(J54="",J54="Cancelado"),"",IF(N(K54)>0,E54*(1+N(Config!$B$6))+E54*N(Config!$B$7)/30*K54,E54)) | M54: =IF(G54="","",IF(YEAR(G54)=Config!$B$4,MONTH(G54),"")) | N54: =IF(J54="Pago",IF(H54<>"",H54,L54),"") | O54: =IF(J54="Vencido",ROW(),"")
A55: {=IF(OR(Alunos!$A$6="",5<IF(Alunos!$M$6="",1,MATCH(Alunos!$M$6,{"Jan";"Fev";"Mar";"Abr";"Mai";"Jun";"Jul";"Ago";"Set";"Out";"Nov";"Dez"},0)),5>IF(Alunos!$N$6="",12,MATCH(Alunos!$N$6,{"Jan";"Fev";"Mar";"Abr";"Mai";"Jun";"Jul";"Ago";"Set";"Out";"Nov";"Dez"},0))),"",Alunos!$A$6)} | B55: =IF(OR(A55="",Alunos!$C$6=""),"",Alunos!$C$6) | C55: =IF(A55="","","Mai") | D55: =IF(OR(A55="",Config!$B$5=""),"",DATE(Config!$B$4,5,Config!$B$5)) | E55: =IF(OR(A55="",Alunos!$K$6=""),"",Alunos!$K$6) | F55: BOL-202605-005 | G55: 46167 | J55: =IF(OR(A55="",E55=""),"",IF(I55="Sim","Cancelado",IF(G55<>"","Pago",IF(D55="","A vencer",IF(TODAY()>D55,"Vencido","A vencer"))))) | K55: =IF(J55="Pago",IF(D55="",0,MAX(0,G55-D55)),IF(J55="Vencido",TODAY()-D55,"")) | L55: =IF(OR(J55="",J55="Cancelado"),"",IF(N(K55)>0,E55*(1+N(Config!$B$6))+E55*N(Config!$B$7)/30*K55,E55)) | M55: =IF(G55="","",IF(YEAR(G55)=Config!$B$4,MONTH(G55),"")) | N55: =IF(J55="Pago",IF(H55<>"",H55,L55),"") | O55: =IF(J55="Vencido",ROW(),"")
